Workbook

Sheet LG
B2: LG
B4: CODIGO | C4: DESCRIPCION | D4: STOCK JUEGOS | E4: STOCK BARRAS | F4: "J" PRECIO VENTA | G4: "J"PRECIO COMPRA | H4: BARRAS | I4: "B"PRECIO VENTA | J4: "B"PRECIO COMPRA | K4: ENTRADAS JUEGOS | L4: ENTRADAS BARRAS | M4: SALIDAS JUEGOS | N4: SALIDA BARRAS | O4: CAPITAL JUEGOS | P4: CAPITAL/GANANCIA/JUEGOS | Q4: CAPITAL BARRA | R4: CAP GAN BARRAS | S4: CANTIDAD INICIAL JUEGO | T4: CANTIDAD INICIAL BARRAS | U4: PRECIO EN $ | V4: CODIGO 2 | W4: CODIGO 3
A5: 1 | B5: 1000 | C5: 32 LA -3B/3V/7-7L | D5: =(LG26V[[#This Row],[CANTIDAD INICIAL JUEGO ]]+LG26V[[#This Row],[ENTRADAS JUEGOS ]]-LG26V[[#This Row],[SALIDAS JUEGOS]]) -> 21 | E5: =(LG26V[[#This Row],[CANTIDAD INICIAL BARRAS]]+LG26V[[#This Row],[ENTRADAS BARRAS]]-LG26V[[#This Row],[SALIDA BARRAS]]) -> 1 | F5: 80 | G5: 43 | H5: 3 | I5: =(LG26V[[#This Row],["J" PRECIO VENTA ]]/LG26V[[#This Row],[BARRAS]]) -> 26.666667 | J5: =(LG26V[[#This Row],["J"PRECIO COMPRA ]]/LG26V[[#This Row],[BARRAS]]) -> 14.333333 | K5: =SUMIF(entradas26[CODIGO],LG26V[[#This Row],[CODIGO ]],entradas26[[CAN JUEGOS ]]) -> 20 | L5: =SUMIF(entradas26[CODIGO],LG26V[[#This Row],[CODIGO ]],entradas26[CAN BARRAS]) -> 0 | M5: =SUMIF(salidas26[[CODIGO ]],LG26V[[#This Row],[CODIGO ]],salidas26[[CANT JUEGOS ]]) -> 8 | N5: =SUMIF(salidas26[[CODIGO ]],LG26V[[#This Row],[CODIGO ]],salidas26[CANT BARRAS]) -> 0 | O5: =(LG26V[[#This Row],["J"PRECIO COMPRA ]]*LG26V[[#This Row],[STOCK JUEGOS]]) -> 903 | P5: =(LG26V[[#This Row],["J" PRECIO VENTA ]]*LG26V[[#This Row],[STOCK JUEGOS]]) -> 1680 | Q5: =(LG26V[[#This Row],["B"PRECIO COMPRA]]*LG26V[[#This Row],[STOCK BARRAS]]) -> 14.333333 | R5: =(LG26V[[#This Row],["B"PRECIO VENTA ]]*LG26V[[#This Row],[STOCK BARRAS]]) -> 26.666667 | S5: 9 | T5: 1 | U5: 1.8 | W5: XLM-0001
A6: 2 | B6: 1003 | C6: 32 LA -3B/3V/7-8-7L | D6: =(LG26V[[#This Row],[CANTIDAD INICIAL JUEGO ]]+LG26V[[#This Row],[ENTRADAS JUEGOS ]]-LG26V[[#This Row],[SALIDAS JUEGOS]]) -> -3 | E6: =(LG26V[[#This Row],[CANTIDAD INICIAL BARRAS]]+LG26V[[#This Row],[ENTRADAS BARRAS]]-LG26V[[#This Row],[SALIDA BARRAS]]) -> 2 | F6: 80 | G6: 30 | H6: 3 | I6: =(LG26V[[#This Row],["J" PRECIO VENTA ]]/LG26V[[#This Row],[BARRAS]]) -> 26.666667 | J6: =(LG26V[[#This Row],["J"PRECIO COMPRA ]]/LG26V[[#This Row],[BARRAS]]) -> 10 | K6: =SUMIF(entradas26[CODIGO],LG26V[[#This Row],[CODIGO ]],entradas26[[CAN JUEGOS ]]) -> 0 | L6: =SUMIF(entradas26[CODIGO],LG26V[[#This Row],[CODIGO ]],entradas26[CAN BARRAS]) -> 0 | M6: =SUMIF(salidas26[[CODIGO ]],LG26V[[#This Row],[CODIGO ]],salidas26[[CANT JUEGOS ]]) -> 10 | N6: =SUMIF(salidas26[[CODIGO ]],LG26V[[#This Row],[CODIGO ]],salidas26[CANT BARRAS]) -> 0 | O6: =(LG26V[[#This Row],["J"PRECIO COMPRA ]]*LG26V[[#This Row],[STOCK JUEGOS]]) -> -90 | P6: =(LG26V[[#This Row],["J" PRECIO VENTA ]]*LG26V[[#This Row],[STOCK JUEGOS]]) -> -240 | Q6: =(LG26V[[#This Row],["B"PRECIO COMPRA]]*LG26V[[#This Row],[STOCK BARRAS]]) -> 20 | R6: =(LG26V[[#This Row],["B"PRECIO VENTA ]]*LG26V[[#This Row],[STOCK BARRAS]]) -> 53.333333 | S6: 7 | T6: 2 | U6: 1.38 | W6: XY-0012-A2
A7: 3 | B7: 1006 | C7: 32 LA -3B/3V/8-8-8 | D7: =(LG26V[[#This Row],[CANTIDAD INICIAL JUEGO ]]+LG26V[[#This Row],[ENTRADAS JUEGOS ]]-LG26V[[#This Row],[SALIDAS JUEGOS]]) -> 31 | E7: =(LG26V[[#This Row],[CANTIDAD INICIAL BARRAS]]+LG26V[[#This Row],[ENTRADAS BARRAS]]-LG26V[[#This Row],[SALIDA BARRAS]]) -> 1 | F7: 80 | G7: 48 | H7: 3 | I7: =(LG26V[[#This Row],["J" PRECIO VENTA ]]/LG26V[[#This Row],[BARRAS]]) -> 26.666667 | J7: =(LG26V[[#This Row],["J"PRECIO COMPRA ]]/LG26V[[#This Row],[BARRAS]]) -> 16 | K7: =SUMIF(entradas26[CODIGO],LG26V[[#This Row],[CODIGO ]],entradas26[[CAN JUEGOS ]]) -> 20 | L7: =SUMIF(entradas26[CODIGO],LG26V[[#This Row],[CODIGO ]],entradas26[CAN BARRAS]) -> 0 | M7: =SUMIF(salidas26[[CODIGO ]],LG26V[[#This Row],[CODIGO ]],salidas26[[CANT JUEGOS ]]) -> 1 | N7: =SUMIF(salidas26[[CODIGO ]],LG26V[[#This Row],[CODIGO ]],salidas26[CANT BARRAS]) -> 0 | O7: =(LG26V[[#This Row],["J"PRECIO COMPRA ]]*LG26V[[#This Row],[STOCK JUEGOS]]) -> 1488 | P7: =(LG26V[[#This Row],["J" PRECIO VENTA ]]*LG26V[[#This Row],[STOCK JUEGOS]]) -> 2480 | Q7: =(LG26V[[#This Row],["B"PRECIO COMPRA]]*LG26V[[#This Row],[STOCK BARRAS]]) -> 16 | R7: =(LG26V[[#This Row],["B"PRECIO VENTA ]]*LG26V[[#This Row],[STOCK BARRAS]]) -> 26.666667 | S7: 12 | T7: 1 | U7: 1.8 | W7: XLM-0026
A8: 5 | B8: 1011 | C8: 32LK540 6L/3V /2B | D8: =(LG26V[[#This Row],[CANTIDAD INICIAL JUEGO ]]+LG26V[[#This Row],[ENTRADAS JUEGOS ]]-LG26V[[#This Row],[SALIDAS JUEGOS]]) -> 0 | E8: =(LG26V[[#This Row],[CANTIDAD INICIAL BARRAS]]+LG26V[[#This Row],[ENTRADAS BARRAS]]-LG26V[[#This Row],[SALIDA BARRAS]]) -> 0 | F8: 70 | G8: 30 | H8: 2 | I8: =(LG26V[[#This Row],["J" PRECIO VENTA ]]/LG26V[[#This Row],[BARRAS]]) -> 35 | J8: =(LG26V[[#This Row],["J"PRECIO COMPRA ]]/LG26V[[#This Row],[BARRAS]]) -> 15 | K8: =SUMIF(entradas26[CODIGO],LG26V[[#This Row],[CODIGO ]],entradas26[[CAN JUEGOS ]]) -> 0 | L8: =SUMIF(entradas26[CODIGO],LG26V[[#This Row],[CODIGO ]],entradas26[CAN BARRAS]) -> 0 | M8: =SUMIF(salidas26[[CODIGO ]],LG26V[[#This Row],[CODIGO ]],salidas26[[CANT JUEGOS ]]) -> 8 | N8: =SUMIF(salidas26[[CODIGO ]],LG26V[[#This Row],[CODIGO ]],salidas26[CANT BARRAS]) -> 0 | O8: =(LG26V[[#This Row],["J"PRECIO COMPRA ]]*LG26V[[#This Row],[STOCK JUEGOS]]) -> 0 | P8: =(LG26V[[#This Row],["J" PRECIO VENTA ]]*LG26V[[#This Row],[STOCK JUEGOS]]) -> 0 | Q8: =(LG26V[[#This Row],["B"PRECIO COMPRA]]*LG26V[[#This Row],[STOCK BARRAS]]) -> 0 | R8: =(LG26V[[#This Row],["B"PRECIO VENTA ]]*LG26V[[#This Row],[STOCK BARRAS]]) -> 0 | S8: 8 | U8: 1.3 | W8: XY-0229
A9: 6 | B9: 1012 | C9: 32LB620B-32LF620B -3B/6V/6L | D9: =(LG26V[[#This Row],[CANTIDAD INICIAL JUEGO ]]+LG26V[[#This Row],[ENTRADAS JUEGOS ]]-LG26V[[#This Row],[SALIDAS JUEGOS]]) -> 13 | E9: =(LG26V[[#This Row],[CANTIDAD INICIAL BARRAS]]+LG26V[[#This Row],[ENTRADAS BARRAS]]-LG26V[[#This Row],[SALIDA BARRAS]]) -> 0 | F9: 90 | G9: 69 | H9: 3 | I9: =(LG26V[[#This Row],["J" PRECIO VENTA ]]/LG26V[[#This Row],[BARRAS]]) -> 30 | J9: =(LG26V[[#This Row],["J"PRECIO COMPRA ]]/LG26V[[#This Row],[BARRAS]]) -> 23 | K9: =SUMIF(entradas26[CODIGO],LG26V[[#This Row],[CODIGO ]],entradas26[[CAN JUEGOS ]]) -> 0 | L9: =SUMIF(entradas26[CODIGO],LG26V[[#This Row],[CODIGO ]],entradas26[CAN BARRAS]) -> 0 | M9: =SUMIF(salidas26[[CODIGO ]],LG26V[[#This Row],[CODIGO ]],salidas26[[CANT JUEGOS ]]) -> 21 | N9: =SUMIF(salidas26[[CODIGO ]],LG26V[[#This Row],[CODIGO ]],salidas26[CANT BARRAS]) -> 0 | O9: =(LG26V[[#This Row],["J"PRECIO COMPRA ]]*LG26V[[#This Row],[STOCK JUEGOS]]) -> 897 | P9: =(LG26V[[#This Row],["J" PRECIO VENTA ]]*LG26V[[#This Row],[STOCK JUEGOS]]) -> 1170 | Q9: =(LG26V[[#This Row],["B"PRECIO COMPRA]]*LG26V[[#This Row],[STOCK BARRAS]]) -> 0 | R9: =(LG26V[[#This Row],["B"PRECIO VENTA ]]*LG26V[[#This Row],[STOCK BARRAS]]) -> 0 | S9: 34 | U9: 2.5 | W9: XLM-0269
A10: 7 | B10: 1015 | C10: 32LH500B-32LK500 3B/7L/3V | D10: =(LG26V[[#This Row],[CANTIDAD INICIAL JUEGO ]]+LG26V[[#This Row],[ENTRADAS JUEGOS ]]-LG26V[[#This Row],[SALIDAS JUEGOS]]) -> 10 | E10: =(LG26V[[#This Row],[CANTIDAD INICIAL BARRAS]]+LG26V[[#This Row],[ENTRADAS BARRAS]]-LG26V[[#This Row],[SALIDA BARRAS]]) -> 0 | F10: 80 | G10: 34.2 | H10: 3 | I10: =(LG26V[[#This Row],["J" PRECIO VENTA ]]/LG26V[[#This Row],[BARRAS]]) -> 26.666667 | J10: =(LG26V[[#This Row],["J"PRECIO COMPRA ]]/LG26V[[#This Row],[BARRAS]]) -> 11.4 | K10: =SUMIF(entradas26[CODIGO],LG26V[[#This Row],[CODIGO ]],entradas26[[CAN JUEGOS ]]) -> 20 | L10: =SUMIF(entradas26[CODIGO],LG26V[[#This Row],[CODIGO ]],entradas26[CAN BARRAS]) -> 3 | M10: =SUMIF(salidas26[[CODIGO ]],LG26V[[#This Row],[CODIGO ]],salidas26[[CANT JUEGOS ]]) -> 35 | N10: =SUMIF(salidas26[[CODIGO ]],LG26V[[#This Row],[CODIGO ]],salidas26[CANT BARRAS]) -> 5 | O10: =(LG26V[[#This Row],["J"PRECIO COMPRA ]]*LG26V[[#This Row],[STOCK JUEGOS]]) -> 342 | P10: =(LG26V[[#This Row],["J" PRECIO VENTA ]]*LG26V[[#This Row],[STOCK JUEGOS]]) -> 800 | Q10: =(LG26V[[#This Row],["B"PRECIO COMPRA]]*LG26V[[#This Row],[STOCK BARRAS]]) -> 0 | R10: =(LG26V[[#This Row],["B"PRECIO VENTA ]]*LG26V[[#This Row],[STOCK BARRAS]]) -> 0 | S10: 25 | T10: 2 | U10: 1.8 | W10: XLM-0329
A11: 8 | B11: 1018 | C11: 32 LH 5100-2B/5L | D11: =(LG26V[[#This Row],[CANTIDAD INICIAL JUEGO ]]+LG26V[[#This Row],[ENTRADAS JUEGOS ]]-LG26V[[#This Row],[SALIDAS JUEGOS]]) -> 15 | E11: =(LG26V[[#This Row],[CANTIDAD INICIAL BARRAS]]+LG26V[[#This Row],[ENTRADAS BARRAS]]-LG26V[[#This Row],[SALIDA BARRAS]]) -> 0 | F11: 80 | G11: 38 | H11: 2 | I11: =(LG26V[[#This Row],["J" PRECIO VENTA ]]/LG26V[[#This Row],[BARRAS]]) -> 40 | J11: =(LG26V[[#This Row],["J"PRECIO COMPRA ]]/LG26V[[#This Row],[BARRAS]]) -> 19 | K11: =SUMIF(entradas26[CODIGO],LG26V[[#This Row],[CODIGO ]],entradas26[[CAN JUEGOS ]]) -> 0 | L11: =SUMIF(entradas26[CODIGO],LG26V[[#This Row],[CODIGO ]],entradas26[CAN BARRAS]) -> 0 | M11: =SUMIF(salidas26[[CODIGO ]],LG26V[[#This Row],[CODIGO ]],salidas26[[CANT JUEGOS ]]) -> 3 | N11: =SUMIF(salidas26[[CODIGO ]],LG26V[[#This Row],[CODIGO ]],salidas26[CANT BARRAS]) -> 0 | O11: =(LG26V[[#This Row],["J"PRECIO COMPRA ]]*LG26V[[#This Row],[STOCK JUEGOS]]) -> 570 | P11: =(LG26V[[#This Row],["J" PRECIO VENTA ]]*LG26V[[#This Row],[STOCK JUEGOS]]) -> 1200 | Q11: =(LG26V[[#This Row],["B"PRECIO COMPRA]]*LG26V[[#This Row],[STOCK BARRAS]]) -> 0 | R11: =(LG26V[[#This Row],["B"PRECIO VENTA ]]*LG26V[[#This Row],[STOCK BARRAS]]) -> 0 | S11: 18 | U11: 1.45 | W11: XLM-270
A12: 9 | B12: 1021 | C12: 32LS3450-4B/7L POLA | D12: =(LG26V[[#This Row],[CANTIDAD INICIAL JUEGO ]]+LG26V[[#This Row],[ENTRADAS JUEGOS ]]-LG26V[[#This Row],[SALIDAS JUEGOS]]) -> 1 | E12: =(LG26V[[#This Row],[CANTIDAD INICIAL BARRAS]]+LG26V[[#This Row],[ENTRADAS BARRAS]]-LG26V[[#This Row],[SALIDA BARRAS]]) -> 0 | F12: 120 | G12: 80 | H12: 4 | I12: =(LG26V[[#This Row],["J" PRECIO VENTA ]]/LG26V[[#This Row],[BARRAS]]) -> 30 | J12: =(LG26V[[#This Row],["J"PRECIO COMPRA ]]/LG26V[[#This Row],[BARRAS]]) -> 20 | K12: =SUMIF(entradas26[CODIGO],LG26V[[#This Row],[CODIGO ]],entradas26[[CAN JUEGOS ]]) -> 0 | L12: =SUMIF(entradas26[CODIGO],LG26V[[#This Row],[CODIGO ]],entradas26[CAN BARRAS]) -> 0 | M12: =SUMIF(salidas26[[CODIGO ]],LG26V[[#This Row],[CODIGO ]],salidas26[[CANT JUEGOS ]]) -> 0 | N12: =SUMIF(salidas26[[CODIGO ]],LG26V[[#This Row],[CODIGO ]],salidas26[CANT BARRAS]) -> 0 | O12: =(LG26V[[#This Row],["J"PRECIO COMPRA ]]*LG26V[[#This Row],[STOCK JUEGOS]]) -> 80 | P12: =(LG26V[[#This Row],["J" PRECIO VENTA ]]*LG26V[[#This Row],[STOCK JUEGOS]]) -> 120 | Q12: =(LG26V[[#This Row],["B"PRECIO COMPRA]]*LG26V[[#This Row],[STOCK BARRAS]]) -> 0 | R12: =(LG26V[[#This Row],["B"PRECIO VENTA ]]*LG26V[[#This Row],[STOCK BARRAS]]) -> 0 | S12: 1
A13: 10 | B13: 1024 | C13: 32LN5100- 3B/6L-6-7-6 POLA | D13: =(LG26V[[#This Row],[CANTIDAD INICIAL JUEGO ]]+LG26V[[#This Row],[ENTRADAS JUEGOS ]]-LG26V[[#This Row],[SALIDAS JUEGOS]]) -> 18 | E13: =(LG26V[[#This Row],[CANTIDAD INICIAL BARRAS]]+LG26V[[#This Row],[ENTRADAS BARRAS]]-LG26V[[#This Row],[SALIDA BARRAS]]) -> 0 | F13: 100 | G13: 64 | H13: 3 | I13: =(LG26V[[#This Row],["J" PRECIO VENTA ]]/LG26V[[#This Row],[BARRAS]]) -> 33.333333 | J13: =(LG26V[[#This Row],["J"PRECIO COMPRA ]]/LG26V[[#This Row],[BARRAS]]) -> 21.333333 | K13: =SUMIF(entradas26[CODIGO],LG26V[[#This Row],[CODIGO ]],entradas26[[CAN JUEGOS ]]) -> 0 | L13: =SUMIF(entradas26[CODIGO],LG26V[[#This Row],[CODIGO ]],entradas26[CAN BARRAS]) -> 0 | M13: =SUMIF(salidas26[[CODIGO ]],LG26V[[#This Row],[CODIGO ]],salidas26[[CANT JUEGOS ]]) -> 4 | N13: =SUMIF(salidas26[[CODIGO ]],LG26V[[#This Row],[CODIGO ]],salidas26[CANT BARRAS]) -> 0 | O13: =(LG26V[[#This Row],["J"PRECIO COMPRA ]]*LG26V[[#This Row],[STOCK JUEGOS]]) -> 1152 | P13: =(LG26V[[#This Row],["J" PRECIO VENTA ]]*LG26V[[#This Row],[STOCK JUEGOS]]) -> 1800 | Q13: =(LG26V[[#This Row],["B"PRECIO COMPRA]]*LG26V[[#This Row],[STOCK BARRAS]]) -> 0 | R13: =(LG26V[[#This Row],["B"PRECIO VENTA ]]*LG26V[[#This Row],[STOCK BARRAS]]) -> 0 | S13: 22 | U13: 2.4 | W13: XLM-0254/0255
A14: 11 | B14: 1027 | C14: 32LM3400-4B/3V/9L | D14: =(LG26V[[#This Row],[CANTIDAD INICIAL JUEGO ]]+LG26V[[#This Row],[ENTRADAS JUEGOS ]]-LG26V[[#This Row],[SALIDAS JUEGOS]]) -> 26 | E14: =(LG26V[[#This Row],[CANTIDAD INICIAL BARRAS]]+LG26V[[#This Row],[ENTRADAS BARRAS]]-LG26V[[#This Row],[SALIDA BARRAS]]) -> 0 | F14: 120 | G14: 70 | H14: 4 | I14: =(LG26V[[#This Row],["J" PRECIO VENTA ]]/LG26V[[#This Row],[BARRAS]]) -> 30 | J14: =(LG26V[[#This Row],["J"PRECIO COMPRA ]]/LG26V[[#This Row],[BARRAS]]) -> 17.5 | K14: =SUMIF(entradas26[CODIGO],LG26V[[#This Row],[CODIGO ]],entradas26[[CAN JUEGOS ]]) -> 20 | L14: =SUMIF(entradas26[CODIGO],LG26V[[#This Row],[CODIGO ]],entradas26[CAN BARRAS]) -> 0 | M14: =SUMIF(salidas26[[CODIGO ]],LG26V[[#This Row],[CODIGO ]],salidas26[[CANT JUEGOS ]]) -> 4 | N14: =SUMIF(salidas26[[CODIGO ]],LG26V[[#This Row],[CODIGO ]],salidas26[CANT BARRAS]) -> 0 | O14: =(LG26V[[#This Row],["J"PRECIO COMPRA ]]*LG26V[[#This Row],[STOCK JUEGOS]]) -> 1820 | P14: =(LG26V[[#This Row],["J" PRECIO VENTA ]]*LG26V[[#This Row],[STOCK JUEGOS]]) -> 3120 | Q14: =(LG26V[[#This Row],["B"PRECIO COMPRA]]*LG26V[[#This Row],[STOCK BARRAS]]) -> 0 | R14: =(LG26V[[#This Row],["B"PRECIO VENTA ]]*LG26V[[#This Row],[STOCK BARRAS]]) -> 0 | S14: 10 | U14: 3.7 | W14: XLM-0103-0104
A15: 12 | B15: 1028 | C15: 29 LG/ 1B | D15: =(LG26V[[#This Row],[CANTIDAD INICIAL JUEGO ]]+LG26V[[#This Row],[ENTRADAS JUEGOS ]]-LG26V[[#This Row],[SALIDAS JUEGOS]]) -> 3 | E15: =(LG26V[[#This Row],[CANTIDAD INICIAL BARRAS]]+LG26V[[#This Row],[ENTRADAS BARRAS]]-LG26V[[#This Row],[SALIDA BARRAS]]) -> 0 | F15: 90 | G15: 50 | H15: 1 | I15: =(LG26V[[#This Row],["J" PRECIO VENTA ]]/LG26V[[#This Row],[BARRAS]]) -> 90 | J15: =(LG26V[[#This Row],["J"PRECIO COMPRA ]]/LG26V[[#This Row],[BARRAS]]) -> 50 | K15: =SUMIF(entradas26[CODIGO],LG26V[[#This Row],[CODIGO ]],entradas26[[CAN JUEGOS ]]) -> 0 | L15: =SUMIF(entradas26[CODIGO],LG26V[[#This Row],[CODIGO ]],entradas26[CAN BARRAS]) -> 0 | M15: =SUMIF(salidas26[[CODIGO ]],LG26V[[#This Row],[CODIGO ]],salidas26[[CANT JUEGOS ]]) -> 0 | N15: =SUMIF(salidas26[[CODIGO ]],LG26V[[#This Row],[CODIGO ]],salidas26[CANT BARRAS]) -> 0 | O15: =(LG26V[[#This Row],["J"PRECIO COMPRA ]]*LG26V[[#This Row],[STOCK JUEGOS]]) -> 150 | P15: =(LG26V[[#This Row],["J" PRECIO VENTA ]]*LG26V[[#This Row],[STOCK JUEGOS]]) -> 270 | Q15: =(LG26V[[#This Row],["B"PRECIO COMPRA]]*LG26V[[#This Row],[STOCK BARRAS]]) -> 0 | R15: =(LG26V[[#This Row],["B"PRECIO VENTA ]]*LG26V[[#This Row],[STOCK BARRAS]]) -> 0 | S15: 3
A16: 13 | B16: 1030 | C16: 40 LB6450/8B/6V | D16: =(LG26V[[#This Row],[CANTIDAD INICIAL JUEGO ]]+LG26V[[#This Row],[ENTRADAS JUEGOS ]]-LG26V[[#This Row],[SALIDAS JUEGOS]]) -> 9 | E16: =(LG26V[[#This Row],[CANTIDAD INICIAL BARRAS]]+LG26V[[#This Row],[ENTRADAS BARRAS]]-LG26V[[#This Row],[SALIDA BARRAS]]) -> 0 | F16: 200 | G16: 110 | H16: 8 | I16: =(LG26V[[#This Row],["J" PRECIO VENTA ]]/LG26V[[#This Row],[BARRAS]]) -> 25 | J16: =(LG26V[[#This Row],["J"PRECIO COMPRA ]]/LG26V[[#This Row],[BARRAS]]) -> 13.75 | K16: =SUMIF(entradas26[CODIGO],LG26V[[#This Row],[CODIGO ]],entradas26[[CAN JUEGOS ]]) -> 0 | L16: =SUMIF(entradas26[CODIGO],LG26V[[#This Row],[CODIGO ]],entradas26[CAN BARRAS]) -> 0 | M16: =SUMIF(salidas26[[CODIGO ]],LG26V[[#This Row],[CODIGO ]],salidas26[[CANT JUEGOS ]]) -> 0 | N16: =SUMIF(salidas26[[CODIGO ]],LG26V[[#This Row],[CODIGO ]],salidas26[CANT BARRAS]) -> 0 | O16: =(LG26V[[#This Row],["J"PRECIO COMPRA ]]*LG26V[[#This Row],[STOCK JUEGOS]]) -> 990 | P16: =(LG26V[[#This Row],["J" PRECIO VENTA ]]*LG26V[[#This Row],[STOCK JUEGOS]]) -> 1800 | Q16: =(LG26V[[#This Row],["B"PRECIO COMPRA]]*LG26V[[#This Row],[STOCK BARRAS]]) -> 0 | R16: =(LG26V[[#This Row],["B"PRECIO VENTA ]]*LG26V[[#This Row],[STOCK BARRAS]]) -> 0 | S16: 9 | U16: 5.5 | W16: XLM-0277/0278
A17: 14 | B17: 1033 | C17: 42LB6200-42LF6200 8B/6V | D17: =(LG26V[[#This Row],[CANTIDAD INICIAL JUEGO ]]+LG26V[[#This Row],[ENTRADAS JUEGOS ]]-LG26V[[#This Row],[SALIDAS JUEGOS]]) -> 18 | E17: =(LG26V[[#This Row],[CANTIDAD INICIAL BARRAS]]+LG26V[[#This Row],[ENTRADAS BARRAS]]-LG26V[[#This Row],[SALIDA BARRAS]]) -> 0 | F17: 180 | G17: 130 | H17: 8 | I17: =(LG26V[[#This Row],["J" PRECIO VENTA ]]/LG26V[[#This Row],[BARRAS]]) -> 22.5 | J17: =(LG26V[[#This Row],["J"PRECIO COMPRA ]]/LG26V[[#This Row],[BARRAS]]) -> 16.25 | K17: =SUMIF(entradas26[CODIGO],LG26V[[#This Row],[CODIGO ]],entradas26[[CAN JUEGOS ]]) -> 23 | L17: =SUMIF(entradas26[CODIGO],LG26V[[#This Row],[CODIGO ]],entradas26[CAN BARRAS]) -> 0 | M17: =SUMIF(salidas26[[CODIGO ]],LG26V[[#This Row],[CODIGO ]],salidas26[[CANT JUEGOS ]]) -> 29 | N17: =SUMIF(salidas26[[CODIGO ]],LG26V[[#This Row],[CODIGO ]],salidas26[CANT BARRAS]) -> 0 | O17: =(LG26V[[#This Row],["J"PRECIO COMPRA ]]*LG26V[[#This Row],[STOCK JUEGOS]]) -> 2340 | P17: =(LG26V[[#This Row],["J" PRECIO VENTA ]]*LG26V[[#This Row],[STOCK JUEGOS]]) -> 3240 | Q17: =(LG26V[[#This Row],["B"PRECIO COMPRA]]*LG26V[[#This Row],[STOCK BARRAS]]) -> 0 | R17: =(LG26V[[#This Row],["B"PRECIO VENTA ]]*LG26V[[#This Row],[STOCK BARRAS]]) -> 0 | S17: 24 | U17: 5.4 | W17: XLM-0250/0251
A18: 15 | B18: 1036 | C18: 42LA6130-42LN5400 10B/3V | D18: =(LG26V[[#This Row],[CANTIDAD INICIAL JUEGO ]]+LG26V[[#This Row],[ENTRADAS JUEGOS ]]-LG26V[[#This Row],[SALIDAS JUEGOS]]) -> 17 | E18: =(LG26V[[#This Row],[CANTIDAD INICIAL BARRAS]]+LG26V[[#This Row],[ENTRADAS BARRAS]]-LG26V[[#This Row],[SALIDA BARRAS]]) -> 6 | F18: 180 | G18: 96.9 | H18: 10 | I18: =(LG26V[[#This Row],["J" PRECIO VENTA ]]/LG26V[[#This Row],[BARRAS]]) -> 18 | J18: =(LG26V[[#This Row],["J"PRECIO COMPRA ]]/LG26V[[#This Row],[BARRAS]]) -> 9.69 | K18: =SUMIF(entradas26[CODIGO],LG26V[[#This Row],[CODIGO ]],entradas26[[CAN JUEGOS ]]) -> 20 | L18: =SUMIF(entradas26[CODIGO],LG26V[[#This Row],[CODIGO ]],entradas26[CAN BARRAS]) -> 0 | M18: =SUMIF(salidas26[[CODIGO ]],LG26V[[#This Row],[CODIGO ]],salidas26[[CANT JUEGOS ]]) -> 14 | N18: =SUMIF(salidas26[[CODIGO ]],LG26V[[#This Row],[CODIGO ]],salidas26[CANT BARRAS]) -> 0 | O18: =(LG26V[[#This Row],["J"PRECIO COMPRA ]]*LG26V[[#This Row],[STOCK JUEGOS]]) -> 1647.3 | P18: =(LG26V[[#This Row],["J" PRECIO VENTA ]]*LG26V[[#This Row],[STOCK JUEGOS]]) -> 3060 | Q18: =(LG26V[[#This Row],["B"PRECIO COMPRA]]*LG26V[[#This Row],[STOCK BARRAS]]) -> 58.14 | R18: =(LG26V[[#This Row],["B"PRECIO VENTA ]]*LG26V[[#This Row],[STOCK BARRAS]]) -> 108 | S18: 11 | T18: 6 | U18: 5.1 | W18: XLM-0244/0242/0245/0243
A19: 16 | B19: 1039 | C19: 42LN5200/10B/3V | D19: =(LG26V[[#This Row],[CANTIDAD INICIAL JUEGO ]]+LG26V[[#This Row],[ENTRADAS JUEGOS ]]-LG26V[[#This Row],[SALIDAS JUEGOS]]) -> 15 | E19: =(LG26V[[#This Row],[CANTIDAD INICIAL BARRAS]]+LG26V[[#This Row],[ENTRADAS BARRAS]]-LG26V[[#This Row],[SALIDA BARRAS]]) -> 16 | F19: 200 | G19: 105 | H19: 10 | I19: =(LG26V[[#This Row],["J" PRECIO VENTA ]]/LG26V[[#This Row],[BARRAS]]) -> 20 | J19: =(LG26V[[#This Row],["J"PRECIO COMPRA ]]/LG26V[[#This Row],[BARRAS]]) -> 10.5 | K19: =SUMIF(entradas26[CODIGO],LG26V[[#This Row],[CODIGO ]],entradas26[[CAN JUEGOS ]]) -> 0 | L19: =SUMIF(entradas26[CODIGO],LG26V[[#This Row],[CODIGO ]],entradas26[CAN BARRAS]) -> 0 | M19: =SUMIF(salidas26[[CODIGO ]],LG26V[[#This Row],[CODIGO ]],salidas26[[CANT JUEGOS ]]) -> 2 | N19: =SUMIF(salidas26[[CODIGO ]],LG26V[[#This Row],[CODIGO ]],salidas26[CANT BARRAS]) -> 0 | O19: =(LG26V[[#This Row],["J"PRECIO COMPRA ]]*LG26V[[#This Row],[STOCK JUEGOS]]) -> 1575 | P19: =(LG26V[[#This Row],["J" PRECIO VENTA ]]*LG26V[[#This Row],[STOCK JUEGOS]]) -> 3000 | Q19: =(LG26V[[#This Row],["B"PRECIO COMPRA]]*LG26V[[#This Row],[STOCK BARRAS]]) -> 168 | R19: =(LG26V[[#This Row],["B"PRECIO VENTA ]]*LG26V[[#This Row],[STOCK BARRAS]]) -> 320 | S19: 17 | T19: 16 | U19: 5.64 | W19: XY-014
A20: 17 | B20: 1042 | C20: 42LS3450/10B | D20: =(LG26V[[#This Row],[CANTIDAD INICIAL JUEGO ]]+LG26V[[#This Row],[ENTRADAS JUEGOS ]]-LG26V[[#This Row],[SALIDAS JUEGOS]]) -> 6 | E20: =(LG26V[[#This Row],[CANTIDAD INICIAL BARRAS]]+LG26V[[#This Row],[ENTRADAS BARRAS]]-LG26V[[#This Row],[SALIDA BARRAS]]) -> 2 | F20: 250 | G20: 245 | H20: 10 | I20: =(LG26V[[#This Row],["J" PRECIO VENTA ]]/LG26V[[#This Row],[BARRAS]]) -> 25 | J20: =(LG26V[[#This Row],["J"PRECIO COMPRA ]]/LG26V[[#This Row],[BARRAS]]) -> 24.5 | K20: =SUMIF(entradas26[CODIGO],LG26V[[#This Row],[CODIGO ]],entradas26[[CAN JUEGOS ]]) -> 0 | L20: =SUMIF(entradas26[CODIGO],LG26V[[#This Row],[CODIGO ]],entradas26[CAN BARRAS]) -> 10 | M20: =SUMIF(salidas26[[CODIGO ]],LG26V[[#This Row],[CODIGO ]],salidas26[[CANT JUEGOS ]]) -> 2 | N20: =SUMIF(salidas26[[CODIGO ]],LG26V[[#This Row],[CODIGO ]],salidas26[CANT BARRAS]) -> 8 | O20: =(LG26V[[#This Row],["J"PRECIO COMPRA ]]*LG26V[[#This Row],[STOCK JUEGOS]]) -> 1470 | P20: =(LG26V[[#This Row],["J" PRECIO VENTA ]]*LG26V[[#This Row],[STOCK JUEGOS]]) -> 1500 | Q20: =(LG26V[[#This Row],["B"PRECIO COMPRA]]*LG26V[[#This Row],[STOCK BARRAS]]) -> 49 | R20: =(LG26V[[#This Row],["B"PRECIO VENTA ]]*LG26V[[#This Row],[STOCK BARRAS]]) -> 50 | S20: 8 | U20: 7.85 | W20: XLM-1232/1233
A21: 18 | B21: 1045 | C21: 42LM6200/1B | D21: =(LG26V[[#This Row],[CANTIDAD INICIAL JUEGO ]]+LG26V[[#This Row],[ENTRADAS JUEGOS ]]-LG26V[[#This Row],[SALIDAS JUEGOS]]) -> 12 | E21: =(LG26V[[#This Row],[CANTIDAD INICIAL BARRAS]]+LG26V[[#This Row],[ENTRADAS BARRAS]]-LG26V[[#This Row],[SALIDA BARRAS]]) -> 0 | F21: 140 | G21: 30 | H21: 1 | I21: =(LG26V[[#This Row],["J" PRECIO VENTA ]]/LG26V[[#This Row],[BARRAS]]) -> 140 | J21: =(LG26V[[#This Row],["J"PRECIO COMPRA ]]/LG26V[[#This Row],[BARRAS]]) -> 30 | K21: =SUMIF(entradas26[CODIGO],LG26V[[#This Row],[CODIGO ]],entradas26[[CAN JUEGOS ]]) -> 0 | L21: =SUMIF(entradas26[CODIGO],LG26V[[#This Row],[CODIGO ]],entradas26[CAN BARRAS]) -> 0 | M21: =SUMIF(salidas26[[CODIGO ]],LG26V[[#This Row],[CODIGO ]],salidas26[[CANT JUEGOS ]]) -> 1 | N21: =SUMIF(salidas26[[CODIGO ]],LG26V[[#This Row],[CODIGO ]],salidas26[CANT BARRAS]) -> 0 | O21: =(LG26V[[#This Row],["J"PRECIO COMPRA ]]*LG26V[[#This Row],[STOCK JUEGOS]]) -> 360 | P21: =(LG26V[[#This Row],["J" PRECIO VENTA ]]*LG26V[[#This Row],[STOCK JUEGOS]]) -> 1680 | Q21: =(LG26V[[#This Row],["B"PRECIO COMPRA]]*LG26V[[#This Row],[STOCK BARRAS]]) -> 0 | R21: =(LG26V[[#This Row],["B"PRECIO VENTA ]]*LG26V[[#This Row],[STOCK BARRAS]]) -> 0 | S21: 13 | U21: 2.15 | W21: XM2746.1
A22: 19 | B22: 1048 | C22: 43 LJ5000 /10L/3V/5B | D22: =(LG26V[[#This Row],[CANTIDAD INICIAL JUEGO ]]+LG26V[[#This Row],[ENTRADAS JUEGOS ]]-LG26V[[#This Row],[SALIDAS JUEGOS]]) -> 0 | E22: =(LG26V[[#This Row],[CANTIDAD INICIAL BARRAS]]+LG26V[[#This Row],[ENTRADAS BARRAS]]-LG26V[[#This Row],[SALIDA BARRAS]]) -> 3 | F22: 180 | G22: 150 | H22: 5 | I22: =(LG26V[[#This Row],["J" PRECIO VENTA ]]/LG26V[[#This Row],[BARRAS]]) -> 36 | J22: =(LG26V[[#This Row],["J"PRECIO COMPRA ]]/LG26V[[#This Row],[BARRAS]]) -> 30 | K22: =SUMIF(entradas26[CODIGO],LG26V[[#This Row],[CODIGO ]],entradas26[[CAN JUEGOS ]]) -> 0 | L22: =SUMIF(entradas26[CODIGO],LG26V[[#This Row],[CODIGO ]],entradas26[CAN BARRAS]) -> 0 | M22: =SUMIF(salidas26[[CODIGO ]],LG26V[[#This Row],[CODIGO ]],salidas26[[CANT JUEGOS ]]) -> 0 | N22: =SUMIF(salidas26[[CODIGO ]],LG26V[[#This Row],[CODIGO ]],salidas26[CANT BARRAS]) -> 0 | O22: =(LG26V[[#This Row],["J"PRECIO COMPRA ]]*LG26V[[#This Row],[STOCK JUEGOS]]) -> 0 | P22: =(LG26V[[#This Row],["J" PRECIO VENTA ]]*LG26V[[#This Row],[STOCK JUEGOS]]) -> 0 | Q22: =(LG26V[[#This Row],["B"PRECIO COMPRA]]*LG26V[[#This Row],[STOCK BARRAS]]) -> 90 | R22: =(LG26V[[#This Row],["B"PRECIO VENTA ]]*LG26V[[#This Row],[STOCK BARRAS]]) -> 108 | T22: 3
A23: 20 | B23: 1049 | C23: 43LJ5500 3B/7L | D23: =(LG26V[[#This Row],[CANTIDAD INICIAL JUEGO ]]+LG26V[[#This Row],[ENTRADAS JUEGOS ]]-LG26V[[#This Row],[SALIDAS JUEGOS]]) -> 24 | E23: =(LG26V[[#This Row],[CANTIDAD INICIAL BARRAS]]+LG26V[[#This Row],[ENTRADAS BARRAS]]-LG26V[[#This Row],[SALIDA BARRAS]]) -> 0 | F23: 180 | G23: 65 | H23: 3 | I23: =(LG26V[[#This Row],["J" PRECIO VENTA ]]/LG26V[[#This Row],[BARRAS]]) -> 60 | J23: =(LG26V[[#This Row],["J"PRECIO COMPRA ]]/LG26V[[#This Row],[BARRAS]]) -> 21.666667 | K23: =SUMIF(entradas26[CODIGO],LG26V[[#This Row],[CODIGO ]],entradas26[[CAN JUEGOS ]]) -> 20 | L23: =SUMIF(entradas26[CODIGO],LG26V[[#This Row],[CODIGO ]],entradas26[CAN BARRAS]) -> 0 | M23: =SUMIF(salidas26[[CODIGO ]],LG26V[[#This Row],[CODIGO ]],salidas26[[CANT JUEGOS ]]) -> 6 | N23: =SUMIF(salidas26[[CODIGO ]],LG26V[[#This Row],[CODIGO ]],salidas26[CANT BARRAS]) -> 0 | O23: =(LG26V[[#This Row],["J"PRECIO COMPRA ]]*LG26V[[#This Row],[STOCK JUEGOS]]) -> 1560 | P23: =(LG26V[[#This Row],["J" PRECIO VENTA ]]*LG26V[[#This Row],[STOCK JUEGOS]]) -> 4320 | Q23: =(LG26V[[#This Row],["B"PRECIO COMPRA]]*LG26V[[#This Row],[STOCK BARRAS]]) -> 0 | R23: =(LG26V[[#This Row],["B"PRECIO VENTA ]]*LG26V[[#This Row],[STOCK BARRAS]]) -> 0 | S23: 10 | U23: 3 | W23: XLM-0354
A24: 21 | B24: 1057 | C24: 43UJ6560-LUPA GIGANTE/4B | D24: =(LG26V[[#This Row],[CANTIDAD INICIAL JUEGO ]]+LG26V[[#This Row],[ENTRADAS JUEGOS ]]-LG26V[[#This Row],[SALIDAS JUEGOS]]) -> 1 | E24: =(LG26V[[#This Row],[CANTIDAD INICIAL BARRAS]]+LG26V[[#This Row],[ENTRADAS BARRAS]]-LG26V[[#This Row],[SALIDA BARRAS]]) -> 0 | F24: 180 | G24: 100 | H24: 4 | I24: =(LG26V[[#This Row],["J" PRECIO VENTA ]]/LG26V[[#This Row],[BARRAS]]) -> 45 | J24: =(LG26V[[#This Row],["J"PRECIO COMPRA ]]/LG26V[[#This Row],[BARRAS]]) -> 25 | K24: =SUMIF(entradas26[CODIGO],LG26V[[#This Row],[CODIGO ]],entradas26[[CAN JUEGOS ]]) -> 0 | L24: =SUMIF(entradas26[CODIGO],LG26V[[#This Row],[CODIGO ]],entradas26[CAN BARRAS]) -> 0 | M24: =SUMIF(salidas26[[CODIGO ]],LG26V[[#This Row],[CODIGO ]],salidas26[[CANT JUEGOS ]]) -> 0 | N24: =SUMIF(salidas26[[CODIGO ]],LG26V[[#This Row],[CODIGO ]],salidas26[CANT BARRAS]) -> 0 | O24: =(LG26V[[#This Row],["J"PRECIO COMPRA ]]*LG26V[[#This Row],[STOCK JUEGOS]]) -> 100 | P24: =(LG26V[[#This Row],["J" PRECIO VENTA ]]*LG26V[[#This Row],[STOCK JUEGOS]]) -> 180 | Q24: =(LG26V[[#This Row],["B"PRECIO COMPRA]]*LG26V[[#This Row],[STOCK BARRAS]]) -> 0 | R24: =(LG26V[[#This Row],["B"PRECIO VENTA ]]*LG26V[[#This Row],[STOCK BARRAS]]) -> 0 | S24: 1
A25: 22 | B25: 1060 | C25: 43LH-LF 5100/6B | D25: =(LG26V[[#This Row],[CANTIDAD INICIAL JUEGO ]]+LG26V[[#This Row],[ENTRADAS JUEGOS ]]-LG26V[[#This Row],[SALIDAS JUEGOS]]) -> 13 | E25: =(LG26V[[#This Row],[CANTIDAD INICIAL BARRAS]]+LG26V[[#This Row],[ENTRADAS BARRAS]]-LG26V[[#This Row],[SALIDA BARRAS]]) -> 4 | F25: 180 | G25: 85 | H25: 6 | I25: =(LG26V[[#This Row],["J" PRECIO VENTA ]]/LG26V[[#This Row],[BARRAS]]) -> 30 | J25: =(LG26V[[#This Row],["J"PRECIO COMPRA ]]/LG26V[[#This Row],[BARRAS]]) -> 14.166667 | K25: =SUMIF(entradas26[CODIGO],LG26V[[#This Row],[CODIGO ]],entradas26[[CAN JUEGOS ]]) -> 0 | L25: =SUMIF(entradas26[CODIGO],LG26V[[#This Row],[CODIGO ]],entradas26[CAN BARRAS]) -> 0 | M25: =SUMIF(salidas26[[CODIGO ]],LG26V[[#This Row],[CODIGO ]],salidas26[[CANT JUEGOS ]]) -> 3 | N25: =SUMIF(salidas26[[CODIGO ]],LG26V[[#This Row],[CODIGO ]],salidas26[CANT BARRAS]) -> 0 | O25: =(LG26V[[#This Row],["J"PRECIO COMPRA ]]*LG26V[[#This Row],[STOCK JUEGOS]]) -> 1105 | P25: =(LG26V[[#This Row],["J" PRECIO VENTA ]]*LG26V[[#This Row],[STOCK JUEGOS]]) -> 2340 | Q25: =(LG26V[[#This Row],["B"PRECIO COMPRA]]*LG26V[[#This Row],[STOCK BARRAS]]) -> 56.666667 | R25: =(LG26V[[#This Row],["B"PRECIO VENTA ]]*LG26V[[#This Row],[STOCK BARRAS]]) -> 120 | S25: 16 | T25: 4 | U25: 3.3 | W25: XLM-0545-0544
A26: 23 | B26: 1063 | C26: 43LH5000/5B | D26: =(LG26V[[#This Row],[CANTIDAD INICIAL JUEGO ]]+LG26V[[#This Row],[ENTRADAS JUEGOS ]]-LG26V[[#This Row],[SALIDAS JUEGOS]]) -> 19 | E26: =(LG26V[[#This Row],[CANTIDAD INICIAL BARRAS]]+LG26V[[#This Row],[ENTRADAS BARRAS]]-LG26V[[#This Row],[SALIDA BARRAS]]) -> 2 | F26: 180 | G26: 82 | H26: 5 | I26: =(LG26V[[#This Row],["J" PRECIO VENTA ]]/LG26V[[#This Row],[BARRAS]]) -> 36 | J26: =(LG26V[[#This Row],["J"PRECIO COMPRA ]]/LG26V[[#This Row],[BARRAS]]) -> 16.4 | K26: =SUMIF(entradas26[CODIGO],LG26V[[#This Row],[CODIGO ]],entradas26[[CAN JUEGOS ]]) -> 0 | L26: =SUMIF(entradas26[CODIGO],LG26V[[#This Row],[CODIGO ]],entradas26[CAN BARRAS]) -> 0 | M26: =SUMIF(salidas26[[CODIGO ]],LG26V[[#This Row],[CODIGO ]],salidas26[[CANT JUEGOS ]]) -> 4 | N26: =SUMIF(salidas26[[CODIGO ]],LG26V[[#This Row],[CODIGO ]],salidas26[CANT BARRAS]) -> 0 | O26: =(LG26V[[#This Row],["J"PRECIO COMPRA ]]*LG26V[[#This Row],[STOCK JUEGOS]]) -> 1558 | P26: =(LG26V[[#This Row],["J" PRECIO VENTA ]]*LG26V[[#This Row],[STOCK JUEGOS]]) -> 3420 | Q26: =(LG26V[[#This Row],["B"PRECIO COMPRA]]*LG26V[[#This Row],[STOCK BARRAS]]) -> 32.8 | R26: =(LG26V[[#This Row],["B"PRECIO VENTA ]]*LG26V[[#This Row],[STOCK BARRAS]]) -> 72 | S26: 23 | T26: 2 | U26: 3.55 | W26: XLM-0735
A27: 24 | B27: 1064 | C27: 43LK540 8B/3V | D27: =(LG26V[[#This Row],[CANTIDAD INICIAL JUEGO ]]+LG26V[[#This Row],[ENTRADAS JUEGOS ]]-LG26V[[#This Row],[SALIDAS JUEGOS]]) -> 18 | E27: =(LG26V[[#This Row],[CANTIDAD INICIAL BARRAS]]+LG26V[[#This Row],[ENTRADAS BARRAS]]-LG26V[[#This Row],[SALIDA BARRAS]]) -> 0 | F27: 180 | G27: 104 | H27: 8 | I27: =(LG26V[[#This Row],["J" PRECIO VENTA ]]/LG26V[[#This Row],[BARRAS]]) -> 22.5 | J27: =(LG26V[[#This Row],["J"PRECIO COMPRA ]]/LG26V[[#This Row],[BARRAS]]) -> 13 | K27: =SUMIF(entradas26[CODIGO],LG26V[[#This Row],[CODIGO ]],entradas26[[CAN JUEGOS ]]) -> 0 | L27: =SUMIF(entradas26[CODIGO],LG26V[[#This Row],[CODIGO ]],entradas26[CAN BARRAS]) -> 0 | M27: =SUMIF(salidas26[[CODIGO ]],LG26V[[#This Row],[CODIGO ]],salidas26[[CANT JUEGOS ]]) -> 2 | N27: =SUMIF(salidas26[[CODIGO ]],LG26V[[#This Row],[CODIGO ]],salidas26[CANT BARRAS]) -> 0 | O27: =(LG26V[[#This Row],["J"PRECIO COMPRA ]]*LG26V[[#This Row],[STOCK JUEGOS]]) -> 1872 | P27: =(LG26V[[#This Row],["J" PRECIO VENTA ]]*LG26V[[#This Row],[STOCK JUEGOS]]) -> 3240 | Q27: =(LG26V[[#This Row],["B"PRECIO COMPRA]]*LG26V[[#This Row],[STOCK BARRAS]]) -> 0 | R27: =(LG26V[[#This Row],["B"PRECIO VENTA ]]*LG26V[[#This Row],[STOCK BARRAS]]) -> 0 | S27: 20 | U27: 4.5 | W27: XY-0730
B28: 1065 | C28: 43UM7300 | D28: =(LG26V[[#This Row],[CANTIDAD INICIAL JUEGO ]]+LG26V[[#This Row],[ENTRADAS JUEGOS ]]-LG26V[[#This Row],[SALIDAS JUEGOS]]) -> 20 | E28: =(LG26V[[#This Row],[CANTIDAD INICIAL BARRAS]]+LG26V[[#This Row],[ENTRADAS BARRAS]]-LG26V[[#This Row],[SALIDA BARRAS]]) -> 0 | F28: 180 | G28: 80 | I28: =(LG26V[[#This Row],["J" PRECIO VENTA ]]/LG26V[[#This Row],[BARRAS]]) -> #DIV/0! | J28: =(LG26V[[#This Row],["J"PRECIO COMPRA ]]/LG26V[[#This Row],[BARRAS]]) -> #DIV/0! | K28: =SUMIF(entradas26[CODIGO],LG26V[[#This Row],[CODIGO ]],entradas26[[CAN JUEGOS ]]) -> 20 | L28: =SUMIF(entradas26[CODIGO],LG26V[[#This Row],[CODIGO ]],entradas26[CAN BARRAS]) -> 0 | M28: =SUMIF(salidas26[[CODIGO ]],LG26V[[#This Row],[CODIGO ]],salidas26[[CANT JUEGOS ]]) -> 0 | N28: =SUMIF(salidas26[[CODIGO ]],LG26V[[#This Row],[CODIGO ]],salidas26[CANT BARRAS]) -> 0 | O28: =(LG26V[[#This Row],["J"PRECIO COMPRA ]]*LG26V[[#This Row],[STOCK JUEGOS]]) -> 1600 | P28: =(LG26V[[#This Row],["J" PRECIO VENTA ]]*LG26V[[#This Row],[STOCK JUEGOS]]) -> 3600 | Q28: =(LG26V[[#This Row],["B"PRECIO COMPRA]]*LG26V[[#This Row],[STOCK BARRAS]]) -> #DIV/0! | R28: =(LG26V[[#This Row],["B"PRECIO VENTA ]]*LG26V[[#This Row],[STOCK BARRAS]]) -> #DIV/0! | U28: 4.2 | W28: XLM-1608
A29: 25 | B29: 1066 | C29: 47LA6130-12B/3V | D29: =(LG26V[[#This Row],[CANTIDAD INICIAL JUEGO ]]+LG26V[[#This Row],[ENTRADAS JUEGOS ]]-LG26V[[#This Row],[SALIDAS JUEGOS]]) -> 8 | E29: =(LG26V[[#This Row],[CANTIDAD INICIAL BARRAS]]+LG26V[[#This Row],[ENTRADAS BARRAS]]-LG26V[[#This Row],[SALIDA BARRAS]]) -> 11 | F29: 240 | G29: 138 | H29: 12 | I29: =(LG26V[[#This Row],["J" PRECIO VENTA ]]/LG26V[[#This Row],[BARRAS]]) -> 20 | J29: =(LG26V[[#This Row],["J"PRECIO COMPRA ]]/LG26V[[#This Row],[BARRAS]]) -> 11.5 | K29: =SUMIF(entradas26[CODIGO],LG26V[[#This Row],[CODIGO ]],entradas26[[CAN JUEGOS ]]) -> 0 | L29: =SUMIF(entradas26[CODIGO],LG26V[[#This Row],[CODIGO ]],entradas26[CAN BARRAS]) -> 0 | M29: =SUMIF(salidas26[[CODIGO ]],LG26V[[#This Row],[CODIGO ]],salidas26[[CANT JUEGOS ]]) -> 3 | N29: =SUMIF(salidas26[[CODIGO ]],LG26V[[#This Row],[CODIGO ]],salidas26[CANT BARRAS]) -> 0 | O29: =(LG26V[[#This Row],["J"PRECIO COMPRA ]]*LG26V[[#This Row],[STOCK JUEGOS]]) -> 1104 | P29: =(LG26V[[#This Row],["J" PRECIO VENTA ]]*LG26V[[#This Row],[STOCK JUEGOS]]) -> 1920 | Q29: =(LG26V[[#This Row],["B"PRECIO COMPRA]]*LG26V[[#This Row],[STOCK BARRAS]]) -> 126.5 | R29: =(LG26V[[#This Row],["B"PRECIO VENTA ]]*LG26V[[#This Row],[STOCK BARRAS]]) -> 220 | S29: 11 | T29: 11 | U29: 4.6 | W29: XLM-0271-0272-0273-0274
A30: 26 | B30: 1067 | C30: 47LA6600/2B | D30: =(LG26V[[#This Row],[CANTIDAD INICIAL JUEGO ]]+LG26V[[#This Row],[ENTRADAS JUEGOS ]]-LG26V[[#This Row],[SALIDAS JUEGOS]]) -> 20 | E30: =(LG26V[[#This Row],[CANTIDAD INICIAL BARRAS]]+LG26V[[#This Row],[ENTRADAS BARRAS]]-LG26V[[#This Row],[SALIDA BARRAS]]) -> 0 | F30: 250 | G30: 150 | H30: 2 | I30: =(LG26V[[#This Row],["J" PRECIO VENTA ]]/LG26V[[#This Row],[BARRAS]]) -> 125 | J30: =(LG26V[[#This Row],["J"PRECIO COMPRA ]]/LG26V[[#This Row],[BARRAS]]) -> 75 | K30: =SUMIF(entradas26[CODIGO],LG26V[[#This Row],[CODIGO ]],entradas26[[CAN JUEGOS ]]) -> 20 | L30: =SUMIF(entradas26[CODIGO],LG26V[[#This Row],[CODIGO ]],entradas26[CAN BARRAS]) -> 0 | M30: =SUMIF(salidas26[[CODIGO ]],LG26V[[#This Row],[CODIGO ]],salidas26[[CANT JUEGOS ]]) -> 2 | N30: =SUMIF(salidas26[[CODIGO ]],LG26V[[#This Row],[CODIGO ]],salidas26[CANT BARRAS]) -> 0 | O30: =(LG26V[[#This Row],["J"PRECIO COMPRA ]]*LG26V[[#This Row],[STOCK JUEGOS]]) -> 3000 | P30: =(LG26V[[#This Row],["J" PRECIO VENTA ]]*LG26V[[#This Row],[STOCK JUEGOS]]) -> 5000 | Q30: =(LG26V[[#This Row],["B"PRECIO COMPRA]]*LG26V[[#This Row],[STOCK BARRAS]]) -> 0 | R30: =(LG26V[[#This Row],["B"PRECIO VENTA ]]*LG26V[[#This Row],[STOCK BARRAS]]) -> 0 | S30: 2 | U30: 4.6 | W30: XLM- 1296/1297
A31: 27 | B31: 1069 | C31: 47LB6500- 8B/6V | D31: =(LG26V[[#This Row],[CANTIDAD INICIAL JUEGO ]]+LG26V[[#This Row],[ENTRADAS JUEGOS ]]-LG26V[[#This Row],[SALIDAS JUEGOS]]) -> 10 | E31: =(LG26V[[#This Row],[CANTIDAD INICIAL BARRAS]]+LG26V[[#This Row],[ENTRADAS BARRAS]]-LG26V[[#This Row],[SALIDA BARRAS]]) -> 11 | F31: 250 | G31: 88 | H31: 8 | I31: =(LG26V[[#This Row],["J" PRECIO VENTA ]]/LG26V[[#This Row],[BARRAS]]) -> 31.25 | J31: =(LG26V[[#This Row],["J"PRECIO COMPRA ]]/LG26V[[#This Row],[BARRAS]]) -> 11 | K31: =SUMIF(entradas26[CODIGO],LG26V[[#This Row],[CODIGO ]],entradas26[[CAN JUEGOS ]]) -> 0 | L31: =SUMIF(entradas26[CODIGO],LG26V[[#This Row],[CODIGO ]],entradas26[CAN BARRAS]) -> 0 | M31: =SUMIF(salidas26[[CODIGO ]],LG26V[[#This Row],[CODIGO ]],salidas26[[CANT JUEGOS ]]) -> 11 | N31: =SUMIF(salidas26[[CODIGO ]],LG26V[[#This Row],[CODIGO ]],salidas26[CANT BARRAS]) -> 0 | O31: =(LG26V[[#This Row],["J"PRECIO COMPRA ]]*LG26V[[#This Row],[STOCK JUEGOS]]) -> 880 | P31: =(LG26V[[#This Row],["J" PRECIO VENTA ]]*LG26V[[#This Row],[STOCK JUEGOS]]) -> 2500 | Q31: =(LG26V[[#This Row],["B"PRECIO COMPRA]]*LG26V[[#This Row],[STOCK BARRAS]]) -> 121 | R31: =(LG26V[[#This Row],["B"PRECIO VENTA ]]*LG26V[[#This Row],[STOCK BARRAS]]) -> 343.75 | S31: 21 | T31: 11 | U31: 5.9 | W31: XLM-0265/0266
A32: 28 | B32: 1072 | C32: 47LM6200/2B | D32: =(LG26V[[#This Row],[CANTIDAD INICIAL JUEGO ]]+LG26V[[#This Row],[ENTRADAS JUEGOS ]]-LG26V[[#This Row],[SALIDAS JUEGOS]]) -> 18 | E32: =(LG26V[[#This Row],[CANTIDAD INICIAL BARRAS]]+LG26V[[#This Row],[ENTRADAS BARRAS]]-LG26V[[#This Row],[SALIDA BARRAS]]) -> 0 | F32: 200 | G32: 103 | H32: 2 | I32: =(LG26V[[#This Row],["J" PRECIO VENTA ]]/LG26V[[#This Row],[BARRAS]]) -> 100 | J32: =(LG26V[[#This Row],["J"PRECIO COMPRA ]]/LG26V[[#This Row],[BARRAS]]) -> 51.5 | K32: =SUMIF(entradas26[CODIGO],LG26V[[#This Row],[CODIGO ]],entradas26[[CAN JUEGOS ]]) -> 0 | L32: =SUMIF(entradas26[CODIGO],LG26V[[#This Row],[CODIGO ]],entradas26[CAN BARRAS]) -> 0 | M32: =SUMIF(salidas26[[CODIGO ]],LG26V[[#This Row],[CODIGO ]],salidas26[[CANT JUEGOS ]]) -> 0 | N32: =SUMIF(salidas26[[CODIGO ]],LG26V[[#This Row],[CODIGO ]],salidas26[CANT BARRAS]) -> 0 | O32: =(LG26V[[#This Row],["J"PRECIO COMPRA ]]*LG26V[[#This Row],[STOCK JUEGOS]]) -> 1854 | P32: =(LG26V[[#This Row],["J" PRECIO VENTA ]]*LG26V[[#This Row],[STOCK JUEGOS]]) -> 3600 | Q32: =(LG26V[[#This Row],["B"PRECIO COMPRA]]*LG26V[[#This Row],[STOCK BARRAS]]) -> 0 | R32: =(LG26V[[#This Row],["B"PRECIO VENTA ]]*LG26V[[#This Row],[STOCK BARRAS]]) -> 0 | S32: 18 | W32: XLM-0462/0463
A33: 29 | B33: 1073 | C33: 47 LWU6500/2B | D33: =(LG26V[[#This Row],[CANTIDAD INICIAL JUEGO ]]+LG26V[[#This Row],[ENTRADAS JUEGOS ]]-LG26V[[#This Row],[SALIDAS JUEGOS]]) -> 2 | E33: =(LG26V[[#This Row],[CANTIDAD INICIAL BARRAS]]+LG26V[[#This Row],[ENTRADAS BARRAS]]-LG26V[[#This Row],[SALIDA BARRAS]]) -> 0 | F33: 250 | G33: 135 | H33: 2 | I33: =(LG26V[[#This Row],["J" PRECIO VENTA ]]/LG26V[[#This Row],[BARRAS]]) -> 125 | J33: =(LG26V[[#This Row],["J"PRECIO COMPRA ]]/LG26V[[#This Row],[BARRAS]]) -> 67.5 | K33: =SUMIF(entradas26[CODIGO],LG26V[[#This Row],[CODIGO ]],entradas26[[CAN JUEGOS ]]) -> 0 | L33: =SUMIF(entradas26[CODIGO],LG26V[[#This Row],[CODIGO ]],entradas26[CAN BARRAS]) -> 0 | M33: =SUMIF(salidas26[[CODIGO ]],LG26V[[#This Row],[CODIGO ]],salidas26[[CANT JUEGOS ]]) -> 0 | N33: =SUMIF(salidas26[[CODIGO ]],LG26V[[#This Row],[CODIGO ]],salidas26[CANT BARRAS]) -> 0 | O33: =(LG26V[[#This Row],["J"PRECIO COMPRA ]]*LG26V[[#This Row],[STOCK JUEGOS]]) -> 270 | P33: =(LG26V[[#This Row],["J" PRECIO VENTA ]]*LG26V[[#This Row],[STOCK JUEGOS]]) -> 500 | Q33: =(LG26V[[#This Row],["B"PRECIO COMPRA]]*LG26V[[#This Row],[STOCK BARRAS]]) -> 0 | R33: =(LG26V[[#This Row],["B"PRECIO VENTA ]]*LG26V[[#This Row],[STOCK BARRAS]]) -> 0 | S33: 2
A34: 30 | B34: 1075 | C34: 49LJ5500-49UJ6300/8B | D34: =(LG26V[[#This Row],[CANTIDAD INICIAL JUEGO ]]+LG26V[[#This Row],[ENTRADAS JUEGOS ]]-LG26V[[#This Row],[SALIDAS JUEGOS]]) -> 22 | E34: =(LG26V[[#This Row],[CANTIDAD INICIAL BARRAS]]+LG26V[[#This Row],[ENTRADAS BARRAS]]-LG26V[[#This Row],[SALIDA BARRAS]]) -> 0 | F34: 240 | G34: 57 | H34: 8 | I34: =(LG26V[[#This Row],["J" PRECIO VENTA ]]/LG26V[[#This Row],[BARRAS]]) -> 30 | J34: =(LG26V[[#This Row],["J"PRECIO COMPRA ]]/LG26V[[#This Row],[BARRAS]]) -> 7.125 | K34: =SUMIF(entradas26[CODIGO],LG26V[[#This Row],[CODIGO ]],entradas26[[CAN JUEGOS ]]) -> 20 | L34: =SUMIF(entradas26[CODIGO],LG26V[[#This Row],[CODIGO ]],entradas26[CAN BARRAS]) -> 0 | M34: =SUMIF(salidas26[[CODIGO ]],LG26V[[#This Row],[CODIGO ]],salidas26[[CANT JUEGOS ]]) -> 4 | N34: =SUMIF(salidas26[[CODIGO ]],LG26V[[#This Row],[CODIGO ]],salidas26[CANT BARRAS]) -> 0 | O34: =(LG26V[[#This Row],["J"PRECIO COMPRA ]]*LG26V[[#This Row],[STOCK JUEGOS]]) -> 1254 | P34: =(LG26V[[#This Row],["J" PRECIO VENTA ]]*LG26V[[#This Row],[STOCK JUEGOS]]) -> 5280 | Q34: =(LG26V[[#This Row],["B"PRECIO COMPRA]]*LG26V[[#This Row],[STOCK BARRAS]]) -> 0 | R34: =(LG26V[[#This Row],["B"PRECIO VENTA ]]*LG26V[[#This Row],[STOCK BARRAS]]) -> 0 | S34: 6 | U34: 3 | W34: XLM-0806/0807
A35: 31 | B35: 1076 | C35: 49 UJ6500 /8B | D35: =(LG26V[[#This Row],[CANTIDAD INICIAL JUEGO ]]+LG26V[[#This Row],[ENTRADAS JUEGOS ]]-LG26V[[#This Row],[SALIDAS JUEGOS]]) -> 1 | E35: =(LG26V[[#This Row],[CANTIDAD INICIAL BARRAS]]+LG26V[[#This Row],[ENTRADAS BARRAS]]-LG26V[[#This Row],[SALIDA BARRAS]]) -> 0 | F35: 250 | G35: 200 | H35: 8 | I35: =(LG26V[[#This Row],["J" PRECIO VENTA ]]/LG26V[[#This Row],[BARRAS]]) -> 31.25 | J35: =(LG26V[[#This Row],["J"PRECIO COMPRA ]]/LG26V[[#This Row],[BARRAS]]) -> 25 | K35: =SUMIF(entradas26[CODIGO],LG26V[[#This Row],[CODIGO ]],entradas26[[CAN JUEGOS ]]) -> 0 | L35: =SUMIF(entradas26[CODIGO],LG26V[[#This Row],[CODIGO ]],entradas26[CAN BARRAS]) -> 0 | M35: =SUMIF(salidas26[[CODIGO ]],LG26V[[#This Row],[CODIGO ]],salidas26[[CANT JUEGOS ]]) -> 1 | N35: =SUMIF(salidas26[[CODIGO ]],LG26V[[#This Row],[CODIGO ]],salidas26[CANT BARRAS]) -> 0 | O35: =(LG26V[[#This Row],["J"PRECIO COMPRA ]]*LG26V[[#This Row],[STOCK JUEGOS]]) -> 200 | P35: =(LG26V[[#This Row],["J" PRECIO VENTA ]]*LG26V[[#This Row],[STOCK JUEGOS]]) -> 250 | Q35: =(LG26V[[#This Row],["B"PRECIO COMPRA]]*LG26V[[#This Row],[STOCK BARRAS]]) -> 0 | R35: =(LG26V[[#This Row],["B"PRECIO VENTA ]]*LG26V[[#This Row],[STOCK BARRAS]]) -> 0 | S35: 2
A36: 32 | B36: 1078 | C36: 49LB-LF/10B | D36: =(LG26V[[#This Row],[CANTIDAD INICIAL JUEGO ]]+LG26V[[#This Row],[ENTRADAS JUEGOS ]]-LG26V[[#This Row],[SALIDAS JUEGOS]]) -> 6 | E36: =(LG26V[[#This Row],[CANTIDAD INICIAL BARRAS]]+LG26V[[#This Row],[ENTRADAS BARRAS]]-LG26V[[#This Row],[SALIDA BARRAS]]) -> 9 | F36: 280 | G36: 183 | H36: 10 | I36: =(LG26V[[#This Row],["J" PRECIO VENTA ]]/LG26V[[#This Row],[BARRAS]]) -> 28 | J36: =(LG26V[[#This Row],["J"PRECIO COMPRA ]]/LG26V[[#This Row],[BARRAS]]) -> 18.3 | K36: =SUMIF(entradas26[CODIGO],LG26V[[#This Row],[CODIGO ]],entradas26[[CAN JUEGOS ]]) -> 0 | L36: =SUMIF(entradas26[CODIGO],LG26V[[#This Row],[CODIGO ]],entradas26[CAN BARRAS]) -> 0 | M36: =SUMIF(salidas26[[CODIGO ]],LG26V[[#This Row],[CODIGO ]],salidas26[[CANT JUEGOS ]]) -> 8 | N36: =SUMIF(salidas26[[CODIGO ]],LG26V[[#This Row],[CODIGO ]],salidas26[CANT BARRAS]) -> 0 | O36: =(LG26V[[#This Row],["J"PRECIO COMPRA ]]*LG26V[[#This Row],[STOCK JUEGOS]]) -> 1098 | P36: =(LG26V[[#This Row],["J" PRECIO VENTA ]]*LG26V[[#This Row],[STOCK JUEGOS]]) -> 1680 | Q36: =(LG26V[[#This Row],["B"PRECIO COMPRA]]*LG26V[[#This Row],[STOCK BARRAS]]) -> 164.7 | R36: =(LG26V[[#This Row],["B"PRECIO VENTA ]]*LG26V[[#This Row],[STOCK BARRAS]]) -> 252 | S36: 14 | T36: 9 | U36: 6.15 | W36: XLM-0279/0280
A37: 33 | B37: 1081 | C37: 49LF5400 2B EL JUEGO | D37: =(LG26V[[#This Row],[CANTIDAD INICIAL JUEGO ]]+LG26V[[#This Row],[ENTRADAS JUEGOS ]]-LG26V[[#This Row],[SALIDAS JUEGOS]]) -> 2 | E37: =(LG26V[[#This Row],[CANTIDAD INICIAL BARRAS]]+LG26V[[#This Row],[ENTRADAS BARRAS]]-LG26V[[#This Row],[SALIDA BARRAS]]) -> 0 | F37: 200 | G37: 120 | H37: 2 | I37: =(LG26V[[#This Row],["J" PRECIO VENTA ]]/LG26V[[#This Row],[BARRAS]]) -> 100 | J37: =(LG26V[[#This Row],["J"PRECIO COMPRA ]]/LG26V[[#This Row],[BARRAS]]) -> 60 | K37: =SUMIF(entradas26[CODIGO],LG26V[[#This Row],[CODIGO ]],entradas26[[CAN JUEGOS ]]) -> 0 | L37: =SUMIF(entradas26[CODIGO],LG26V[[#This Row],[CODIGO ]],entradas26[CAN BARRAS]) -> 0 | M37: =SUMIF(salidas26[[CODIGO ]],LG26V[[#This Row],[CODIGO ]],salidas26[[CANT JUEGOS ]]) -> 2 | N37: =SUMIF(salidas26[[CODIGO ]],LG26V[[#This Row],[CODIGO ]],salidas26[CANT BARRAS]) -> 0 | O37: =(LG26V[[#This Row],["J"PRECIO COMPRA ]]*LG26V[[#This Row],[STOCK JUEGOS]]) -> 240 | P37: =(LG26V[[#This Row],["J" PRECIO VENTA ]]*LG26V[[#This Row],[STOCK JUEGOS]]) -> 400 | Q37: =(LG26V[[#This Row],["B"PRECIO COMPRA]]*LG26V[[#This Row],[STOCK BARRAS]]) -> 0 | R37: =(LG26V[[#This Row],["B"PRECIO VENTA ]]*LG26V[[#This Row],[STOCK BARRAS]]) -> 0 | S37: 4
A38: 34 | B38: 1084 | C38: 49LJ5100/8B | D38: =(LG26V[[#This Row],[CANTIDAD INICIAL JUEGO ]]+LG26V[[#This Row],[ENTRADAS JUEGOS ]]-LG26V[[#This Row],[SALIDAS JUEGOS]]) -> 0 | E38: =(LG26V[[#This Row],[CANTIDAD INICIAL BARRAS]]+LG26V[[#This Row],[ENTRADAS BARRAS]]-LG26V[[#This Row],[SALIDA BARRAS]]) -> 6 | F38: 250 | G38: 120 | H38: 8 | I38: =(LG26V[[#This Row],["J" PRECIO VENTA ]]/LG26V[[#This Row],[BARRAS]]) -> 31.25 | J38: =(LG26V[[#This Row],["J"PRECIO COMPRA ]]/LG26V[[#This Row],[BARRAS]]) -> 15 | K38: =SUMIF(entradas26[CODIGO],LG26V[[#This Row],[CODIGO ]],entradas26[[CAN JUEGOS ]]) -> 0 | L38: =SUMIF(entradas26[CODIGO],LG26V[[#This Row],[CODIGO ]],entradas26[CAN BARRAS]) -> 0 | M38: =SUMIF(salidas26[[CODIGO ]],LG26V[[#This Row],[CODIGO ]],salidas26[[CANT JUEGOS ]]) -> 0 | N38: =SUMIF(salidas26[[CODIGO ]],LG26V[[#This Row],[CODIGO ]],salidas26[CANT BARRAS]) -> 0 | O38: =(LG26V[[#This Row],["J"PRECIO COMPRA ]]*LG26V[[#This Row],[STOCK JUEGOS]]) -> 0 | P38: =(LG26V[[#This Row],["J" PRECIO VENTA ]]*LG26V[[#This Row],[STOCK JUEGOS]]) -> 0 | Q38: =(LG26V[[#This Row],["B"PRECIO COMPRA]]*LG26V[[#This Row],[STOCK BARRAS]]) -> 90 | R38: =(LG26V[[#This Row],["B"PRECIO VENTA ]]*LG26V[[#This Row],[STOCK BARRAS]]) -> 187.5 | S38: 0 | T38: 6
A39: 35 | B39: 1087 | C39: 49LK5400 /8B | D39: =(LG26V[[#This Row],[CANTIDAD INICIAL JUEGO ]]+LG26V[[#This Row],[ENTRADAS JUEGOS ]]-LG26V[[#This Row],[SALIDAS JUEGOS]]) -> 13 | E39: =(LG26V[[#This Row],[CANTIDAD INICIAL BARRAS]]+LG26V[[#This Row],[ENTRADAS BARRAS]]-LG26V[[#This Row],[SALIDA BARRAS]]) -> 7 | F39: 220 | G39: 114 | H39: 8 | I39: =(LG26V[[#This Row],["J" PRECIO VENTA ]]/LG26V[[#This Row],[BARRAS]]) -> 27.5 | J39: =(LG26V[[#This Row],["J"PRECIO COMPRA ]]/LG26V[[#This Row],[BARRAS]]) -> 14.25 | K39: =SUMIF(entradas26[CODIGO],LG26V[[#This Row],[CODIGO ]],entradas26[[CAN JUEGOS ]]) -> 0 | L39: =SUMIF(entradas26[CODIGO],LG26V[[#This Row],[CODIGO ]],entradas26[CAN BARRAS]) -> 0 | M39: =SUMIF(salidas26[[CODIGO ]],LG26V[[#This Row],[CODIGO ]],salidas26[[CANT JUEGOS ]]) -> 3 | N39: =SUMIF(salidas26[[CODIGO ]],LG26V[[#This Row],[CODIGO ]],salidas26[CANT BARRAS]) -> 0 | O39: =(LG26V[[#This Row],["J"PRECIO COMPRA ]]*LG26V[[#This Row],[STOCK JUEGOS]]) -> 1482 | P39: =(LG26V[[#This Row],["J" PRECIO VENTA ]]*LG26V[[#This Row],[STOCK JUEGOS]]) -> 2860 | Q39: =(LG26V[[#This Row],["B"PRECIO COMPRA]]*LG26V[[#This Row],[STOCK BARRAS]]) -> 99.75 | R39: =(LG26V[[#This Row],["B"PRECIO VENTA ]]*LG26V[[#This Row],[STOCK BARRAS]]) -> 192.5 | S39: 16 | T39: 7 | U39: 5.7 | W39: XLM-W0760
A40: 36 | B40: 1090 | C40: 49UB8300/ 2B | D40: =(LG26V[[#This Row],[CANTIDAD INICIAL JUEGO ]]+LG26V[[#This Row],[ENTRADAS JUEGOS ]]-LG26V[[#This Row],[SALIDAS JUEGOS]]) -> 16 | E40: =(LG26V[[#This Row],[CANTIDAD INICIAL BARRAS]]+LG26V[[#This Row],[ENTRADAS BARRAS]]-LG26V[[#This Row],[SALIDA BARRAS]]) -> 0 | F40: 250 | G40: 63 | H40: 2 | I40: =(LG26V[[#This Row],["J" PRECIO VENTA ]]/LG26V[[#This Row],[BARRAS]]) -> 125 | J40: =(LG26V[[#This Row],["J"PRECIO COMPRA ]]/LG26V[[#This Row],[BARRAS]]) -> 31.5 | K40: =SUMIF(entradas26[CODIGO],LG26V[[#This Row],[CODIGO ]],entradas26[[CAN JUEGOS ]]) -> 0 | L40: =SUMIF(entradas26[CODIGO],LG26V[[#This Row],[CODIGO ]],entradas26[CAN BARRAS]) -> 0 | M40: =SUMIF(salidas26[[CODIGO ]],LG26V[[#This Row],[CODIGO ]],salidas26[[CANT JUEGOS ]]) -> 0 | N40: =SUMIF(salidas26[[CODIGO ]],LG26V[[#This Row],[CODIGO ]],salidas26[CANT BARRAS]) -> 0 | O40: =(LG26V[[#This Row],["J"PRECIO COMPRA ]]*LG26V[[#This Row],[STOCK JUEGOS]]) -> 1008 | P40: =(LG26V[[#This Row],["J" PRECIO VENTA ]]*LG26V[[#This Row],[STOCK JUEGOS]]) -> 4000 | Q40: =(LG26V[[#This Row],["B"PRECIO COMPRA]]*LG26V[[#This Row],[STOCK BARRAS]]) -> 0 | R40: =(LG26V[[#This Row],["B"PRECIO VENTA ]]*LG26V[[#This Row],[STOCK BARRAS]]) -> 0 | S40: 16 | U40: 4.5 | W40: XLM-1019/1020
A41: 37 | B41: 1094 | C41: 49 UH6100-LH5100 /8B | D41: =(LG26V[[#This Row],[CANTIDAD INICIAL JUEGO ]]+LG26V[[#This Row],[ENTRADAS JUEGOS ]]-LG26V[[#This Row],[SALIDAS JUEGOS]]) -> 13 | E41: =(LG26V[[#This Row],[CANTIDAD INICIAL BARRAS]]+LG26V[[#This Row],[ENTRADAS BARRAS]]-LG26V[[#This Row],[SALIDA BARRAS]]) -> 6 | F41: 250 | G41: 96 | H41: 8 | I41: =(LG26V[[#This Row],["J" PRECIO VENTA ]]/LG26V[[#This Row],[BARRAS]]) -> 31.25 | J41: =(LG26V[[#This Row],["J"PRECIO COMPRA ]]/LG26V[[#This Row],[BARRAS]]) -> 12 | K41: =SUMIF(entradas26[CODIGO],LG26V[[#This Row],[CODIGO ]],entradas26[[CAN JUEGOS ]]) -> 0 | L41: =SUMIF(entradas26[CODIGO],LG26V[[#This Row],[CODIGO ]],entradas26[CAN BARRAS]) -> 0 | M41: =SUMIF(salidas26[[CODIGO ]],LG26V[[#This Row],[CODIGO ]],salidas26[[CANT JUEGOS ]]) -> 1 | N41: =SUMIF(salidas26[[CODIGO ]],LG26V[[#This Row],[CODIGO ]],salidas26[CANT BARRAS]) -> 0 | O41: =(LG26V[[#This Row],["J"PRECIO COMPRA ]]*LG26V[[#This Row],[STOCK JUEGOS]]) -> 1248 | P41: =(LG26V[[#This Row],["J" PRECIO VENTA ]]*LG26V[[#This Row],[STOCK JUEGOS]]) -> 3250 | Q41: =(LG26V[[#This Row],["B"PRECIO COMPRA]]*LG26V[[#This Row],[STOCK BARRAS]]) -> 72 | R41: =(LG26V[[#This Row],["B"PRECIO VENTA ]]*LG26V[[#This Row],[STOCK BARRAS]]) -> 187.5 | S41: 14 | T41: 6 | U41: 4.36 | W41: XY-0032
A42: 38 | B42: 1096 | C42: 49LH6000 /8B | D42: =(LG26V[[#This Row],[CANTIDAD INICIAL JUEGO ]]+LG26V[[#This Row],[ENTRADAS JUEGOS ]]-LG26V[[#This Row],[SALIDAS JUEGOS]]) -> 12 | E42: =(LG26V[[#This Row],[CANTIDAD INICIAL BARRAS]]+LG26V[[#This Row],[ENTRADAS BARRAS]]-LG26V[[#This Row],[SALIDA BARRAS]]) -> 0 | F42: 260 | G42: 112 | H42: 8 | I42: =(LG26V[[#This Row],["J" PRECIO VENTA ]]/LG26V[[#This Row],[BARRAS]]) -> 32.5 | J42: =(LG26V[[#This Row],["J"PRECIO COMPRA ]]/LG26V[[#This Row],[BARRAS]]) -> 14 | K42: =SUMIF(entradas26[CODIGO],LG26V[[#This Row],[CODIGO ]],entradas26[[CAN JUEGOS ]]) -> 0 | L42: =SUMIF(entradas26[CODIGO],LG26V[[#This Row],[CODIGO ]],entradas26[CAN BARRAS]) -> 0 | M42: =SUMIF(salidas26[[CODIGO ]],LG26V[[#This Row],[CODIGO ]],salidas26[[CANT JUEGOS ]]) -> 1 | N42: =SUMIF(salidas26[[CODIGO ]],LG26V[[#This Row],[CODIGO ]],salidas26[CANT BARRAS]) -> 0 | O42: =(LG26V[[#This Row],["J"PRECIO COMPRA ]]*LG26V[[#This Row],[STOCK JUEGOS]]) -> 1344 | P42: =(LG26V[[#This Row],["J" PRECIO VENTA ]]*LG26V[[#This Row],[STOCK JUEGOS]]) -> 3120 | Q42: =(LG26V[[#This Row],["B"PRECIO COMPRA]]*LG26V[[#This Row],[STOCK BARRAS]]) -> 0 | R42: =(LG26V[[#This Row],["B"PRECIO VENTA ]]*LG26V[[#This Row],[STOCK BARRAS]]) -> 0 | S42: 13
A43: 39 | B43: 1099 | C43: 49UJ6560-LUPA GIGANTE/4B | D43: =(LG26V[[#This Row],[CANTIDAD INICIAL JUEGO ]]+LG26V[[#This Row],[ENTRADAS JUEGOS ]]-LG26V[[#This Row],[SALIDAS JUEGOS]]) -> 7 | E43: =(LG26V[[#This Row],[CANTIDAD INICIAL BARRAS]]+LG26V[[#This Row],[ENTRADAS BARRAS]]-LG26V[[#This Row],[SALIDA BARRAS]]) -> 3 | F43: 220 | G43: 92 | H43: 4 | I43: =(LG26V[[#This Row],["J" PRECIO VENTA ]]/LG26V[[#This Row],[BARRAS]]) -> 55 | J43: =(LG26V[[#This Row],["J"PRECIO COMPRA ]]/LG26V[[#This Row],[BARRAS]]) -> 23 | K43: =SUMIF(entradas26[CODIGO],LG26V[[#This Row],[CODIGO ]],entradas26[[CAN JUEGOS ]]) -> 0 | L43: =SUMIF(entradas26[CODIGO],LG26V[[#This Row],[CODIGO ]],entradas26[CAN BARRAS]) -> 0 | M43: =SUMIF(salidas26[[CODIGO ]],LG26V[[#This Row],[CODIGO ]],salidas26[[CANT JUEGOS ]]) -> 2 | N43: =SUMIF(salidas26[[CODIGO ]],LG26V[[#This Row],[CODIGO ]],salidas26[CANT BARRAS]) -> 0 | O43: =(LG26V[[#This Row],["J"PRECIO COMPRA ]]*LG26V[[#This Row],[STOCK JUEGOS]]) -> 644 | P43: =(LG26V[[#This Row],["J" PRECIO VENTA ]]*LG26V[[#This Row],[STOCK JUEGOS]]) -> 1540 | Q43: =(LG26V[[#This Row],["B"PRECIO COMPRA]]*LG26V[[#This Row],[STOCK BARRAS]]) -> 69 | R43: =(LG26V[[#This Row],["B"PRECIO VENTA ]]*LG26V[[#This Row],[STOCK BARRAS]]) -> 165 | S43: 9 | T43: 3 | U43: 4.2 | W43: XLM-0246/0247
A44: 40 | B44: 1102 | C44: 50LA6200/12B/3V | D44: =(LG26V[[#This Row],[CANTIDAD INICIAL JUEGO ]]+LG26V[[#This Row],[ENTRADAS JUEGOS ]]-LG26V[[#This Row],[SALIDAS JUEGOS]]) -> 18 | E44: =(LG26V[[#This Row],[CANTIDAD INICIAL BARRAS]]+LG26V[[#This Row],[ENTRADAS BARRAS]]-LG26V[[#This Row],[SALIDA BARRAS]]) -> 2 | F44: 280 | G44: 116 | H44: 12 | I44: =(LG26V[[#This Row],["J" PRECIO VENTA ]]/LG26V[[#This Row],[BARRAS]]) -> 23.333333 | J44: =(LG26V[[#This Row],["J"PRECIO COMPRA ]]/LG26V[[#This Row],[BARRAS]]) -> 9.6666667 | K44: =SUMIF(entradas26[CODIGO],LG26V[[#This Row],[CODIGO ]],entradas26[[CAN JUEGOS ]]) -> 20 | L44: =SUMIF(entradas26[CODIGO],LG26V[[#This Row],[CODIGO ]],entradas26[CAN BARRAS]) -> 0 | M44: =SUMIF(salidas26[[CODIGO ]],LG26V[[#This Row],[CODIGO ]],salidas26[[CANT JUEGOS ]]) -> 6 | N44: =SUMIF(salidas26[[CODIGO ]],LG26V[[#This Row],[CODIGO ]],salidas26[CANT BARRAS]) -> 0 | O44: =(LG26V[[#This Row],["J"PRECIO COMPRA ]]*LG26V[[#This Row],[STOCK JUEGOS]]) -> 2088 | P44: =(LG26V[[#This Row],["J" PRECIO VENTA ]]*LG26V[[#This Row],[STOCK JUEGOS]]) -> 5040 | Q44: =(LG26V[[#This Row],["B"PRECIO COMPRA]]*LG26V[[#This Row],[STOCK BARRAS]]) -> 19.333333 | R44: =(LG26V[[#This Row],["B"PRECIO VENTA ]]*LG26V[[#This Row],[STOCK BARRAS]]) -> 46.666667 | S44: 4 | T44: 2 | U44: 6.1 | W44: XLM-0261/0262/0259/0260
A45: 41 | B45: 1105 | C45: 50LB6500/10B | D45: =(LG26V[[#This Row],[CANTIDAD INICIAL JUEGO ]]+LG26V[[#This Row],[ENTRADAS JUEGOS ]]-LG26V[[#This Row],[SALIDAS JUEGOS]]) -> 23 | E45: =(LG26V[[#This Row],[CANTIDAD INICIAL BARRAS]]+LG26V[[#This Row],[ENTRADAS BARRAS]]-LG26V[[#This Row],[SALIDA BARRAS]]) -> 0 | F45: 300 | G45: 177 | H45: 10 | I45: =(LG26V[[#This Row],["J" PRECIO VENTA ]]/LG26V[[#This Row],[BARRAS]]) -> 30 | J45: =(LG26V[[#This Row],["J"PRECIO COMPRA ]]/LG26V[[#This Row],[BARRAS]]) -> 17.7 | K45: =SUMIF(entradas26[CODIGO],LG26V[[#This Row],[CODIGO ]],entradas26[[CAN JUEGOS ]]) -> 0 | L45: =SUMIF(entradas26[CODIGO],LG26V[[#This Row],[CODIGO ]],entradas26[CAN BARRAS]) -> 0 | M45: =SUMIF(salidas26[[CODIGO ]],LG26V[[#This Row],[CODIGO ]],salidas26[[CANT JUEGOS ]]) -> 2 | N45: =SUMIF(salidas26[[CODIGO ]],LG26V[[#This Row],[CODIGO ]],salidas26[CANT BARRAS]) -> 0 | O45: =(LG26V[[#This Row],["J"PRECIO COMPRA ]]*LG26V[[#This Row],[STOCK JUEGOS]]) -> 4071 | P45: =(LG26V[[#This Row],["J" PRECIO VENTA ]]*LG26V[[#This Row],[STOCK JUEGOS]]) -> 6900 | Q45: =(LG26V[[#This Row],["B"PRECIO COMPRA]]*LG26V[[#This Row],[STOCK BARRAS]]) -> 0 | R45: =(LG26V[[#This Row],["B"PRECIO VENTA ]]*LG26V[[#This Row],[STOCK BARRAS]]) -> 0 | S45: 25 | U45: 7.7 | W45: XY-0007-SE
A46: 42 | B46: 1108 | C46: 50 UK 6550 /3B | D46: =(LG26V[[#This Row],[CANTIDAD INICIAL JUEGO ]]+LG26V[[#This Row],[ENTRADAS JUEGOS ]]-LG26V[[#This Row],[SALIDAS JUEGOS]]) -> 25 | E46: =(LG26V[[#This Row],[CANTIDAD INICIAL BARRAS]]+LG26V[[#This Row],[ENTRADAS BARRAS]]-LG26V[[#This Row],[SALIDA BARRAS]]) -> 0 | F46: 300 | G46: 65 | H46: 3 | I46: =(LG26V[[#This Row],["J" PRECIO VENTA ]]/LG26V[[#This Row],[BARRAS]]) -> 100 | J46: =(LG26V[[#This Row],["J"PRECIO COMPRA ]]/LG26V[[#This Row],[BARRAS]]) -> 21.666667 | K46: =SUMIF(entradas26[CODIGO],LG26V[[#This Row],[CODIGO ]],entradas26[[CAN JUEGOS ]]) -> 20 | L46: =SUMIF(entradas26[CODIGO],LG26V[[#This Row],[CODIGO ]],entradas26[CAN BARRAS]) -> 0 | M46: =SUMIF(salidas26[[CODIGO ]],LG26V[[#This Row],[CODIGO ]],salidas26[[CANT JUEGOS ]]) -> 1 | N46: =SUMIF(salidas26[[CODIGO ]],LG26V[[#This Row],[CODIGO ]],salidas26[CANT BARRAS]) -> 0 | O46: =(LG26V[[#This Row],["J"PRECIO COMPRA ]]*LG26V[[#This Row],[STOCK JUEGOS]]) -> 1625 | P46: =(LG26V[[#This Row],["J" PRECIO VENTA ]]*LG26V[[#This Row],[STOCK JUEGOS]]) -> 7500 | Q46: =(LG26V[[#This Row],["B"PRECIO COMPRA]]*LG26V[[#This Row],[STOCK BARRAS]]) -> 0 | R46: =(LG26V[[#This Row],["B"PRECIO VENTA ]]*LG26V[[#This Row],[STOCK BARRAS]]) -> 0 | S46: 6 | U46: 5.8 | W46: XLM-0923
A47: 43 | B47: 1111 | C47: 55 UK 6300-UM7100 /3B | D47: =(LG26V[[#This Row],[CANTIDAD INICIAL JUEGO ]]+LG26V[[#This Row],[ENTRADAS JUEGOS ]]-LG26V[[#This Row],[SALIDAS JUEGOS]]) -> 10 | E47: =(LG26V[[#This Row],[CANTIDAD INICIAL BARRAS]]+LG26V[[#This Row],[ENTRADAS BARRAS]]-LG26V[[#This Row],[SALIDA BARRAS]]) -> 2 | F47: 280 | G47: 69 | H47: 3 | I47: =(LG26V[[#This Row],["J" PRECIO VENTA ]]/LG26V[[#This Row],[BARRAS]]) -> 93.333333 | J47: =(LG26V[[#This Row],["J"PRECIO COMPRA ]]/LG26V[[#This Row],[BARRAS]]) -> 23 | K47: =SUMIF(entradas26[CODIGO],LG26V[[#This Row],[CODIGO ]],entradas26[[CAN JUEGOS ]]) -> 0 | L47: =SUMIF(entradas26[CODIGO],LG26V[[#This Row],[CODIGO ]],entradas26[CAN BARRAS]) -> 0 | M47: =SUMIF(salidas26[[CODIGO ]],LG26V[[#This Row],[CODIGO ]],salidas26[[CANT JUEGOS ]]) -> 2 | N47: =SUMIF(salidas26[[CODIGO ]],LG26V[[#This Row],[CODIGO ]],salidas26[CANT BARRAS]) -> 0 | O47: =(LG26V[[#This Row],["J"PRECIO COMPRA ]]*LG26V[[#This Row],[STOCK JUEGOS]]) -> 690 | P47: =(LG26V[[#This Row],["J" PRECIO VENTA ]]*LG26V[[#This Row],[STOCK JUEGOS]]) -> 2800 | Q47: =(LG26V[[#This Row],["B"PRECIO COMPRA]]*LG26V[[#This Row],[STOCK BARRAS]]) -> 46 | R47: =(LG26V[[#This Row],["B"PRECIO VENTA ]]*LG26V[[#This Row],[STOCK BARRAS]]) -> 186.66667 | S47: 12 | T47: 2 | U47: 6.2 | W47: XLM-1262
A48: 44 | B48: 1112 | C48: 55 SM8100 2B | D48: =(LG26V[[#This Row],[CANTIDAD INICIAL JUEGO ]]+LG26V[[#This Row],[ENTRADAS JUEGOS ]]-LG26V[[#This Row],[SALIDAS JUEGOS]]) -> 6 | E48: =(LG26V[[#This Row],[CANTIDAD INICIAL BARRAS]]+LG26V[[#This Row],[ENTRADAS BARRAS]]-LG26V[[#This Row],[SALIDA BARRAS]]) -> 1 | F48: 400 | G48: 180 | H48: 2 | I48: =(LG26V[[#This Row],["J" PRECIO VENTA ]]/LG26V[[#This Row],[BARRAS]]) -> 200 | J48: =(LG26V[[#This Row],["J"PRECIO COMPRA ]]/LG26V[[#This Row],[BARRAS]]) -> 90 | K48: =SUMIF(entradas26[CODIGO],LG26V[[#This Row],[CODIGO ]],entradas26[[CAN JUEGOS ]]) -> 0 | L48: =SUMIF(entradas26[CODIGO],LG26V[[#This Row],[CODIGO ]],entradas26[CAN BARRAS]) -> 0 | M48: =SUMIF(salidas26[[CODIGO ]],LG26V[[#This Row],[CODIGO ]],salidas26[[CANT JUEGOS ]]) -> 0 | N48: =SUMIF(salidas26[[CODIGO ]],LG26V[[#This Row],[CODIGO ]],salidas26[CANT BARRAS]) -> 0 | O48: =(LG26V[[#This Row],["J"PRECIO COMPRA ]]*LG26V[[#This Row],[STOCK JUEGOS]]) -> 1080 | P48: =(LG26V[[#This Row],["J" PRECIO VENTA ]]*LG26V[[#This Row],[STOCK JUEGOS]]) -> 2400 | Q48: =(LG26V[[#This Row],["B"PRECIO COMPRA]]*LG26V[[#This Row],[STOCK BARRAS]]) -> 90 | R48: =(LG26V[[#This Row],["B"PRECIO VENTA ]]*LG26V[[#This Row],[STOCK BARRAS]]) -> 200 | S48: 6 | T48: 1 | U48: 8.5 | W48: XLM-W0857
A49: 45 | B49: 1114 | C49: 55LA6600/2B | D49: =(LG26V[[#This Row],[CANTIDAD INICIAL JUEGO ]]+LG26V[[#This Row],[ENTRADAS JUEGOS ]]-LG26V[[#This Row],[SALIDAS JUEGOS]]) -> 16 | E49: =(LG26V[[#This Row],[CANTIDAD INICIAL BARRAS]]+LG26V[[#This Row],[ENTRADAS BARRAS]]-LG26V[[#This Row],[SALIDA BARRAS]]) -> 0 | F49: 280 | G49: 53 | H49: 2 | I49: =(LG26V[[#This Row],["J" PRECIO VENTA ]]/LG26V[[#This Row],[BARRAS]]) -> 140 | J49: =(LG26V[[#This Row],["J"PRECIO COMPRA ]]/LG26V[[#This Row],[BARRAS]]) -> 26.5 | K49: =SUMIF(entradas26[CODIGO],LG26V[[#This Row],[CODIGO ]],entradas26[[CAN JUEGOS ]]) -> 0 | L49: =SUMIF(entradas26[CODIGO],LG26V[[#This Row],[CODIGO ]],entradas26[CAN BARRAS]) -> 0 | M49: =SUMIF(salidas26[[CODIGO ]],LG26V[[#This Row],[CODIGO ]],salidas26[[CANT JUEGOS ]]) -> 1 | N49: =SUMIF(salidas26[[CODIGO ]],LG26V[[#This Row],[CODIGO ]],salidas26[CANT BARRAS]) -> 0 | O49: =(LG26V[[#This Row],["J"PRECIO COMPRA ]]*LG26V[[#This Row],[STOCK JUEGOS]]) -> 848 | P49: =(LG26V[[#This Row],["J" PRECIO VENTA ]]*LG26V[[#This Row],[STOCK JUEGOS]]) -> 4480 | Q49: =(LG26V[[#This Row],["B"PRECIO COMPRA]]*LG26V[[#This Row],[STOCK BARRAS]]) -> 0 | R49: =(LG26V[[#This Row],["B"PRECIO VENTA ]]*LG26V[[#This Row],[STOCK BARRAS]]) -> 0 | S49: 17 | U49: 5.35 | W49: XLM-0725/0726
A50: 46 | B50: 1117 | C50: 55LB6500/10B/6V | D50: =(LG26V[[#This Row],[CANTIDAD INICIAL JUEGO ]]+LG26V[[#This Row],[ENTRADAS JUEGOS ]]-LG26V[[#This Row],[SALIDAS JUEGOS]]) -> 21 | E50: =(LG26V[[#This Row],[CANTIDAD INICIAL BARRAS]]+LG26V[[#This Row],[ENTRADAS BARRAS]]-LG26V[[#This Row],[SALIDA BARRAS]]) -> 0 | F50: 350 | G50: 263 | H50: 10 | I50: =(LG26V[[#This Row],["J" PRECIO VENTA ]]/LG26V[[#This Row],[BARRAS]]) -> 35 | J50: =(LG26V[[#This Row],["J"PRECIO COMPRA ]]/LG26V[[#This Row],[BARRAS]]) -> 26.3 | K50: =SUMIF(entradas26[CODIGO],LG26V[[#This Row],[CODIGO ]],entradas26[[CAN JUEGOS ]]) -> 20 | L50: =SUMIF(entradas26[CODIGO],LG26V[[#This Row],[CODIGO ]],entradas26[CAN BARRAS]) -> 0 | M50: =SUMIF(salidas26[[CODIGO ]],LG26V[[#This Row],[CODIGO ]],salidas26[[CANT JUEGOS ]]) -> 5 | N50: =SUMIF(salidas26[[CODIGO ]],LG26V[[#This Row],[CODIGO ]],salidas26[CANT BARRAS]) -> 0 | O50: =(LG26V[[#This Row],["J"PRECIO COMPRA ]]*LG26V[[#This Row],[STOCK JUEGOS]]) -> 5523 | P50: =(LG26V[[#This Row],["J" PRECIO VENTA ]]*LG26V[[#This Row],[STOCK JUEGOS]]) -> 7350 | Q50: =(LG26V[[#This Row],["B"PRECIO COMPRA]]*LG26V[[#This Row],[STOCK BARRAS]]) -> 0 | R50: =(LG26V[[#This Row],["B"PRECIO VENTA ]]*LG26V[[#This Row],[STOCK BARRAS]]) -> 0 | S50: 6 | U50: 9.45 | W50: XLM-0267/0268
A51: 47 | B51: 1120 | C51: 55LM6200/2B | D51: =(LG26V[[#This Row],[CANTIDAD INICIAL JUEGO ]]+LG26V[[#This Row],[ENTRADAS JUEGOS ]]-LG26V[[#This Row],[SALIDAS JUEGOS]]) -> 15 | E51: =(LG26V[[#This Row],[CANTIDAD INICIAL BARRAS]]+LG26V[[#This Row],[ENTRADAS BARRAS]]-LG26V[[#This Row],[SALIDA BARRAS]]) -> 1 | F51: 220 | G51: 84 | H51: 2 | I51: =(LG26V[[#This Row],["J" PRECIO VENTA ]]/LG26V[[#This Row],[BARRAS]]) -> 110 | J51: =(LG26V[[#This Row],["J"PRECIO COMPRA ]]/LG26V[[#This Row],[BARRAS]]) -> 42 | K51: =SUMIF(entradas26[CODIGO],LG26V[[#This Row],[CODIGO ]],entradas26[[CAN JUEGOS ]]) -> 0 | L51: =SUMIF(entradas26[CODIGO],LG26V[[#This Row],[CODIGO ]],entradas26[CAN BARRAS]) -> 0 | M51: =SUMIF(salidas26[[CODIGO ]],LG26V[[#This Row],[CODIGO ]],salidas26[[CANT JUEGOS ]]) -> 2 | N51: =SUMIF(salidas26[[CODIGO ]],LG26V[[#This Row],[CODIGO ]],salidas26[CANT BARRAS]) -> 0 | O51: =(LG26V[[#This Row],["J"PRECIO COMPRA ]]*LG26V[[#This Row],[STOCK JUEGOS]]) -> 1260 | P51: =(LG26V[[#This Row],["J" PRECIO VENTA ]]*LG26V[[#This Row],[STOCK JUEGOS]]) -> 3300 | Q51: =(LG26V[[#This Row],["B"PRECIO COMPRA]]*LG26V[[#This Row],[STOCK BARRAS]]) -> 42 | R51: =(LG26V[[#This Row],["B"PRECIO VENTA ]]*LG26V[[#This Row],[STOCK BARRAS]]) -> 110 | S51: 17 | T51: 1 | U51: 3.8 | W51: XLM-0170/0171
A52: 48 | B52: 1121 | C52: 55 LM8600 | D52: =(LG26V[[#This Row],[CANTIDAD INICIAL JUEGO ]]+LG26V[[#This Row],[ENTRADAS JUEGOS ]]-LG26V[[#This Row],[SALIDAS JUEGOS]]) -> 16 | E52: =(LG26V[[#This Row],[CANTIDAD INICIAL BARRAS]]+LG26V[[#This Row],[ENTRADAS BARRAS]]-LG26V[[#This Row],[SALIDA BARRAS]]) -> 0 | F52: 300 | G52: 117 | H52: 2 | I52: =(LG26V[[#This Row],["J" PRECIO VENTA ]]/LG26V[[#This Row],[BARRAS]]) -> 150 | J52: =(LG26V[[#This Row],["J"PRECIO COMPRA ]]/LG26V[[#This Row],[BARRAS]]) -> 58.5 | K52: =SUMIF(entradas26[CODIGO],LG26V[[#This Row],[CODIGO ]],entradas26[[CAN JUEGOS ]]) -> 0 | L52: =SUMIF(entradas26[CODIGO],LG26V[[#This Row],[CODIGO ]],entradas26[CAN BARRAS]) -> 0 | M52: =SUMIF(salidas26[[CODIGO ]],LG26V[[#This Row],[CODIGO ]],salidas26[[CANT JUEGOS ]]) -> 3 | N52: =SUMIF(salidas26[[CODIGO ]],LG26V[[#This Row],[CODIGO ]],salidas26[CANT BARRAS]) -> 0 | O52: =(LG26V[[#This Row],["J"PRECIO COMPRA ]]*LG26V[[#This Row],[STOCK JUEGOS]]) -> 1872 | P52: =(LG26V[[#This Row],["J" PRECIO VENTA ]]*LG26V[[#This Row],[STOCK JUEGOS]]) -> 4800 | Q52: =(LG26V[[#This Row],["B"PRECIO COMPRA]]*LG26V[[#This Row],[STOCK BARRAS]]) -> 0 | R52: =(LG26V[[#This Row],["B"PRECIO VENTA ]]*LG26V[[#This Row],[STOCK BARRAS]]) -> 0 | S52: 19 | U52: 5.3
A53: 49 | B53: 1123 | C53: 55 UB8300/2B | D53: =(LG26V[[#This Row],[CANTIDAD INICIAL JUEGO ]]+LG26V[[#This Row],[ENTRADAS JUEGOS ]]-LG26V[[#This Row],[SALIDAS JUEGOS]]) -> 16 | E53: =(LG26V[[#This Row],[CANTIDAD INICIAL BARRAS]]+LG26V[[#This Row],[ENTRADAS BARRAS]]-LG26V[[#This Row],[SALIDA BARRAS]]) -> 0 | F53: 320 | G53: 69 | H53: 2 | I53: =(LG26V[[#This Row],["J" PRECIO VENTA ]]/LG26V[[#This Row],[BARRAS]]) -> 160 | J53: =(LG26V[[#This Row],["J"PRECIO COMPRA ]]/LG26V[[#This Row],[BARRAS]]) -> 34.5 | K53: =SUMIF(entradas26[CODIGO],LG26V[[#This Row],[CODIGO ]],entradas26[[CAN JUEGOS ]]) -> 0 | L53: =SUMIF(entradas26[CODIGO],LG26V[[#This Row],[CODIGO ]],entradas26[CAN BARRAS]) -> 0 | M53: =SUMIF(salidas26[[CODIGO ]],LG26V[[#This Row],[CODIGO ]],salidas26[[CANT JUEGOS ]]) -> 3 | N53: =SUMIF(salidas26[[CODIGO ]],LG26V[[#This Row],[CODIGO ]],salidas26[CANT BARRAS]) -> 0 | O53: =(LG26V[[#This Row],["J"PRECIO COMPRA ]]*LG26V[[#This Row],[STOCK JUEGOS]]) -> 1104 | P53: =(LG26V[[#This Row],["J" PRECIO VENTA ]]*LG26V[[#This Row],[STOCK JUEGOS]]) -> 5120 | Q53: =(LG26V[[#This Row],["B"PRECIO COMPRA]]*LG26V[[#This Row],[STOCK BARRAS]]) -> 0 | R53: =(LG26V[[#This Row],["B"PRECIO VENTA ]]*LG26V[[#This Row],[STOCK BARRAS]]) -> 0 | S53: 19 | U53: 4.9
A54: 50 | B54: 1126 | C54: 55UH6150/2B | D54: =(LG26V[[#This Row],[CANTIDAD INICIAL JUEGO ]]+LG26V[[#This Row],[ENTRADAS JUEGOS ]]-LG26V[[#This Row],[SALIDAS JUEGOS]]) -> 21 | E54: =(LG26V[[#This Row],[CANTIDAD INICIAL BARRAS]]+LG26V[[#This Row],[ENTRADAS BARRAS]]-LG26V[[#This Row],[SALIDA BARRAS]]) -> 0 | F54: 260 | G54: 70 | H54: 2 | I54: =(LG26V[[#This Row],["J" PRECIO VENTA ]]/LG26V[[#This Row],[BARRAS]]) -> 130 | J54: =(LG26V[[#This Row],["J"PRECIO COMPRA ]]/LG26V[[#This Row],[BARRAS]]) -> 35 | K54: =SUMIF(entradas26[CODIGO],LG26V[[#This Row],[CODIGO ]],entradas26[[CAN JUEGOS ]]) -> 20 | L54: =SUMIF(entradas26[CODIGO],LG26V[[#This Row],[CODIGO ]],entradas26[CAN BARRAS]) -> 0 | M54: =SUMIF(salidas26[[CODIGO ]],LG26V[[#This Row],[CODIGO ]],salidas26[[CANT JUEGOS ]]) -> 2 | N54: =SUMIF(salidas26[[CODIGO ]],LG26V[[#This Row],[CODIGO ]],salidas26[CANT BARRAS]) -> 0 | O54: =(LG26V[[#This Row],["J"PRECIO COMPRA ]]*LG26V[[#This Row],[STOCK JUEGOS]]) -> 1470 | P54: =(LG26V[[#This Row],["J" PRECIO VENTA ]]*LG26V[[#This Row],[STOCK JUEGOS]]) -> 5460 | Q54: =(LG26V[[#This Row],["B"PRECIO COMPRA]]*LG26V[[#This Row],[STOCK BARRAS]]) -> 0 | R54: =(LG26V[[#This Row],["B"PRECIO VENTA ]]*LG26V[[#This Row],[STOCK BARRAS]]) -> 0 | S54: 3 | U54: 304 | W54: XLM-0174/0175
A55: 51 | B55: 1129 | C55: 55UH6500/2B | D55: =(LG26V[[#This Row],[CANTIDAD INICIAL JUEGO ]]+LG26V[[#This Row],[ENTRADAS JUEGOS ]]-LG26V[[#This Row],[SALIDAS JUEGOS]]) -> 18 | E55: =(LG26V[[#This Row],[CANTIDAD INICIAL BARRAS]]+LG26V[[#This Row],[ENTRADAS BARRAS]]-LG26V[[#This Row],[SALIDA BARRAS]]) -> 0 | F55: 260 | G55: 42 | H55: 2 | I55: =(LG26V[[#This Row],["J" PRECIO VENTA ]]/LG26V[[#This Row],[BARRAS]]) -> 130 | J55: =(LG26V[[#This Row],["J"PRECIO COMPRA ]]/LG26V[[#This Row],[BARRAS]]) -> 21 | K55: =SUMIF(entradas26[CODIGO],LG26V[[#This Row],[CODIGO ]],entradas26[[CAN JUEGOS ]]) -> 0 | L55: =SUMIF(entradas26[CODIGO],LG26V[[#This Row],[CODIGO ]],entradas26[CAN BARRAS]) -> 0 | M55: =SUMIF(salidas26[[CODIGO ]],LG26V[[#This Row],[CODIGO ]],salidas26[[CANT JUEGOS ]]) -> 1 | N55: =SUMIF(salidas26[[CODIGO ]],LG26V[[#This Row],[CODIGO ]],salidas26[CANT BARRAS]) -> 0 | O55: =(LG26V[[#This Row],["J"PRECIO COMPRA ]]*LG26V[[#This Row],[STOCK JUEGOS]]) -> 756 | P55: =(LG26V[[#This Row],["J" PRECIO VENTA ]]*LG26V[[#This Row],[STOCK JUEGOS]]) -> 4680 | Q55: =(LG26V[[#This Row],["B"PRECIO COMPRA]]*LG26V[[#This Row],[STOCK BARRAS]]) -> 0 | R55: =(LG26V[[#This Row],["B"PRECIO VENTA ]]*LG26V[[#This Row],[STOCK BARRAS]]) -> 0 | S55: 19 | U55: 4.25 | W55: XLM-1021/1022
A56: 52 | B56: 1132 | C56: 55UH8500/2B | D56: =(LG26V[[#This Row],[CANTIDAD INICIAL JUEGO ]]+LG26V[[#This Row],[ENTRADAS JUEGOS ]]-LG26V[[#This Row],[SALIDAS JUEGOS]]) -> 20 | E56: =(LG26V[[#This Row],[CANTIDAD INICIAL BARRAS]]+LG26V[[#This Row],[ENTRADAS BARRAS]]-LG26V[[#This Row],[SALIDA BARRAS]]) -> 0 | F56: 260 | G56: 124 | H56: 2 | I56: =(LG26V[[#This Row],["J" PRECIO VENTA ]]/LG26V[[#This Row],[BARRAS]]) -> 130 | J56: =(LG26V[[#This Row],["J"PRECIO COMPRA ]]/LG26V[[#This Row],[BARRAS]]) -> 62 | K56: =SUMIF(entradas26[CODIGO],LG26V[[#This Row],[CODIGO ]],entradas26[[CAN JUEGOS ]]) -> 0 | L56: =SUMIF(entradas26[CODIGO],LG26V[[#This Row],[CODIGO ]],entradas26[CAN BARRAS]) -> 0 | M56: =SUMIF(salidas26[[CODIGO ]],LG26V[[#This Row],[CODIGO ]],salidas26[[CANT JUEGOS ]]) -> 6 | N56: =SUMIF(salidas26[[CODIGO ]],LG26V[[#This Row],[CODIGO ]],salidas26[CANT BARRAS]) -> 0 | O56: =(LG26V[[#This Row],["J"PRECIO COMPRA ]]*LG26V[[#This Row],[STOCK JUEGOS]]) -> 2480 | P56: =(LG26V[[#This Row],["J" PRECIO VENTA ]]*LG26V[[#This Row],[STOCK JUEGOS]]) -> 5200 | Q56: =(LG26V[[#This Row],["B"PRECIO COMPRA]]*LG26V[[#This Row],[STOCK BARRAS]]) -> 0 | R56: =(LG26V[[#This Row],["B"PRECIO VENTA ]]*LG26V[[#This Row],[STOCK BARRAS]]) -> 0 | S56: 26 | U56: 6.2 | W56: XLM-W1196
A57: 53 | B57: 1135 | C57: 55LA6200 POLA-14B/3V | D57: =(LG26V[[#This Row],[CANTIDAD INICIAL JUEGO ]]+LG26V[[#This Row],[ENTRADAS JUEGOS ]]-LG26V[[#This Row],[SALIDAS JUEGOS]]) -> 23 | E57: =(LG26V[[#This Row],[CANTIDAD INICIAL BARRAS]]+LG26V[[#This Row],[ENTRADAS BARRAS]]-LG26V[[#This Row],[SALIDA BARRAS]]) -> 0 | F57: 380 | G57: 261 | H57: 14 | I57: =(LG26V[[#This Row],["J" PRECIO VENTA ]]/LG26V[[#This Row],[BARRAS]]) -> 27.142857 | J57: =(LG26V[[#This Row],["J"PRECIO COMPRA ]]/LG26V[[#This Row],[BARRAS]]) -> 18.642857 | K57: =SUMIF(entradas26[CODIGO],LG26V[[#This Row],[CODIGO ]],entradas26[[CAN JUEGOS ]]) -> 0 | L57: =SUMIF(entradas26[CODIGO],LG26V[[#This Row],[CODIGO ]],entradas26[CAN BARRAS]) -> 0 | M57: =SUMIF(salidas26[[CODIGO ]],LG26V[[#This Row],[CODIGO ]],salidas26[[CANT JUEGOS ]]) -> 0 | N57: =SUMIF(salidas26[[CODIGO ]],LG26V[[#This Row],[CODIGO ]],salidas26[CANT BARRAS]) -> 0 | O57: =(LG26V[[#This Row],["J"PRECIO COMPRA ]]*LG26V[[#This Row],[STOCK JUEGOS]]) -> 6003 | P57: =(LG26V[[#This Row],["J" PRECIO VENTA ]]*LG26V[[#This Row],[STOCK JUEGOS]]) -> 8740 | Q57: =(LG26V[[#This Row],["B"PRECIO COMPRA]]*LG26V[[#This Row],[STOCK BARRAS]]) -> 0 | R57: =(LG26V[[#This Row],["B"PRECIO VENTA ]]*LG26V[[#This Row],[STOCK BARRAS]]) -> 0 | S57: 23 | U57: 12 | W57: XLM-0281/0282
A58: 54 | B58: 1138 | C58: 55UJ6300-55LJ5500/10B | D58: =(LG26V[[#This Row],[CANTIDAD INICIAL JUEGO ]]+LG26V[[#This Row],[ENTRADAS JUEGOS ]]-LG26V[[#This Row],[SALIDAS JUEGOS]]) -> 13 | E58: =(LG26V[[#This Row],[CANTIDAD INICIAL BARRAS]]+LG26V[[#This Row],[ENTRADAS BARRAS]]-LG26V[[#This Row],[SALIDA BARRAS]]) -> 0 | F58: 280 | G58: 196 | H58: 10 | I58: =(LG26V[[#This Row],["J" PRECIO VENTA ]]/LG26V[[#This Row],[BARRAS]]) -> 28 | J58: =(LG26V[[#This Row],["J"PRECIO COMPRA ]]/LG26V[[#This Row],[BARRAS]]) -> 19.6 | K58: =SUMIF(entradas26[CODIGO],LG26V[[#This Row],[CODIGO ]],entradas26[[CAN JUEGOS ]]) -> 0 | L58: =SUMIF(entradas26[CODIGO],LG26V[[#This Row],[CODIGO ]],entradas26[CAN BARRAS]) -> 0 | M58: =SUMIF(salidas26[[CODIGO ]],LG26V[[#This Row],[CODIGO ]],salidas26[[CANT JUEGOS ]]) -> 4 | N58: =SUMIF(salidas26[[CODIGO ]],LG26V[[#This Row],[CODIGO ]],salidas26[CANT BARRAS]) -> 0 | O58: =(LG26V[[#This Row],["J"PRECIO COMPRA ]]*LG26V[[#This Row],[STOCK JUEGOS]]) -> 2548 | P58: =(LG26V[[#This Row],["J" PRECIO VENTA ]]*LG26V[[#This Row],[STOCK JUEGOS]]) -> 3640 | Q58: =(LG26V[[#This Row],["B"PRECIO COMPRA]]*LG26V[[#This Row],[STOCK BARRAS]]) -> 0 | R58: =(LG26V[[#This Row],["B"PRECIO VENTA ]]*LG26V[[#This Row],[STOCK BARRAS]]) -> 0 | S58: 17 | U58: 6.3 | W58: XLM-0599/0598
A59: 55 | B59: 1139 | C59: 55 UM 8L 4B EL JUEGO | D59: =(LG26V[[#This Row],[CANTIDAD INICIAL JUEGO ]]+LG26V[[#This Row],[ENTRADAS JUEGOS ]]-LG26V[[#This Row],[SALIDAS JUEGOS]]) -> 12 | E59: =(LG26V[[#This Row],[CANTIDAD INICIAL BARRAS]]+LG26V[[#This Row],[ENTRADAS BARRAS]]-LG26V[[#This Row],[SALIDA BARRAS]]) -> 0 | F59: 320 | G59: 151 | H59: 4 | I59: =(LG26V[[#This Row],["J" PRECIO VENTA ]]/LG26V[[#This Row],[BARRAS]]) -> 80 | J59: =(LG26V[[#This Row],["J"PRECIO COMPRA ]]/LG26V[[#This Row],[BARRAS]]) -> 37.75 | K59: =SUMIF(entradas26[CODIGO],LG26V[[#This Row],[CODIGO ]],entradas26[[CAN JUEGOS ]]) -> 0 | L59: =SUMIF(entradas26[CODIGO],LG26V[[#This Row],[CODIGO ]],entradas26[CAN BARRAS]) -> 0 | M59: =SUMIF(salidas26[[CODIGO ]],LG26V[[#This Row],[CODIGO ]],salidas26[[CANT JUEGOS ]]) -> 3 | N59: =SUMIF(salidas26[[CODIGO ]],LG26V[[#This Row],[CODIGO ]],salidas26[CANT BARRAS]) -> 0 | O59: =(LG26V[[#This Row],["J"PRECIO COMPRA ]]*LG26V[[#This Row],[STOCK JUEGOS]]) -> 1812 | P59: =(LG26V[[#This Row],["J" PRECIO VENTA ]]*LG26V[[#This Row],[STOCK JUEGOS]]) -> 3840 | Q59: =(LG26V[[#This Row],["B"PRECIO COMPRA]]*LG26V[[#This Row],[STOCK BARRAS]]) -> 0 | R59: =(LG26V[[#This Row],["B"PRECIO VENTA ]]*LG26V[[#This Row],[STOCK BARRAS]]) -> 0 | S59: 15 | U59: 6.85 | W59: XLM1204
A60: 56 | B60: 1141 | C60: 60LB6500/12B/6V | D60: =(LG26V[[#This Row],[CANTIDAD INICIAL JUEGO ]]+LG26V[[#This Row],[ENTRADAS JUEGOS ]]-LG26V[[#This Row],[SALIDAS JUEGOS]]) -> 2 | E60: =(LG26V[[#This Row],[CANTIDAD INICIAL BARRAS]]+LG26V[[#This Row],[ENTRADAS BARRAS]]-LG26V[[#This Row],[SALIDA BARRAS]]) -> 11 | F60: 450 | G60: 244 | H60: 12 | I60: =(LG26V[[#This Row],["J" PRECIO VENTA ]]/LG26V[[#This Row],[BARRAS]]) -> 37.5 | J60: =(LG26V[[#This Row],["J"PRECIO COMPRA ]]/LG26V[[#This Row],[BARRAS]]) -> 20.333333 | K60: =SUMIF(entradas26[CODIGO],LG26V[[#This Row],[CODIGO ]],entradas26[[CAN JUEGOS ]]) -> 0 | L60: =SUMIF(entradas26[CODIGO],LG26V[[#This Row],[CODIGO ]],entradas26[CAN BARRAS]) -> 0 | M60: =SUMIF(salidas26[[CODIGO ]],LG26V[[#This Row],[CODIGO ]],salidas26[[CANT JUEGOS ]]) -> 3 | N60: =SUMIF(salidas26[[CODIGO ]],LG26V[[#This Row],[CODIGO ]],salidas26[CANT BARRAS]) -> 0 | O60: =(LG26V[[#This Row],["J"PRECIO COMPRA ]]*LG26V[[#This Row],[STOCK JUEGOS]]) -> 488 | P60: =(LG26V[[#This Row],["J" PRECIO VENTA ]]*LG26V[[#This Row],[STOCK JUEGOS]]) -> 900 | Q60: =(LG26V[[#This Row],["B"PRECIO COMPRA]]*LG26V[[#This Row],[STOCK BARRAS]]) -> 223.66667 | R60: =(LG26V[[#This Row],["B"PRECIO VENTA ]]*LG26V[[#This Row],[STOCK BARRAS]]) -> 412.5 | S60: 5 | T60: 11 | U60: 10.6 | W60: XY-0009-SE
A61: 57 | B61: 1144 | C61: 60 UJ6300/ 10B | D61: =(LG26V[[#This Row],[CANTIDAD INICIAL JUEGO ]]+LG26V[[#This Row],[ENTRADAS JUEGOS ]]-LG26V[[#This Row],[SALIDAS JUEGOS]]) -> 17 | E61: =(LG26V[[#This Row],[CANTIDAD INICIAL BARRAS]]+LG26V[[#This Row],[ENTRADAS BARRAS]]-LG26V[[#This Row],[SALIDA BARRAS]]) -> 0 | F61: 400 | G61: 188 | H61: 10 | I61: =(LG26V[[#This Row],["J" PRECIO VENTA ]]/LG26V[[#This Row],[BARRAS]]) -> 40 | J61: =(LG26V[[#This Row],["J"PRECIO COMPRA ]]/LG26V[[#This Row],[BARRAS]]) -> 18.8 | K61: =SUMIF(entradas26[CODIGO],LG26V[[#This Row],[CODIGO ]],entradas26[[CAN JUEGOS ]]) -> 0 | L61: =SUMIF(entradas26[CODIGO],LG26V[[#This Row],[CODIGO ]],entradas26[CAN BARRAS]) -> 0 | M61: =SUMIF(salidas26[[CODIGO ]],LG26V[[#This Row],[CODIGO ]],salidas26[[CANT JUEGOS ]]) -> 1 | N61: =SUMIF(salidas26[[CODIGO ]],LG26V[[#This Row],[CODIGO ]],salidas26[CANT BARRAS]) -> 0 | O61: =(LG26V[[#This Row],["J"PRECIO COMPRA ]]*LG26V[[#This Row],[STOCK JUEGOS]]) -> 3196 | P61: =(LG26V[[#This Row],["J" PRECIO VENTA ]]*LG26V[[#This Row],[STOCK JUEGOS]]) -> 6800 | Q61: =(LG26V[[#This Row],["B"PRECIO COMPRA]]*LG26V[[#This Row],[STOCK BARRAS]]) -> 0 | R61: =(LG26V[[#This Row],["B"PRECIO VENTA ]]*LG26V[[#This Row],[STOCK BARRAS]]) -> 0 | S61: 18 | U61: 8.6 | W61: XLM-0740/0741/0742/0743
A62: 58 | B62: 1147 | C62: 65UJ6300/12B | D62: =(LG26V[[#This Row],[CANTIDAD INICIAL JUEGO ]]+LG26V[[#This Row],[ENTRADAS JUEGOS ]]-LG26V[[#This Row],[SALIDAS JUEGOS]]) -> 10 | E62: =(LG26V[[#This Row],[CANTIDAD INICIAL BARRAS]]+LG26V[[#This Row],[ENTRADAS BARRAS]]-LG26V[[#This Row],[SALIDA BARRAS]]) -> 11 | F62: 420 | G62: 222 | H62: 12 | I62: =(LG26V[[#This Row],["J" PRECIO VENTA ]]/LG26V[[#This Row],[BARRAS]]) -> 35 | J62: =(LG26V[[#This Row],["J"PRECIO COMPRA ]]/LG26V[[#This Row],[BARRAS]]) -> 18.5 | K62: =SUMIF(entradas26[CODIGO],LG26V[[#This Row],[CODIGO ]],entradas26[[CAN JUEGOS ]]) -> 0 | L62: =SUMIF(entradas26[CODIGO],LG26V[[#This Row],[CODIGO ]],entradas26[CAN BARRAS]) -> 0 | M62: =SUMIF(salidas26[[CODIGO ]],LG26V[[#This Row],[CODIGO ]],salidas26[[CANT JUEGOS ]]) -> 0 | N62: =SUMIF(salidas26[[CODIGO ]],LG26V[[#This Row],[CODIGO ]],salidas26[CANT BARRAS]) -> 0 | O62: =(LG26V[[#This Row],["J"PRECIO COMPRA ]]*LG26V[[#This Row],[STOCK JUEGOS]]) -> 2220 | P62: =(LG26V[[#This Row],["J" PRECIO VENTA ]]*LG26V[[#This Row],[STOCK JUEGOS]]) -> 4200 | Q62: =(LG26V[[#This Row],["B"PRECIO COMPRA]]*LG26V[[#This Row],[STOCK BARRAS]]) -> 203.5 | R62: =(LG26V[[#This Row],["B"PRECIO VENTA ]]*LG26V[[#This Row],[STOCK BARRAS]]) -> 385 | S62: 10 | T62: 11 | U62: 9.5 | W62: XLM-0636/0637/0638/0639
A63: 59 | B63: 1148 | C63: 65 SM8100 2B/6V EGDE | D63: =(LG26V[[#This Row],[CANTIDAD INICIAL JUEGO ]]+LG26V[[#This Row],[ENTRADAS JUEGOS ]]-LG26V[[#This Row],[SALIDAS JUEGOS]]) -> 9 | E63: =(LG26V[[#This Row],[CANTIDAD INICIAL BARRAS]]+LG26V[[#This Row],[ENTRADAS BARRAS]]-LG26V[[#This Row],[SALIDA BARRAS]]) -> 0 | F63: 500 | G63: 187 | H63: 2 | I63: =(LG26V[[#This Row],["J" PRECIO VENTA ]]/LG26V[[#This Row],[BARRAS]]) -> 250 | J63: =(LG26V[[#This Row],["J"PRECIO COMPRA ]]/LG26V[[#This Row],[BARRAS]]) -> 93.5 | K63: =SUMIF(entradas26[CODIGO],LG26V[[#This Row],[CODIGO ]],entradas26[[CAN JUEGOS ]]) -> 0 | L63: =SUMIF(entradas26[CODIGO],LG26V[[#This Row],[CODIGO ]],entradas26[CAN BARRAS]) -> 0 | M63: =SUMIF(salidas26[[CODIGO ]],LG26V[[#This Row],[CODIGO ]],salidas26[[CANT JUEGOS ]]) -> 0 | N63: =SUMIF(salidas26[[CODIGO ]],LG26V[[#This Row],[CODIGO ]],salidas26[CANT BARRAS]) -> 0 | O63: =(LG26V[[#This Row],["J"PRECIO COMPRA ]]*LG26V[[#This Row],[STOCK JUEGOS]]) -> 1683 | P63: =(LG26V[[#This Row],["J" PRECIO VENTA ]]*LG26V[[#This Row],[STOCK JUEGOS]]) -> 4500 | Q63: =(LG26V[[#This Row],["B"PRECIO COMPRA]]*LG26V[[#This Row],[STOCK BARRAS]]) -> 0 | R63: =(LG26V[[#This Row],["B"PRECIO VENTA ]]*LG26V[[#This Row],[STOCK BARRAS]]) -> 0 | S63: 9 | U63: 8.85 | W63: XLM-W1547
A64: 60 | B64: 1149 | C64: 65 SJ8000 2B | D64: =(LG26V[[#This Row],[CANTIDAD INICIAL JUEGO ]]+LG26V[[#This Row],[ENTRADAS JUEGOS ]]-LG26V[[#This Row],[SALIDAS JUEGOS]]) -> 2 | E64: =(LG26V[[#This Row],[CANTIDAD INICIAL BARRAS]]+LG26V[[#This Row],[ENTRADAS BARRAS]]-LG26V[[#This Row],[SALIDA BARRAS]]) -> 0 | F64: 500 | G64: 350 | H64: 2 | I64: =(LG26V[[#This Row],["J" PRECIO VENTA ]]/LG26V[[#This Row],[BARRAS]]) -> 250 | J64: =(LG26V[[#This Row],["J"PRECIO COMPRA ]]/LG26V[[#This Row],[BARRAS]]) -> 175 | K64: =SUMIF(entradas26[CODIGO],LG26V[[#This Row],[CODIGO ]],entradas26[[CAN JUEGOS ]]) -> 0 | L64: =SUMIF(entradas26[CODIGO],LG26V[[#This Row],[CODIGO ]],entradas26[CAN BARRAS]) -> 0 | M64: =SUMIF(salidas26[[CODIGO ]],LG26V[[#This Row],[CODIGO ]],salidas26[[CANT JUEGOS ]]) -> 0 | N64: =SUMIF(salidas26[[CODIGO ]],LG26V[[#This Row],[CODIGO ]],salidas26[CANT BARRAS]) -> 0 | O64: =(LG26V[[#This Row],["J"PRECIO COMPRA ]]*LG26V[[#This Row],[STOCK JUEGOS]]) -> 700 | P64: =(LG26V[[#This Row],["J" PRECIO VENTA ]]*LG26V[[#This Row],[STOCK JUEGOS]]) -> 1000 | Q64: =(LG26V[[#This Row],["B"PRECIO COMPRA]]*LG26V[[#This Row],[STOCK BARRAS]]) -> 0 | R64: =(LG26V[[#This Row],["B"PRECIO VENTA ]]*LG26V[[#This Row],[STOCK BARRAS]]) -> 0 | S64: 2
A65: 61 | B65: 1150 | C65: 65UK6300 /4B | D65: =(LG26V[[#This Row],[CANTIDAD INICIAL JUEGO ]]+LG26V[[#This Row],[ENTRADAS JUEGOS ]]-LG26V[[#This Row],[SALIDAS JUEGOS]]) -> 10 | E65: =(LG26V[[#This Row],[CANTIDAD INICIAL BARRAS]]+LG26V[[#This Row],[ENTRADAS BARRAS]]-LG26V[[#This Row],[SALIDA BARRAS]]) -> 3 | F65: 450 | G65: 155 | H65: 4 | I65: =(LG26V[[#This Row],["J" PRECIO VENTA ]]/LG26V[[#This Row],[BARRAS]]) -> 112.5 | J65: =(LG26V[[#This Row],["J"PRECIO COMPRA ]]/LG26V[[#This Row],[BARRAS]]) -> 38.75 | K65: =SUMIF(entradas26[CODIGO],LG26V[[#This Row],[CODIGO ]],entradas26[[CAN JUEGOS ]]) -> 0 | L65: =SUMIF(entradas26[CODIGO],LG26V[[#This Row],[CODIGO ]],entradas26[CAN BARRAS]) -> 0 | M65: =SUMIF(salidas26[[CODIGO ]],LG26V[[#This Row],[CODIGO ]],salidas26[[CANT JUEGOS ]]) -> 0 | N65: =SUMIF(salidas26[[CODIGO ]],LG26V[[#This Row],[CODIGO ]],salidas26[CANT BARRAS]) -> 0 | O65: =(LG26V[[#This Row],["J"PRECIO COMPRA ]]*LG26V[[#This Row],[STOCK JUEGOS]]) -> 1550 | P65: =(LG26V[[#This Row],["J" PRECIO VENTA ]]*LG26V[[#This Row],[STOCK JUEGOS]]) -> 4500 | Q65: =(LG26V[[#This Row],["B"PRECIO COMPRA]]*LG26V[[#This Row],[STOCK BARRAS]]) -> 116.25 | R65: =(LG26V[[#This Row],["B"PRECIO VENTA ]]*LG26V[[#This Row],[STOCK BARRAS]]) -> 337.5 | S65: 10 | T65: 3 | U65: 5.9 | W65: XLM-0987
A66: 62 | B66: 1153 | C66: 70LB7200 LG 6-4-6 L/6V 24 B | D66: =(LG26V[[#This Row],[CANTIDAD INICIAL JUEGO ]]+LG26V[[#This Row],[ENTRADAS JUEGOS ]]-LG26V[[#This Row],[SALIDAS JUEGOS]]) -> 4 | E66: =(LG26V[[#This Row],[CANTIDAD INICIAL BARRAS]]+LG26V[[#This Row],[ENTRADAS BARRAS]]-LG26V[[#This Row],[SALIDA BARRAS]]) -> 0 | F66: 1200 | G66: 439 | H66: 24 | I66: =(LG26V[[#This Row],["J" PRECIO VENTA ]]/LG26V[[#This Row],[BARRAS]]) -> 50 | J66: =(LG26V[[#This Row],["J"PRECIO COMPRA ]]/LG26V[[#This Row],[BARRAS]]) -> 18.291667 | K66: =SUMIF(entradas26[CODIGO],LG26V[[#This Row],[CODIGO ]],entradas26[[CAN JUEGOS ]]) -> 0 | L66: =SUMIF(entradas26[CODIGO],LG26V[[#This Row],[CODIGO ]],entradas26[CAN BARRAS]) -> 0 | M66: =SUMIF(salidas26[[CODIGO ]],LG26V[[#This Row],[CODIGO ]],salidas26[[CANT JUEGOS ]]) -> 0 | N66: =SUMIF(salidas26[[CODIGO ]],LG26V[[#This Row],[CODIGO ]],salidas26[CANT BARRAS]) -> 0 | O66: =(LG26V[[#This Row],["J"PRECIO COMPRA ]]*LG26V[[#This Row],[STOCK JUEGOS]]) -> 1756 | P66: =(LG26V[[#This Row],["J" PRECIO VENTA ]]*LG26V[[#This Row],[STOCK JUEGOS]]) -> 4800 | Q66: =(LG26V[[#This Row],["B"PRECIO COMPRA]]*LG26V[[#This Row],[STOCK BARRAS]]) -> 0 | R66: =(LG26V[[#This Row],["B"PRECIO VENTA ]]*LG26V[[#This Row],[STOCK BARRAS]]) -> 0 | S66: 4 | U66: 31.34
B67: 1154 | C67: 86Q9050- 86UP8770 | D67: =(LG26V[[#This Row],[CANTIDAD INICIAL JUEGO ]]+LG26V[[#This Row],[ENTRADAS JUEGOS ]]-LG26V[[#This Row],[SALIDAS JUEGOS]]) -> 5 | E67: =(LG26V[[#This Row],[CANTIDAD INICIAL BARRAS]]+LG26V[[#This Row],[ENTRADAS BARRAS]]-LG26V[[#This Row],[SALIDA BARRAS]]) -> 0 | F67: 1500 | G67: 551 | I67: =(LG26V[[#This Row],["J" PRECIO VENTA ]]/LG26V[[#This Row],[BARRAS]]) -> #DIV/0! | J67: =(LG26V[[#This Row],["J"PRECIO COMPRA ]]/LG26V[[#This Row],[BARRAS]]) -> #DIV/0! | K67: =SUMIF(entradas26[CODIGO],LG26V[[#This Row],[CODIGO ]],entradas26[[CAN JUEGOS ]]) -> 5 | L67: =SUMIF(entradas26[CODIGO],LG26V[[#This Row],[CODIGO ]],entradas26[CAN BARRAS]) -> 0 | M67: =SUMIF(salidas26[[CODIGO ]],LG26V[[#This Row],[CODIGO ]],salidas26[[CANT JUEGOS ]]) -> 0 | N67: =SUMIF(salidas26[[CODIGO ]],LG26V[[#This Row],[CODIGO ]],salidas26[CANT BARRAS]) -> 0 | O67: =(LG26V[[#This Row],["J"PRECIO COMPRA ]]*LG26V[[#This Row],[STOCK JUEGOS]]) -> 2755 | P67: =(LG26V[[#This Row],["J" PRECIO VENTA ]]*LG26V[[#This Row],[STOCK JUEGOS]]) -> 7500 | Q67: =(LG26V[[#This Row],["B"PRECIO COMPRA]]*LG26V[[#This Row],[STOCK BARRAS]]) -> #DIV/0! | R67: =(LG26V[[#This Row],["B"PRECIO VENTA ]]*LG26V[[#This Row],[STOCK BARRAS]]) -> #DIV/0! | S67: 0 | U67: 29 | W67: XLM-W2622

Sheet SAMSUNG
B2: SAMSUNG
B4: CODIGO | C4: DESCRIPCION | D4: STOCK JUEGOS | E4: STOCK BARRAS | F4: "J" PRECIO VENTA | G4: "J"PRECIO COMPRA | H4: BARRAS | I4: "B"PRECIO VENTA | J4: "B"PRECIO COMPRA | K4: ENTRADAS JUEGOS | L4: ENTRADAS BARRAS | M4: SALIDAS JUEGOS | N4: SALIDA BARRAS | O4: CAPITAL JUEGOS | P4: CAPITAL/GANANCIA/JUEGOS | Q4: CAPITAL BARRA | R4: CAP GAN BARRAS | S4: CANTIDAD INICIAL JUEGO | T4: CANTIDAD INICIAL BARRAS | U4: PRECIO EN $ | V4: CODIGO 2 | W4: CODIGO 3 | X4: CODIGO 4
A5: 1 | B5: 2000 | C5: UN32FH4005G-UN32JH4005G CUERNITO 2B | D5: =(samgung26[[#This Row],[CANTIDAD INICIAL JUEGO ]]+samgung26[[#This Row],[ENTRADAS JUEGOS ]]-samgung26[[#This Row],[SALIDAS JUEGOS]]) -> 4 | E5: =(samgung26[[#This Row],[CANTIDAD INICIAL BARRAS]]+samgung26[[#This Row],[ENTRADAS BARRAS]]-samgung26[[#This Row],[SALIDA BARRAS]]) -> 1 | F5: 80 | G5: 37 | H5: 2 | I5: =(samgung26[[#This Row],["J" PRECIO VENTA ]]/samgung26[[#This Row],[BARRAS]]) -> 40 | J5: =(samgung26[[#This Row],["J"PRECIO COMPRA ]]/samgung26[[#This Row],[BARRAS]]) -> 18.5 | K5: =SUMIF(entradas26[CODIGO],samgung26[[#This Row],[CODIGO ]],entradas26[[CAN JUEGOS ]]) -> 0 | L5: =SUMIF(entradas26[CODIGO],samgung26[[#This Row],[CODIGO ]],entradas26[CAN BARRAS]) -> 0 | M5: =SUMIF(salidas26[[CODIGO ]],samgung26[[#This Row],[CODIGO ]],salidas26[[CANT JUEGOS ]]) -> 28 | N5: =SUMIF(salidas26[[CODIGO ]],samgung26[[#This Row],[CODIGO ]],salidas26[CANT BARRAS]) -> 0 | O5: =(samgung26[[#This Row],["J"PRECIO COMPRA ]]*samgung26[[#This Row],[STOCK JUEGOS]]) -> 148 | P5: =(samgung26[[#This Row],["J" PRECIO VENTA ]]*samgung26[[#This Row],[STOCK JUEGOS]]) -> 320 | Q5: =(samgung26[[#This Row],["B"PRECIO COMPRA]]*samgung26[[#This Row],[STOCK BARRAS]]) -> 18.5 | R5: =(samgung26[[#This Row],["B"PRECIO VENTA ]]*samgung26[[#This Row],[STOCK BARRAS]]) -> 40 | S5: 32 | T5: 1 | U5: 1.55 | W5: XLM-0289 | X5: XY-0065
A6: 2 | B6: 2001 | C6: UN32EH4000 4B/3V | D6: =(samgung26[[#This Row],[CANTIDAD INICIAL JUEGO ]]+samgung26[[#This Row],[ENTRADAS JUEGOS ]]-samgung26[[#This Row],[SALIDAS JUEGOS]]) -> 2 | E6: =(samgung26[[#This Row],[CANTIDAD INICIAL BARRAS]]+samgung26[[#This Row],[ENTRADAS BARRAS]]-samgung26[[#This Row],[SALIDA BARRAS]]) -> 0 | F6: 150 | G6: 100 | H6: 4 | I6: =(samgung26[[#This Row],["J" PRECIO VENTA ]]/samgung26[[#This Row],[BARRAS]]) -> 37.5 | J6: =(samgung26[[#This Row],["J"PRECIO COMPRA ]]/samgung26[[#This Row],[BARRAS]]) -> 25 | K6: =SUMIF(entradas26[CODIGO],samgung26[[#This Row],[CODIGO ]],entradas26[[CAN JUEGOS ]]) -> 0 | L6: =SUMIF(entradas26[CODIGO],samgung26[[#This Row],[CODIGO ]],entradas26[CAN BARRAS]) -> 0 | M6: =SUMIF(salidas26[[CODIGO ]],samgung26[[#This Row],[CODIGO ]],salidas26[[CANT JUEGOS ]]) -> 1 | N6: =SUMIF(salidas26[[CODIGO ]],samgung26[[#This Row],[CODIGO ]],salidas26[CANT BARRAS]) -> 0 | O6: =(samgung26[[#This Row],["J"PRECIO COMPRA ]]*samgung26[[#This Row],[STOCK JUEGOS]]) -> 200 | P6: =(samgung26[[#This Row],["J" PRECIO VENTA ]]*samgung26[[#This Row],[STOCK JUEGOS]]) -> 300 | Q6: =(samgung26[[#This Row],["B"PRECIO COMPRA]]*samgung26[[#This Row],[STOCK BARRAS]]) -> 0 | R6: =(samgung26[[#This Row],["B"PRECIO VENTA ]]*samgung26[[#This Row],[STOCK BARRAS]]) -> 0 | S6: 3
A7: 3 | B7: 2003 | C7: UN32F5000-SAMSUNG 5B | D7: =(samgung26[[#This Row],[CANTIDAD INICIAL JUEGO ]]+samgung26[[#This Row],[ENTRADAS JUEGOS ]]-samgung26[[#This Row],[SALIDAS JUEGOS]]) -> 25 | E7: =(samgung26[[#This Row],[CANTIDAD INICIAL BARRAS]]+samgung26[[#This Row],[ENTRADAS BARRAS]]-samgung26[[#This Row],[SALIDA BARRAS]]) -> 3 | F7: 130 | G7: 74 | H7: 5 | I7: =(samgung26[[#This Row],["J" PRECIO VENTA ]]/samgung26[[#This Row],[BARRAS]]) -> 26 | J7: =(samgung26[[#This Row],["J"PRECIO COMPRA ]]/samgung26[[#This Row],[BARRAS]]) -> 14.8 | K7: =SUMIF(entradas26[CODIGO],samgung26[[#This Row],[CODIGO ]],entradas26[[CAN JUEGOS ]]) -> 20 | L7: =SUMIF(entradas26[CODIGO],samgung26[[#This Row],[CODIGO ]],entradas26[CAN BARRAS]) -> 15 | M7: =SUMIF(salidas26[[CODIGO ]],samgung26[[#This Row],[CODIGO ]],salidas26[[CANT JUEGOS ]]) -> 8 | N7: =SUMIF(salidas26[[CODIGO ]],samgung26[[#This Row],[CODIGO ]],salidas26[CANT BARRAS]) -> 14 | O7: =(samgung26[[#This Row],["J"PRECIO COMPRA ]]*samgung26[[#This Row],[STOCK JUEGOS]]) -> 1850 | P7: =(samgung26[[#This Row],["J" PRECIO VENTA ]]*samgung26[[#This Row],[STOCK JUEGOS]]) -> 3250 | Q7: =(samgung26[[#This Row],["B"PRECIO COMPRA]]*samgung26[[#This Row],[STOCK BARRAS]]) -> 44.4 | R7: =(samgung26[[#This Row],["B"PRECIO VENTA ]]*samgung26[[#This Row],[STOCK BARRAS]]) -> 78 | S7: 13 | T7: 2 | U7: 3.9 | V7: poner nombre | W7: XLM-0319
A8: 4 | B8: 2006 | C8: UN32J/ 2B | D8: =(samgung26[[#This Row],[CANTIDAD INICIAL JUEGO ]]+samgung26[[#This Row],[ENTRADAS JUEGOS ]]-samgung26[[#This Row],[SALIDAS JUEGOS]]) -> 18 | E8: =(samgung26[[#This Row],[CANTIDAD INICIAL BARRAS]]+samgung26[[#This Row],[ENTRADAS BARRAS]]-samgung26[[#This Row],[SALIDA BARRAS]]) -> 1 | F8: 90 | G8: 38 | H8: 2 | I8: =(samgung26[[#This Row],["J" PRECIO VENTA ]]/samgung26[[#This Row],[BARRAS]]) -> 45 | J8: =(samgung26[[#This Row],["J"PRECIO COMPRA ]]/samgung26[[#This Row],[BARRAS]]) -> 19 | K8: =SUMIF(entradas26[CODIGO],samgung26[[#This Row],[CODIGO ]],entradas26[[CAN JUEGOS ]]) -> 0 | L8: =SUMIF(entradas26[CODIGO],samgung26[[#This Row],[CODIGO ]],entradas26[CAN BARRAS]) -> 0 | M8: =SUMIF(salidas26[[CODIGO ]],samgung26[[#This Row],[CODIGO ]],salidas26[[CANT JUEGOS ]]) -> 3 | N8: =SUMIF(salidas26[[CODIGO ]],samgung26[[#This Row],[CODIGO ]],salidas26[CANT BARRAS]) -> 0 | O8: =(samgung26[[#This Row],["J"PRECIO COMPRA ]]*samgung26[[#This Row],[STOCK JUEGOS]]) -> 684 | P8: =(samgung26[[#This Row],["J" PRECIO VENTA ]]*samgung26[[#This Row],[STOCK JUEGOS]]) -> 1620 | Q8: =(samgung26[[#This Row],["B"PRECIO COMPRA]]*samgung26[[#This Row],[STOCK BARRAS]]) -> 19 | R8: =(samgung26[[#This Row],["B"PRECIO VENTA ]]*samgung26[[#This Row],[STOCK BARRAS]]) -> 45 | S8: 21 | T8: 1 | U8: 1.6 | W8: XLM-1956
A9: 5 | B9: 2009 | C9: UN40D5500/2B | D9: =(samgung26[[#This Row],[CANTIDAD INICIAL JUEGO ]]+samgung26[[#This Row],[ENTRADAS JUEGOS ]]-samgung26[[#This Row],[SALIDAS JUEGOS]]) -> 19 | E9: =(samgung26[[#This Row],[CANTIDAD INICIAL BARRAS]]+samgung26[[#This Row],[ENTRADAS BARRAS]]-samgung26[[#This Row],[SALIDA BARRAS]]) -> 0 | F9: 180 | G9: 75 | H9: 2 | I9: =(samgung26[[#This Row],["J" PRECIO VENTA ]]/samgung26[[#This Row],[BARRAS]]) -> 90 | J9: =(samgung26[[#This Row],["J"PRECIO COMPRA ]]/samgung26[[#This Row],[BARRAS]]) -> 37.5 | K9: =SUMIF(entradas26[CODIGO],samgung26[[#This Row],[CODIGO ]],entradas26[[CAN JUEGOS ]]) -> 0 | L9: =SUMIF(entradas26[CODIGO],samgung26[[#This Row],[CODIGO ]],entradas26[CAN BARRAS]) -> 0 | M9: =SUMIF(salidas26[[CODIGO ]],samgung26[[#This Row],[CODIGO ]],salidas26[[CANT JUEGOS ]]) -> 0 | N9: =SUMIF(salidas26[[CODIGO ]],samgung26[[#This Row],[CODIGO ]],salidas26[CANT BARRAS]) -> 0 | O9: =(samgung26[[#This Row],["J"PRECIO COMPRA ]]*samgung26[[#This Row],[STOCK JUEGOS]]) -> 1425 | P9: =(samgung26[[#This Row],["J" PRECIO VENTA ]]*samgung26[[#This Row],[STOCK JUEGOS]]) -> 3420 | Q9: =(samgung26[[#This Row],["B"PRECIO COMPRA]]*samgung26[[#This Row],[STOCK BARRAS]]) -> 0 | R9: =(samgung26[[#This Row],["B"PRECIO VENTA ]]*samgung26[[#This Row],[STOCK BARRAS]]) -> 0 | S9: 19 | U9: 3.55 | W9: XLM-0178/0179
B10: 2008 | C10: UN 40 D6500/2B | D10: =(samgung26[[#This Row],[CANTIDAD INICIAL JUEGO ]]+samgung26[[#This Row],[ENTRADAS JUEGOS ]]-samgung26[[#This Row],[SALIDAS JUEGOS]]) -> 10 | E10: =(samgung26[[#This Row],[CANTIDAD INICIAL BARRAS]]+samgung26[[#This Row],[ENTRADAS BARRAS]]-samgung26[[#This Row],[SALIDA BARRAS]]) -> 0 | F10: 200 | G10: 103 | I10: =(samgung26[[#This Row],["J" PRECIO VENTA ]]/samgung26[[#This Row],[BARRAS]]) -> #DIV/0! | J10: =(samgung26[[#This Row],["J"PRECIO COMPRA ]]/samgung26[[#This Row],[BARRAS]]) -> #DIV/0! | K10: =SUMIF(entradas26[CODIGO],samgung26[[#This Row],[CODIGO ]],entradas26[[CAN JUEGOS ]]) -> 10 | L10: =SUMIF(entradas26[CODIGO],samgung26[[#This Row],[CODIGO ]],entradas26[CAN BARRAS]) -> 0 | M10: =SUMIF(salidas26[[CODIGO ]],samgung26[[#This Row],[CODIGO ]],salidas26[[CANT JUEGOS ]]) -> 0 | N10: =SUMIF(salidas26[[CODIGO ]],samgung26[[#This Row],[CODIGO ]],salidas26[CANT BARRAS]) -> 0 | O10: =(samgung26[[#This Row],["J"PRECIO COMPRA ]]*samgung26[[#This Row],[STOCK JUEGOS]]) -> 1030 | P10: =(samgung26[[#This Row],["J" PRECIO VENTA ]]*samgung26[[#This Row],[STOCK JUEGOS]]) -> 2000 | Q10: =(samgung26[[#This Row],["B"PRECIO COMPRA]]*samgung26[[#This Row],[STOCK BARRAS]]) -> #DIV/0! | R10: =(samgung26[[#This Row],["B"PRECIO VENTA ]]*samgung26[[#This Row],[STOCK BARRAS]]) -> #DIV/0! | U10: 5.4 | W10: XLM - W0896
A11: 6 | B11: 2012 | C11: UN40J5000 -40J5200-40M5000 8L/3B | D11: =(samgung26[[#This Row],[CANTIDAD INICIAL JUEGO ]]+samgung26[[#This Row],[ENTRADAS JUEGOS ]]-samgung26[[#This Row],[SALIDAS JUEGOS]]) -> 14 | E11: =(samgung26[[#This Row],[CANTIDAD INICIAL BARRAS]]+samgung26[[#This Row],[ENTRADAS BARRAS]]-samgung26[[#This Row],[SALIDA BARRAS]]) -> 0 | F11: 160 | G11: 62 | H11: 3 | I11: =(samgung26[[#This Row],["J" PRECIO VENTA ]]/samgung26[[#This Row],[BARRAS]]) -> 53.333333 | J11: =(samgung26[[#This Row],["J"PRECIO COMPRA ]]/samgung26[[#This Row],[BARRAS]]) -> 20.666667 | K11: =SUMIF(entradas26[CODIGO],samgung26[[#This Row],[CODIGO ]],entradas26[[CAN JUEGOS ]]) -> 0 | L11: =SUMIF(entradas26[CODIGO],samgung26[[#This Row],[CODIGO ]],entradas26[CAN BARRAS]) -> 0 | M11: =SUMIF(salidas26[[CODIGO ]],samgung26[[#This Row],[CODIGO ]],salidas26[[CANT JUEGOS ]]) -> 10 | N11: =SUMIF(salidas26[[CODIGO ]],samgung26[[#This Row],[CODIGO ]],salidas26[CANT BARRAS]) -> 0 | O11: =(samgung26[[#This Row],["J"PRECIO COMPRA ]]*samgung26[[#This Row],[STOCK JUEGOS]]) -> 868 | P11: =(samgung26[[#This Row],["J" PRECIO VENTA ]]*samgung26[[#This Row],[STOCK JUEGOS]]) -> 2240 | Q11: =(samgung26[[#This Row],["B"PRECIO COMPRA]]*samgung26[[#This Row],[STOCK BARRAS]]) -> 0 | R11: =(samgung26[[#This Row],["B"PRECIO VENTA ]]*samgung26[[#This Row],[STOCK BARRAS]]) -> 0 | S11: 24 | U11: 3.4 | W11: XLM-0306
B12: 2013 | C12: UN40J6400 | D12: =(samgung26[[#This Row],[CANTIDAD INICIAL JUEGO ]]+samgung26[[#This Row],[ENTRADAS JUEGOS ]]-samgung26[[#This Row],[SALIDAS JUEGOS]]) -> 10 | E12: =(samgung26[[#This Row],[CANTIDAD INICIAL BARRAS]]+samgung26[[#This Row],[ENTRADAS BARRAS]]-samgung26[[#This Row],[SALIDA BARRAS]]) -> 0 | F12: 250 | H12: 10 | I12: =(samgung26[[#This Row],["J" PRECIO VENTA ]]/samgung26[[#This Row],[BARRAS]]) -> 25 | J12: =(samgung26[[#This Row],["J"PRECIO COMPRA ]]/samgung26[[#This Row],[BARRAS]]) -> 0 | K12: =SUMIF(entradas26[CODIGO],samgung26[[#This Row],[CODIGO ]],entradas26[[CAN JUEGOS ]]) -> 10 | L12: =SUMIF(entradas26[CODIGO],samgung26[[#This Row],[CODIGO ]],entradas26[CAN BARRAS]) -> 0 | M12: =SUMIF(salidas26[[CODIGO ]],samgung26[[#This Row],[CODIGO ]],salidas26[[CANT JUEGOS ]]) -> 0 | N12: =SUMIF(salidas26[[CODIGO ]],samgung26[[#This Row],[CODIGO ]],salidas26[CANT BARRAS]) -> 0 | O12: =(samgung26[[#This Row],["J"PRECIO COMPRA ]]*samgung26[[#This Row],[STOCK JUEGOS]]) -> 0 | P12: =(samgung26[[#This Row],["J" PRECIO VENTA ]]*samgung26[[#This Row],[STOCK JUEGOS]]) -> 2500 | Q12: =(samgung26[[#This Row],["B"PRECIO COMPRA]]*samgung26[[#This Row],[STOCK BARRAS]]) -> 0 | R12: =(samgung26[[#This Row],["B"PRECIO VENTA ]]*samgung26[[#This Row],[STOCK BARRAS]]) -> 0 | W12: XLM-0395/0408
A13: 7 | B13: 2015 | C13: UN40FH5005 3B/2C/1R/13-12-13 | D13: =(samgung26[[#This Row],[CANTIDAD INICIAL JUEGO ]]+samgung26[[#This Row],[ENTRADAS JUEGOS ]]-samgung26[[#This Row],[SALIDAS JUEGOS]]) -> 10 | E13: =(samgung26[[#This Row],[CANTIDAD INICIAL BARRAS]]+samgung26[[#This Row],[ENTRADAS BARRAS]]-samgung26[[#This Row],[SALIDA BARRAS]]) -> 3 | F13: 160 | G13: 99 | H13: 3 | I13: =(samgung26[[#This Row],["J" PRECIO VENTA ]]/samgung26[[#This Row],[BARRAS]]) -> 53.333333 | J13: =(samgung26[[#This Row],["J"PRECIO COMPRA ]]/samgung26[[#This Row],[BARRAS]]) -> 33 | K13: =SUMIF(entradas26[CODIGO],samgung26[[#This Row],[CODIGO ]],entradas26[[CAN JUEGOS ]]) -> 0 | L13: =SUMIF(entradas26[CODIGO],samgung26[[#This Row],[CODIGO ]],entradas26[CAN BARRAS]) -> 0 | M13: =SUMIF(salidas26[[CODIGO ]],samgung26[[#This Row],[CODIGO ]],salidas26[[CANT JUEGOS ]]) -> 3 | N13: =SUMIF(salidas26[[CODIGO ]],samgung26[[#This Row],[CODIGO ]],salidas26[CANT BARRAS]) -> 0 | O13: =(samgung26[[#This Row],["J"PRECIO COMPRA ]]*samgung26[[#This Row],[STOCK JUEGOS]]) -> 990 | P13: =(samgung26[[#This Row],["J" PRECIO VENTA ]]*samgung26[[#This Row],[STOCK JUEGOS]]) -> 1600 | Q13: =(samgung26[[#This Row],["B"PRECIO COMPRA]]*samgung26[[#This Row],[STOCK BARRAS]]) -> 99 | R13: =(samgung26[[#This Row],["B"PRECIO VENTA ]]*samgung26[[#This Row],[STOCK BARRAS]]) -> 160 | S13: 13 | T13: 3 | U13: 3.8 | W13: XLM-0320/0232 | X13: XY-068
A14: 8 | B14: 2018 | C14: UN40FH6203 3B/2C/1R/13-13-13 | D14: =(samgung26[[#This Row],[CANTIDAD INICIAL JUEGO ]]+samgung26[[#This Row],[ENTRADAS JUEGOS ]]-samgung26[[#This Row],[SALIDAS JUEGOS]]) -> 16 | E14: =(samgung26[[#This Row],[CANTIDAD INICIAL BARRAS]]+samgung26[[#This Row],[ENTRADAS BARRAS]]-samgung26[[#This Row],[SALIDA BARRAS]]) -> 0 | F14: 160 | G14: 102 | H14: 3 | I14: =(samgung26[[#This Row],["J" PRECIO VENTA ]]/samgung26[[#This Row],[BARRAS]]) -> 53.333333 | J14: =(samgung26[[#This Row],["J"PRECIO COMPRA ]]/samgung26[[#This Row],[BARRAS]]) -> 34 | K14: =SUMIF(entradas26[CODIGO],samgung26[[#This Row],[CODIGO ]],entradas26[[CAN JUEGOS ]]) -> 0 | L14: =SUMIF(entradas26[CODIGO],samgung26[[#This Row],[CODIGO ]],entradas26[CAN BARRAS]) -> 0 | M14: =SUMIF(salidas26[[CODIGO ]],samgung26[[#This Row],[CODIGO ]],salidas26[[CANT JUEGOS ]]) -> 3 | N14: =SUMIF(salidas26[[CODIGO ]],samgung26[[#This Row],[CODIGO ]],salidas26[CANT BARRAS]) -> 0 | O14: =(samgung26[[#This Row],["J"PRECIO COMPRA ]]*samgung26[[#This Row],[STOCK JUEGOS]]) -> 1632 | P14: =(samgung26[[#This Row],["J" PRECIO VENTA ]]*samgung26[[#This Row],[STOCK JUEGOS]]) -> 2560 | Q14: =(samgung26[[#This Row],["B"PRECIO COMPRA]]*samgung26[[#This Row],[STOCK BARRAS]]) -> 0 | R14: =(samgung26[[#This Row],["B"PRECIO VENTA ]]*samgung26[[#This Row],[STOCK BARRAS]]) -> 0 | S14: 19 | U14: 2.71 | W14: XLM-1802/1803 | X14: XY-698
A15: 9 | B15: 2021 | C15: UN40F5000-F6400/14 B | D15: =(samgung26[[#This Row],[CANTIDAD INICIAL JUEGO ]]+samgung26[[#This Row],[ENTRADAS JUEGOS ]]-samgung26[[#This Row],[SALIDAS JUEGOS]]) -> 5 | E15: =(samgung26[[#This Row],[CANTIDAD INICIAL BARRAS]]+samgung26[[#This Row],[ENTRADAS BARRAS]]-samgung26[[#This Row],[SALIDA BARRAS]]) -> 7 | F15: 260 | G15: 225 | H15: 14 | I15: =(samgung26[[#This Row],["J" PRECIO VENTA ]]/samgung26[[#This Row],[BARRAS]]) -> 18.571429 | J15: =(samgung26[[#This Row],["J"PRECIO COMPRA ]]/samgung26[[#This Row],[BARRAS]]) -> 16.071429 | K15: =SUMIF(entradas26[CODIGO],samgung26[[#This Row],[CODIGO ]],entradas26[[CAN JUEGOS ]]) -> 0 | L15: =SUMIF(entradas26[CODIGO],samgung26[[#This Row],[CODIGO ]],entradas26[CAN BARRAS]) -> 0 | M15: =SUMIF(salidas26[[CODIGO ]],samgung26[[#This Row],[CODIGO ]],salidas26[[CANT JUEGOS ]]) -> 5 | N15: =SUMIF(salidas26[[CODIGO ]],samgung26[[#This Row],[CODIGO ]],salidas26[CANT BARRAS]) -> 0 | O15: =(samgung26[[#This Row],["J"PRECIO COMPRA ]]*samgung26[[#This Row],[STOCK JUEGOS]]) -> 1125 | P15: =(samgung26[[#This Row],["J" PRECIO VENTA ]]*samgung26[[#This Row],[STOCK JUEGOS]]) -> 1300 | Q15: =(samgung26[[#This Row],["B"PRECIO COMPRA]]*samgung26[[#This Row],[STOCK BARRAS]]) -> 112.5 | R15: =(samgung26[[#This Row],["B"PRECIO VENTA ]]*samgung26[[#This Row],[STOCK BARRAS]]) -> 130 | S15: 10 | T15: 7 | U15: 6.75 | W15: XLM-0317/0318 | X15: XY-0043
A16: 10 | B16: 2024 | C16: UN43J5202/ 3 BARRAS/8L/3V | D16: =(samgung26[[#This Row],[CANTIDAD INICIAL JUEGO ]]+samgung26[[#This Row],[ENTRADAS JUEGOS ]]-samgung26[[#This Row],[SALIDAS JUEGOS]]) -> 18 | E16: =(samgung26[[#This Row],[CANTIDAD INICIAL BARRAS]]+samgung26[[#This Row],[ENTRADAS BARRAS]]-samgung26[[#This Row],[SALIDA BARRAS]]) -> 0 | F16: 180 | G16: 42 | H16: 3 | I16: =(samgung26[[#This Row],["J" PRECIO VENTA ]]/samgung26[[#This Row],[BARRAS]]) -> 60 | J16: =(samgung26[[#This Row],["J"PRECIO COMPRA ]]/samgung26[[#This Row],[BARRAS]]) -> 14 | K16: =SUMIF(entradas26[CODIGO],samgung26[[#This Row],[CODIGO ]],entradas26[[CAN JUEGOS ]]) -> 0 | L16: =SUMIF(entradas26[CODIGO],samgung26[[#This Row],[CODIGO ]],entradas26[CAN BARRAS]) -> 0 | M16: =SUMIF(salidas26[[CODIGO ]],samgung26[[#This Row],[CODIGO ]],salidas26[[CANT JUEGOS ]]) -> 8 | N16: =SUMIF(salidas26[[CODIGO ]],samgung26[[#This Row],[CODIGO ]],salidas26[CANT BARRAS]) -> 0 | O16: =(samgung26[[#This Row],["J"PRECIO COMPRA ]]*samgung26[[#This Row],[STOCK JUEGOS]]) -> 756 | P16: =(samgung26[[#This Row],["J" PRECIO VENTA ]]*samgung26[[#This Row],[STOCK JUEGOS]]) -> 3240 | Q16: =(samgung26[[#This Row],["B"PRECIO COMPRA]]*samgung26[[#This Row],[STOCK BARRAS]]) -> 0 | R16: =(samgung26[[#This Row],["B"PRECIO VENTA ]]*samgung26[[#This Row],[STOCK BARRAS]]) -> 0 | S16: 26 | U16: 2.1 | W16: XLM-0668 | X16: XY-0318
B17: 2025 | C17: 43AU7000 | D17: =(samgung26[[#This Row],[CANTIDAD INICIAL JUEGO ]]+samgung26[[#This Row],[ENTRADAS JUEGOS ]]-samgung26[[#This Row],[SALIDAS JUEGOS]]) -> 20 | E17: =(samgung26[[#This Row],[CANTIDAD INICIAL BARRAS]]+samgung26[[#This Row],[ENTRADAS BARRAS]]-samgung26[[#This Row],[SALIDA BARRAS]]) -> 0 | F17: 200 | G17: 63 | I17: =(samgung26[[#This Row],["J" PRECIO VENTA ]]/samgung26[[#This Row],[BARRAS]]) -> #DIV/0! | J17: =(samgung26[[#This Row],["J"PRECIO COMPRA ]]/samgung26[[#This Row],[BARRAS]]) -> #DIV/0! | K17: =SUMIF(entradas26[CODIGO],samgung26[[#This Row],[CODIGO ]],entradas26[[CAN JUEGOS ]]) -> 20 | L17: =SUMIF(entradas26[CODIGO],samgung26[[#This Row],[CODIGO ]],entradas26[CAN BARRAS]) -> 0 | M17: =SUMIF(salidas26[[CODIGO ]],samgung26[[#This Row],[CODIGO ]],salidas26[[CANT JUEGOS ]]) -> 0 | N17: =SUMIF(salidas26[[CODIGO ]],samgung26[[#This Row],[CODIGO ]],salidas26[CANT BARRAS]) -> 0 | O17: =(samgung26[[#This Row],["J"PRECIO COMPRA ]]*samgung26[[#This Row],[STOCK JUEGOS]]) -> 1260 | P17: =(samgung26[[#This Row],["J" PRECIO VENTA ]]*samgung26[[#This Row],[STOCK JUEGOS]]) -> 4000 | Q17: =(samgung26[[#This Row],["B"PRECIO COMPRA]]*samgung26[[#This Row],[STOCK BARRAS]]) -> #DIV/0! | R17: =(samgung26[[#This Row],["B"PRECIO VENTA ]]*samgung26[[#This Row],[STOCK BARRAS]]) -> #DIV/0! | U17: 3.3 | W17: XLM-0988/0989
A18: 11 | B18: 2027 | C18: UN43J5290/8B | D18: =(samgung26[[#This Row],[CANTIDAD INICIAL JUEGO ]]+samgung26[[#This Row],[ENTRADAS JUEGOS ]]-samgung26[[#This Row],[SALIDAS JUEGOS]]) -> 12 | E18: =(samgung26[[#This Row],[CANTIDAD INICIAL BARRAS]]+samgung26[[#This Row],[ENTRADAS BARRAS]]-samgung26[[#This Row],[SALIDA BARRAS]]) -> 3 | F18: 180 | G18: 108 | H18: 8 | I18: =(samgung26[[#This Row],["J" PRECIO VENTA ]]/samgung26[[#This Row],[BARRAS]]) -> 22.5 | J18: =(samgung26[[#This Row],["J"PRECIO COMPRA ]]/samgung26[[#This Row],[BARRAS]]) -> 13.5 | K18: =SUMIF(entradas26[CODIGO],samgung26[[#This Row],[CODIGO ]],entradas26[[CAN JUEGOS ]]) -> 0 | L18: =SUMIF(entradas26[CODIGO],samgung26[[#This Row],[CODIGO ]],entradas26[CAN BARRAS]) -> 8 | M18: =SUMIF(salidas26[[CODIGO ]],samgung26[[#This Row],[CODIGO ]],salidas26[[CANT JUEGOS ]]) -> 8 | N18: =SUMIF(salidas26[[CODIGO ]],samgung26[[#This Row],[CODIGO ]],salidas26[CANT BARRAS]) -> 6 | O18: =(samgung26[[#This Row],["J"PRECIO COMPRA ]]*samgung26[[#This Row],[STOCK JUEGOS]]) -> 1296 | P18: =(samgung26[[#This Row],["J" PRECIO VENTA ]]*samgung26[[#This Row],[STOCK JUEGOS]]) -> 2160 | Q18: =(samgung26[[#This Row],["B"PRECIO COMPRA]]*samgung26[[#This Row],[STOCK BARRAS]]) -> 40.5 | R18: =(samgung26[[#This Row],["B"PRECIO VENTA ]]*samgung26[[#This Row],[STOCK BARRAS]]) -> 67.5 | S18: 20 | T18: 1 | U18: 4.6 | W18: XLM-0304/0305 | X18: XLM-1576/1577
A19: 12 | B19: 2029 | C19: UN43AU8000-43BU8000/2B | D19: =(samgung26[[#This Row],[CANTIDAD INICIAL JUEGO ]]+samgung26[[#This Row],[ENTRADAS JUEGOS ]]-samgung26[[#This Row],[SALIDAS JUEGOS]]) -> 8 | E19: =(samgung26[[#This Row],[CANTIDAD INICIAL BARRAS]]+samgung26[[#This Row],[ENTRADAS BARRAS]]-samgung26[[#This Row],[SALIDA BARRAS]]) -> 0 | F19: 220 | G19: 122 | H19: 2 | I19: =(samgung26[[#This Row],["J" PRECIO VENTA ]]/samgung26[[#This Row],[BARRAS]]) -> 110 | J19: =(samgung26[[#This Row],["J"PRECIO COMPRA ]]/samgung26[[#This Row],[BARRAS]]) -> 61 | K19: =SUMIF(entradas26[CODIGO],samgung26[[#This Row],[CODIGO ]],entradas26[[CAN JUEGOS ]]) -> 0 | L19: =SUMIF(entradas26[CODIGO],samgung26[[#This Row],[CODIGO ]],entradas26[CAN BARRAS]) -> 0 | M19: =SUMIF(salidas26[[CODIGO ]],samgung26[[#This Row],[CODIGO ]],salidas26[[CANT JUEGOS ]]) -> 1 | N19: =SUMIF(salidas26[[CODIGO ]],samgung26[[#This Row],[CODIGO ]],salidas26[CANT BARRAS]) -> 0 | O19: =(samgung26[[#This Row],["J"PRECIO COMPRA ]]*samgung26[[#This Row],[STOCK JUEGOS]]) -> 976 | P19: =(samgung26[[#This Row],["J" PRECIO VENTA ]]*samgung26[[#This Row],[STOCK JUEGOS]]) -> 1760 | Q19: =(samgung26[[#This Row],["B"PRECIO COMPRA]]*samgung26[[#This Row],[STOCK BARRAS]]) -> 0 | R19: =(samgung26[[#This Row],["B"PRECIO VENTA ]]*samgung26[[#This Row],[STOCK BARRAS]]) -> 0 | S19: 9 | U19: 3.9 | W19: XLM-1685
A20: 13 | B20: 2030 | C20: UN43N.U./2B EDGE | D20: =(samgung26[[#This Row],[CANTIDAD INICIAL JUEGO ]]+samgung26[[#This Row],[ENTRADAS JUEGOS ]]-samgung26[[#This Row],[SALIDAS JUEGOS]]) -> 2 | E20: =(samgung26[[#This Row],[CANTIDAD INICIAL BARRAS]]+samgung26[[#This Row],[ENTRADAS BARRAS]]-samgung26[[#This Row],[SALIDA BARRAS]]) -> 1 | F20: 150 | G20: 80 | H20: 2 | I20: =(samgung26[[#This Row],["J" PRECIO VENTA ]]/samgung26[[#This Row],[BARRAS]]) -> 75 | J20: =(samgung26[[#This Row],["J"PRECIO COMPRA ]]/samgung26[[#This Row],[BARRAS]]) -> 40 | K20: =SUMIF(entradas26[CODIGO],samgung26[[#This Row],[CODIGO ]],entradas26[[CAN JUEGOS ]]) -> 0 | L20: =SUMIF(entradas26[CODIGO],samgung26[[#This Row],[CODIGO ]],entradas26[CAN BARRAS]) -> 0 | M20: =SUMIF(salidas26[[CODIGO ]],samgung26[[#This Row],[CODIGO ]],salidas26[[CANT JUEGOS ]]) -> 0 | N20: =SUMIF(salidas26[[CODIGO ]],samgung26[[#This Row],[CODIGO ]],salidas26[CANT BARRAS]) -> 0 | O20: =(samgung26[[#This Row],["J"PRECIO COMPRA ]]*samgung26[[#This Row],[STOCK JUEGOS]]) -> 160 | P20: =(samgung26[[#This Row],["J" PRECIO VENTA ]]*samgung26[[#This Row],[STOCK JUEGOS]]) -> 300 | Q20: =(samgung26[[#This Row],["B"PRECIO COMPRA]]*samgung26[[#This Row],[STOCK BARRAS]]) -> 40 | R20: =(samgung26[[#This Row],["B"PRECIO VENTA ]]*samgung26[[#This Row],[STOCK BARRAS]]) -> 75 | S20: 2 | T20: 1
A21: 14 | B21: 2033 | C21: UN46F5000 - F6400 /16B | D21: =(samgung26[[#This Row],[CANTIDAD INICIAL JUEGO ]]+samgung26[[#This Row],[ENTRADAS JUEGOS ]]-samgung26[[#This Row],[SALIDAS JUEGOS]]) -> 20 | E21: =(samgung26[[#This Row],[CANTIDAD INICIAL BARRAS]]+samgung26[[#This Row],[ENTRADAS BARRAS]]-samgung26[[#This Row],[SALIDA BARRAS]]) -> 0 | F21: 350 | G21: 200 | H21: 16 | I21: =(samgung26[[#This Row],["J" PRECIO VENTA ]]/samgung26[[#This Row],[BARRAS]]) -> 21.875 | J21: =(samgung26[[#This Row],["J"PRECIO COMPRA ]]/samgung26[[#This Row],[BARRAS]]) -> 12.5 | K21: =SUMIF(entradas26[CODIGO],samgung26[[#This Row],[CODIGO ]],entradas26[[CAN JUEGOS ]]) -> 20 | L21: =SUMIF(entradas26[CODIGO],samgung26[[#This Row],[CODIGO ]],entradas26[CAN BARRAS]) -> 0 | M21: =SUMIF(salidas26[[CODIGO ]],samgung26[[#This Row],[CODIGO ]],salidas26[[CANT JUEGOS ]]) -> 2 | N21: =SUMIF(salidas26[[CODIGO ]],samgung26[[#This Row],[CODIGO ]],salidas26[CANT BARRAS]) -> 0 | O21: =(samgung26[[#This Row],["J"PRECIO COMPRA ]]*samgung26[[#This Row],[STOCK JUEGOS]]) -> 4000 | P21: =(samgung26[[#This Row],["J" PRECIO VENTA ]]*samgung26[[#This Row],[STOCK JUEGOS]]) -> 7000 | Q21: =(samgung26[[#This Row],["B"PRECIO COMPRA]]*samgung26[[#This Row],[STOCK BARRAS]]) -> 0 | R21: =(samgung26[[#This Row],["B"PRECIO VENTA ]]*samgung26[[#This Row],[STOCK BARRAS]]) -> 0 | S21: 2 | U21: 8.84 | X21: XY-0045
A22: 15 | B22: 2036 | C22: UN46FH6203-46FH5005/8B | D22: =(samgung26[[#This Row],[CANTIDAD INICIAL JUEGO ]]+samgung26[[#This Row],[ENTRADAS JUEGOS ]]-samgung26[[#This Row],[SALIDAS JUEGOS]]) -> 26 | E22: =(samgung26[[#This Row],[CANTIDAD INICIAL BARRAS]]+samgung26[[#This Row],[ENTRADAS BARRAS]]-samgung26[[#This Row],[SALIDA BARRAS]]) -> 0 | F22: 220 | G22: 63 | H22: 8 | I22: =(samgung26[[#This Row],["J" PRECIO VENTA ]]/samgung26[[#This Row],[BARRAS]]) -> 27.5 | J22: =(samgung26[[#This Row],["J"PRECIO COMPRA ]]/samgung26[[#This Row],[BARRAS]]) -> 7.875 | K22: =SUMIF(entradas26[CODIGO],samgung26[[#This Row],[CODIGO ]],entradas26[[CAN JUEGOS ]]) -> 0 | L22: =SUMIF(entradas26[CODIGO],samgung26[[#This Row],[CODIGO ]],entradas26[CAN BARRAS]) -> 0 | M22: =SUMIF(salidas26[[CODIGO ]],samgung26[[#This Row],[CODIGO ]],salidas26[[CANT JUEGOS ]]) -> 6 | N22: =SUMIF(salidas26[[CODIGO ]],samgung26[[#This Row],[CODIGO ]],salidas26[CANT BARRAS]) -> 0 | O22: =(samgung26[[#This Row],["J"PRECIO COMPRA ]]*samgung26[[#This Row],[STOCK JUEGOS]]) -> 1638 | P22: =(samgung26[[#This Row],["J" PRECIO VENTA ]]*samgung26[[#This Row],[STOCK JUEGOS]]) -> 5720 | Q22: =(samgung26[[#This Row],["B"PRECIO COMPRA]]*samgung26[[#This Row],[STOCK BARRAS]]) -> 0 | R22: =(samgung26[[#This Row],["B"PRECIO VENTA ]]*samgung26[[#This Row],[STOCK BARRAS]]) -> 0 | S22: 32 | U22: 4.1 | W22: XLM-0626/0625 | X22: XY-0379
A23: 17 | B23: 2039 | C23: UN48H4200/8B | D23: =(samgung26[[#This Row],[CANTIDAD INICIAL JUEGO ]]+samgung26[[#This Row],[ENTRADAS JUEGOS ]]-samgung26[[#This Row],[SALIDAS JUEGOS]]) -> 19 | E23: =(samgung26[[#This Row],[CANTIDAD INICIAL BARRAS]]+samgung26[[#This Row],[ENTRADAS BARRAS]]-samgung26[[#This Row],[SALIDA BARRAS]]) -> 0 | F23: 280 | G23: 156 | H23: 8 | I23: =(samgung26[[#This Row],["J" PRECIO VENTA ]]/samgung26[[#This Row],[BARRAS]]) -> 35 | J23: =(samgung26[[#This Row],["J"PRECIO COMPRA ]]/samgung26[[#This Row],[BARRAS]]) -> 19.5 | K23: =SUMIF(entradas26[CODIGO],samgung26[[#This Row],[CODIGO ]],entradas26[[CAN JUEGOS ]]) -> 20 | L23: =SUMIF(entradas26[CODIGO],samgung26[[#This Row],[CODIGO ]],entradas26[CAN BARRAS]) -> 0 | M23: =SUMIF(salidas26[[CODIGO ]],samgung26[[#This Row],[CODIGO ]],salidas26[[CANT JUEGOS ]]) -> 4 | N23: =SUMIF(salidas26[[CODIGO ]],samgung26[[#This Row],[CODIGO ]],salidas26[CANT BARRAS]) -> 0 | O23: =(samgung26[[#This Row],["J"PRECIO COMPRA ]]*samgung26[[#This Row],[STOCK JUEGOS]]) -> 2964 | P23: =(samgung26[[#This Row],["J" PRECIO VENTA ]]*samgung26[[#This Row],[STOCK JUEGOS]]) -> 5320 | Q23: =(samgung26[[#This Row],["B"PRECIO COMPRA]]*samgung26[[#This Row],[STOCK BARRAS]]) -> 0 | R23: =(samgung26[[#This Row],["B"PRECIO VENTA ]]*samgung26[[#This Row],[STOCK BARRAS]]) -> 0 | S23: 3 | U23: 5 | W23: XLM-W0170
A24: 18 | B24: 2040 | C24: UN48H6400-48J6400/12B | D24: =(samgung26[[#This Row],[CANTIDAD INICIAL JUEGO ]]+samgung26[[#This Row],[ENTRADAS JUEGOS ]]-samgung26[[#This Row],[SALIDAS JUEGOS]]) -> 15 | E24: =(samgung26[[#This Row],[CANTIDAD INICIAL BARRAS]]+samgung26[[#This Row],[ENTRADAS BARRAS]]-samgung26[[#This Row],[SALIDA BARRAS]]) -> 0 | F24: 360 | G24: 185 | H24: 12 | I24: =(samgung26[[#This Row],["J" PRECIO VENTA ]]/samgung26[[#This Row],[BARRAS]]) -> 30 | J24: =(samgung26[[#This Row],["J"PRECIO COMPRA ]]/samgung26[[#This Row],[BARRAS]]) -> 15.416667 | K24: =SUMIF(entradas26[CODIGO],samgung26[[#This Row],[CODIGO ]],entradas26[[CAN JUEGOS ]]) -> 0 | L24: =SUMIF(entradas26[CODIGO],samgung26[[#This Row],[CODIGO ]],entradas26[CAN BARRAS]) -> 0 | M24: =SUMIF(salidas26[[CODIGO ]],samgung26[[#This Row],[CODIGO ]],salidas26[[CANT JUEGOS ]]) -> 1 | N24: =SUMIF(salidas26[[CODIGO ]],samgung26[[#This Row],[CODIGO ]],salidas26[CANT BARRAS]) -> 0 | O24: =(samgung26[[#This Row],["J"PRECIO COMPRA ]]*samgung26[[#This Row],[STOCK JUEGOS]]) -> 2775 | P24: =(samgung26[[#This Row],["J" PRECIO VENTA ]]*samgung26[[#This Row],[STOCK JUEGOS]]) -> 5400 | Q24: =(samgung26[[#This Row],["B"PRECIO COMPRA]]*samgung26[[#This Row],[STOCK BARRAS]]) -> 0 | R24: =(samgung26[[#This Row],["B"PRECIO VENTA ]]*samgung26[[#This Row],[STOCK BARRAS]]) -> 0 | S24: 16 | U24: 8.83 | X24: XY-0061
A25: 19 | B25: 2042 | C25: UN48J5000AG/8B | D25: =(samgung26[[#This Row],[CANTIDAD INICIAL JUEGO ]]+samgung26[[#This Row],[ENTRADAS JUEGOS ]]-samgung26[[#This Row],[SALIDAS JUEGOS]]) -> 10 | E25: =(samgung26[[#This Row],[CANTIDAD INICIAL BARRAS]]+samgung26[[#This Row],[ENTRADAS BARRAS]]-samgung26[[#This Row],[SALIDA BARRAS]]) -> 0 | F25: 260 | G25: 109 | H25: 8 | I25: =(samgung26[[#This Row],["J" PRECIO VENTA ]]/samgung26[[#This Row],[BARRAS]]) -> 32.5 | J25: =(samgung26[[#This Row],["J"PRECIO COMPRA ]]/samgung26[[#This Row],[BARRAS]]) -> 13.625 | K25: =SUMIF(entradas26[CODIGO],samgung26[[#This Row],[CODIGO ]],entradas26[[CAN JUEGOS ]]) -> 0 | L25: =SUMIF(entradas26[CODIGO],samgung26[[#This Row],[CODIGO ]],entradas26[CAN BARRAS]) -> 0 | M25: =SUMIF(salidas26[[CODIGO ]],samgung26[[#This Row],[CODIGO ]],salidas26[[CANT JUEGOS ]]) -> 4 | N25: =SUMIF(salidas26[[CODIGO ]],samgung26[[#This Row],[CODIGO ]],salidas26[CANT BARRAS]) -> 0 | O25: =(samgung26[[#This Row],["J"PRECIO COMPRA ]]*samgung26[[#This Row],[STOCK JUEGOS]]) -> 1090 | P25: =(samgung26[[#This Row],["J" PRECIO VENTA ]]*samgung26[[#This Row],[STOCK JUEGOS]]) -> 2600 | Q25: =(samgung26[[#This Row],["B"PRECIO COMPRA]]*samgung26[[#This Row],[STOCK BARRAS]]) -> 0 | R25: =(samgung26[[#This Row],["B"PRECIO VENTA ]]*samgung26[[#This Row],[STOCK BARRAS]]) -> 0 | S25: 14 | U25: 5 | W25: XLM-0302/0303
A26: 20 | B26: 2045 | C26: UN49KU6500-UN49MU6500/2B | D26: =(samgung26[[#This Row],[CANTIDAD INICIAL JUEGO ]]+samgung26[[#This Row],[ENTRADAS JUEGOS ]]-samgung26[[#This Row],[SALIDAS JUEGOS]]) -> 5 | E26: =(samgung26[[#This Row],[CANTIDAD INICIAL BARRAS]]+samgung26[[#This Row],[ENTRADAS BARRAS]]-samgung26[[#This Row],[SALIDA BARRAS]]) -> 1 | F26: 400 | G26: 98 | H26: 2 | I26: =(samgung26[[#This Row],["J" PRECIO VENTA ]]/samgung26[[#This Row],[BARRAS]]) -> 200 | J26: =(samgung26[[#This Row],["J"PRECIO COMPRA ]]/samgung26[[#This Row],[BARRAS]]) -> 49 | K26: =SUMIF(entradas26[CODIGO],samgung26[[#This Row],[CODIGO ]],entradas26[[CAN JUEGOS ]]) -> 0 | L26: =SUMIF(entradas26[CODIGO],samgung26[[#This Row],[CODIGO ]],entradas26[CAN BARRAS]) -> 0 | M26: =SUMIF(salidas26[[CODIGO ]],samgung26[[#This Row],[CODIGO ]],salidas26[[CANT JUEGOS ]]) -> 9 | N26: =SUMIF(salidas26[[CODIGO ]],samgung26[[#This Row],[CODIGO ]],salidas26[CANT BARRAS]) -> 0 | O26: =(samgung26[[#This Row],["J"PRECIO COMPRA ]]*samgung26[[#This Row],[STOCK JUEGOS]]) -> 490 | P26: =(samgung26[[#This Row],["J" PRECIO VENTA ]]*samgung26[[#This Row],[STOCK JUEGOS]]) -> 2000 | Q26: =(samgung26[[#This Row],["B"PRECIO COMPRA]]*samgung26[[#This Row],[STOCK BARRAS]]) -> 49 | R26: =(samgung26[[#This Row],["B"PRECIO VENTA ]]*samgung26[[#This Row],[STOCK BARRAS]]) -> 200 | S26: 14 | T26: 1 | U26: 10 | W26: XLM-1144/1145
A27: 21 | B27: 2048 | C27: UN49 NU7100/2B EDGE | D27: =(samgung26[[#This Row],[CANTIDAD INICIAL JUEGO ]]+samgung26[[#This Row],[ENTRADAS JUEGOS ]]-samgung26[[#This Row],[SALIDAS JUEGOS]]) -> 26 | E27: =(samgung26[[#This Row],[CANTIDAD INICIAL BARRAS]]+samgung26[[#This Row],[ENTRADAS BARRAS]]-samgung26[[#This Row],[SALIDA BARRAS]]) -> 1 | F27: 180 | G27: 71 | H27: 2 | I27: =(samgung26[[#This Row],["J" PRECIO VENTA ]]/samgung26[[#This Row],[BARRAS]]) -> 90 | J27: =(samgung26[[#This Row],["J"PRECIO COMPRA ]]/samgung26[[#This Row],[BARRAS]]) -> 35.5 | K27: =SUMIF(entradas26[CODIGO],samgung26[[#This Row],[CODIGO ]],entradas26[[CAN JUEGOS ]]) -> 0 | L27: =SUMIF(entradas26[CODIGO],samgung26[[#This Row],[CODIGO ]],entradas26[CAN BARRAS]) -> 2 | M27: =SUMIF(salidas26[[CODIGO ]],samgung26[[#This Row],[CODIGO ]],salidas26[[CANT JUEGOS ]]) -> 8 | N27: =SUMIF(salidas26[[CODIGO ]],samgung26[[#This Row],[CODIGO ]],salidas26[CANT BARRAS]) -> 1 | O27: =(samgung26[[#This Row],["J"PRECIO COMPRA ]]*samgung26[[#This Row],[STOCK JUEGOS]]) -> 1846 | P27: =(samgung26[[#This Row],["J" PRECIO VENTA ]]*samgung26[[#This Row],[STOCK JUEGOS]]) -> 4680 | Q27: =(samgung26[[#This Row],["B"PRECIO COMPRA]]*samgung26[[#This Row],[STOCK BARRAS]]) -> 35.5 | R27: =(samgung26[[#This Row],["B"PRECIO VENTA ]]*samgung26[[#This Row],[STOCK BARRAS]]) -> 90 | S27: 34 | U27: 2.7 | W27: XLM-0287
A28: 22 | B28: 2051 | C28: UN49J5290/8B | D28: =(samgung26[[#This Row],[CANTIDAD INICIAL JUEGO ]]+samgung26[[#This Row],[ENTRADAS JUEGOS ]]-samgung26[[#This Row],[SALIDAS JUEGOS]]) -> 14 | E28: =(samgung26[[#This Row],[CANTIDAD INICIAL BARRAS]]+samgung26[[#This Row],[ENTRADAS BARRAS]]-samgung26[[#This Row],[SALIDA BARRAS]]) -> 8 | F28: 260 | G28: 138 | H28: 8 | I28: =(samgung26[[#This Row],["J" PRECIO VENTA ]]/samgung26[[#This Row],[BARRAS]]) -> 32.5 | J28: =(samgung26[[#This Row],["J"PRECIO COMPRA ]]/samgung26[[#This Row],[BARRAS]]) -> 17.25 | K28: =SUMIF(entradas26[CODIGO],samgung26[[#This Row],[CODIGO ]],entradas26[[CAN JUEGOS ]]) -> 0 | L28: =SUMIF(entradas26[CODIGO],samgung26[[#This Row],[CODIGO ]],entradas26[CAN BARRAS]) -> 0 | M28: =SUMIF(salidas26[[CODIGO ]],samgung26[[#This Row],[CODIGO ]],salidas26[[CANT JUEGOS ]]) -> 6 | N28: =SUMIF(salidas26[[CODIGO ]],samgung26[[#This Row],[CODIGO ]],salidas26[CANT BARRAS]) -> 0 | O28: =(samgung26[[#This Row],["J"PRECIO COMPRA ]]*samgung26[[#This Row],[STOCK JUEGOS]]) -> 1932 | P28: =(samgung26[[#This Row],["J" PRECIO VENTA ]]*samgung26[[#This Row],[STOCK JUEGOS]]) -> 3640 | Q28: =(samgung26[[#This Row],["B"PRECIO COMPRA]]*samgung26[[#This Row],[STOCK BARRAS]]) -> 138 | R28: =(samgung26[[#This Row],["B"PRECIO VENTA ]]*samgung26[[#This Row],[STOCK BARRAS]]) -> 260 | S28: 20 | T28: 8 | U28: 6.28 | W28: XLM-1441/1442
A29: 23 | B29: 2054 | C29: UN49K6500/1B | D29: =(samgung26[[#This Row],[CANTIDAD INICIAL JUEGO ]]+samgung26[[#This Row],[ENTRADAS JUEGOS ]]-samgung26[[#This Row],[SALIDAS JUEGOS]]) -> 2 | E29: =(samgung26[[#This Row],[CANTIDAD INICIAL BARRAS]]+samgung26[[#This Row],[ENTRADAS BARRAS]]-samgung26[[#This Row],[SALIDA BARRAS]]) -> 0 | F29: 280 | G29: 62 | H29: 1 | I29: =(samgung26[[#This Row],["J" PRECIO VENTA ]]/samgung26[[#This Row],[BARRAS]]) -> 280 | J29: =(samgung26[[#This Row],["J"PRECIO COMPRA ]]/samgung26[[#This Row],[BARRAS]]) -> 62 | K29: =SUMIF(entradas26[CODIGO],samgung26[[#This Row],[CODIGO ]],entradas26[[CAN JUEGOS ]]) -> 0 | L29: =SUMIF(entradas26[CODIGO],samgung26[[#This Row],[CODIGO ]],entradas26[CAN BARRAS]) -> 0 | M29: =SUMIF(salidas26[[CODIGO ]],samgung26[[#This Row],[CODIGO ]],salidas26[[CANT JUEGOS ]]) -> 0 | N29: =SUMIF(salidas26[[CODIGO ]],samgung26[[#This Row],[CODIGO ]],salidas26[CANT BARRAS]) -> 0 | O29: =(samgung26[[#This Row],["J"PRECIO COMPRA ]]*samgung26[[#This Row],[STOCK JUEGOS]]) -> 124 | P29: =(samgung26[[#This Row],["J" PRECIO VENTA ]]*samgung26[[#This Row],[STOCK JUEGOS]]) -> 560 | Q29: =(samgung26[[#This Row],["B"PRECIO COMPRA]]*samgung26[[#This Row],[STOCK BARRAS]]) -> 0 | R29: =(samgung26[[#This Row],["B"PRECIO VENTA ]]*samgung26[[#This Row],[STOCK BARRAS]]) -> 0 | S29: 2 | U29: 4.4 | W29: XLM-1138
A30: 24 | B30: 2057 | C30: UN50F5000 -50F6400/ 18B | D30: =(samgung26[[#This Row],[CANTIDAD INICIAL JUEGO ]]+samgung26[[#This Row],[ENTRADAS JUEGOS ]]-samgung26[[#This Row],[SALIDAS JUEGOS]]) -> 10 | E30: =(samgung26[[#This Row],[CANTIDAD INICIAL BARRAS]]+samgung26[[#This Row],[ENTRADAS BARRAS]]-samgung26[[#This Row],[SALIDA BARRAS]]) -> 0 | F30: 400 | G30: 226 | H30: 18 | I30: =(samgung26[[#This Row],["J" PRECIO VENTA ]]/samgung26[[#This Row],[BARRAS]]) -> 22.222222 | J30: =(samgung26[[#This Row],["J"PRECIO COMPRA ]]/samgung26[[#This Row],[BARRAS]]) -> 12.555556 | K30: =SUMIF(entradas26[CODIGO],samgung26[[#This Row],[CODIGO ]],entradas26[[CAN JUEGOS ]]) -> 0 | L30: =SUMIF(entradas26[CODIGO],samgung26[[#This Row],[CODIGO ]],entradas26[CAN BARRAS]) -> 0 | M30: =SUMIF(salidas26[[CODIGO ]],samgung26[[#This Row],[CODIGO ]],salidas26[[CANT JUEGOS ]]) -> 1 | N30: =SUMIF(salidas26[[CODIGO ]],samgung26[[#This Row],[CODIGO ]],salidas26[CANT BARRAS]) -> 0 | O30: =(samgung26[[#This Row],["J"PRECIO COMPRA ]]*samgung26[[#This Row],[STOCK JUEGOS]]) -> 2260 | P30: =(samgung26[[#This Row],["J" PRECIO VENTA ]]*samgung26[[#This Row],[STOCK JUEGOS]]) -> 4000 | Q30: =(samgung26[[#This Row],["B"PRECIO COMPRA]]*samgung26[[#This Row],[STOCK BARRAS]]) -> 0 | R30: =(samgung26[[#This Row],["B"PRECIO VENTA ]]*samgung26[[#This Row],[STOCK BARRAS]]) -> 0 | S30: 11 | U30: 11.3 | W30: XLM-0290/0291
A31: 25 | B31: 2060 | C31: UN50FH5303/8-7L/8B | D31: =(samgung26[[#This Row],[CANTIDAD INICIAL JUEGO ]]+samgung26[[#This Row],[ENTRADAS JUEGOS ]]-samgung26[[#This Row],[SALIDAS JUEGOS]]) -> 7 | E31: =(samgung26[[#This Row],[CANTIDAD INICIAL BARRAS]]+samgung26[[#This Row],[ENTRADAS BARRAS]]-samgung26[[#This Row],[SALIDA BARRAS]]) -> 0 | F31: 300 | G31: 162 | H31: 8 | I31: =(samgung26[[#This Row],["J" PRECIO VENTA ]]/samgung26[[#This Row],[BARRAS]]) -> 37.5 | J31: =(samgung26[[#This Row],["J"PRECIO COMPRA ]]/samgung26[[#This Row],[BARRAS]]) -> 20.25 | K31: =SUMIF(entradas26[CODIGO],samgung26[[#This Row],[CODIGO ]],entradas26[[CAN JUEGOS ]]) -> 0 | L31: =SUMIF(entradas26[CODIGO],samgung26[[#This Row],[CODIGO ]],entradas26[CAN BARRAS]) -> 0 | M31: =SUMIF(salidas26[[CODIGO ]],samgung26[[#This Row],[CODIGO ]],salidas26[[CANT JUEGOS ]]) -> 0 | N31: =SUMIF(salidas26[[CODIGO ]],samgung26[[#This Row],[CODIGO ]],salidas26[CANT BARRAS]) -> 0 | O31: =(samgung26[[#This Row],["J"PRECIO COMPRA ]]*samgung26[[#This Row],[STOCK JUEGOS]]) -> 1134 | P31: =(samgung26[[#This Row],["J" PRECIO VENTA ]]*samgung26[[#This Row],[STOCK JUEGOS]]) -> 2100 | Q31: =(samgung26[[#This Row],["B"PRECIO COMPRA]]*samgung26[[#This Row],[STOCK BARRAS]]) -> 0 | R31: =(samgung26[[#This Row],["B"PRECIO VENTA ]]*samgung26[[#This Row],[STOCK BARRAS]]) -> 0 | S31: 7 | U31: 5.2 | W31: XLM-1061-1062
A32: 26 | B32: 2063 | C32: UN50NU7100./2B EDGE | D32: =(samgung26[[#This Row],[CANTIDAD INICIAL JUEGO ]]+samgung26[[#This Row],[ENTRADAS JUEGOS ]]-samgung26[[#This Row],[SALIDAS JUEGOS]]) -> 25 | E32: =(samgung26[[#This Row],[CANTIDAD INICIAL BARRAS]]+samgung26[[#This Row],[ENTRADAS BARRAS]]-samgung26[[#This Row],[SALIDA BARRAS]]) -> 0 | F32: 180 | G32: 69 | H32: 2 | I32: =(samgung26[[#This Row],["J" PRECIO VENTA ]]/samgung26[[#This Row],[BARRAS]]) -> 90 | J32: =(samgung26[[#This Row],["J"PRECIO COMPRA ]]/samgung26[[#This Row],[BARRAS]]) -> 34.5 | K32: =SUMIF(entradas26[CODIGO],samgung26[[#This Row],[CODIGO ]],entradas26[[CAN JUEGOS ]]) -> 0 | L32: =SUMIF(entradas26[CODIGO],samgung26[[#This Row],[CODIGO ]],entradas26[CAN BARRAS]) -> 0 | M32: =SUMIF(salidas26[[CODIGO ]],samgung26[[#This Row],[CODIGO ]],salidas26[[CANT JUEGOS ]]) -> 7 | N32: =SUMIF(salidas26[[CODIGO ]],samgung26[[#This Row],[CODIGO ]],salidas26[CANT BARRAS]) -> 0 | O32: =(samgung26[[#This Row],["J"PRECIO COMPRA ]]*samgung26[[#This Row],[STOCK JUEGOS]]) -> 1725 | P32: =(samgung26[[#This Row],["J" PRECIO VENTA ]]*samgung26[[#This Row],[STOCK JUEGOS]]) -> 4500 | Q32: =(samgung26[[#This Row],["B"PRECIO COMPRA]]*samgung26[[#This Row],[STOCK BARRAS]]) -> 0 | R32: =(samgung26[[#This Row],["B"PRECIO VENTA ]]*samgung26[[#This Row],[STOCK BARRAS]]) -> 0 | S32: 32 | U32: 3.25 | W32: XLM-0288 | X32: XY-077
A33: 27 | B33: 2064 | C33: UN50AU7000G/6B | D33: =(samgung26[[#This Row],[CANTIDAD INICIAL JUEGO ]]+samgung26[[#This Row],[ENTRADAS JUEGOS ]]-samgung26[[#This Row],[SALIDAS JUEGOS]]) -> 15 | E33: =(samgung26[[#This Row],[CANTIDAD INICIAL BARRAS]]+samgung26[[#This Row],[ENTRADAS BARRAS]]-samgung26[[#This Row],[SALIDA BARRAS]]) -> 0 | F33: 250 | G33: 78 | H33: 6 | I33: =(samgung26[[#This Row],["J" PRECIO VENTA ]]/samgung26[[#This Row],[BARRAS]]) -> 41.666667 | J33: =(samgung26[[#This Row],["J"PRECIO COMPRA ]]/samgung26[[#This Row],[BARRAS]]) -> 13 | K33: =SUMIF(entradas26[CODIGO],samgung26[[#This Row],[CODIGO ]],entradas26[[CAN JUEGOS ]]) -> 0 | L33: =SUMIF(entradas26[CODIGO],samgung26[[#This Row],[CODIGO ]],entradas26[CAN BARRAS]) -> 0 | M33: =SUMIF(salidas26[[CODIGO ]],samgung26[[#This Row],[CODIGO ]],salidas26[[CANT JUEGOS ]]) -> 5 | N33: =SUMIF(salidas26[[CODIGO ]],samgung26[[#This Row],[CODIGO ]],salidas26[CANT BARRAS]) -> 0 | O33: =(samgung26[[#This Row],["J"PRECIO COMPRA ]]*samgung26[[#This Row],[STOCK JUEGOS]]) -> 1170 | P33: =(samgung26[[#This Row],["J" PRECIO VENTA ]]*samgung26[[#This Row],[STOCK JUEGOS]]) -> 3750 | Q33: =(samgung26[[#This Row],["B"PRECIO COMPRA]]*samgung26[[#This Row],[STOCK BARRAS]]) -> 0 | R33: =(samgung26[[#This Row],["B"PRECIO VENTA ]]*samgung26[[#This Row],[STOCK BARRAS]]) -> 0 | S33: 20 | U33: 3.77 | W33: XLM-0808/0809 | X33: XY-930
A34: 28 | B34: 2065 | C34: UN50AU/BU8000 2B EDGE | D34: =(samgung26[[#This Row],[CANTIDAD INICIAL JUEGO ]]+samgung26[[#This Row],[ENTRADAS JUEGOS ]]-samgung26[[#This Row],[SALIDAS JUEGOS]]) -> 13 | E34: =(samgung26[[#This Row],[CANTIDAD INICIAL BARRAS]]+samgung26[[#This Row],[ENTRADAS BARRAS]]-samgung26[[#This Row],[SALIDA BARRAS]]) -> 0 | F34: 220 | G34: 93 | H34: 2 | I34: =(samgung26[[#This Row],["J" PRECIO VENTA ]]/samgung26[[#This Row],[BARRAS]]) -> 110 | J34: =(samgung26[[#This Row],["J"PRECIO COMPRA ]]/samgung26[[#This Row],[BARRAS]]) -> 46.5 | K34: =SUMIF(entradas26[CODIGO],samgung26[[#This Row],[CODIGO ]],entradas26[[CAN JUEGOS ]]) -> 0 | L34: =SUMIF(entradas26[CODIGO],samgung26[[#This Row],[CODIGO ]],entradas26[CAN BARRAS]) -> 0 | M34: =SUMIF(salidas26[[CODIGO ]],samgung26[[#This Row],[CODIGO ]],salidas26[[CANT JUEGOS ]]) -> 3 | N34: =SUMIF(salidas26[[CODIGO ]],samgung26[[#This Row],[CODIGO ]],salidas26[CANT BARRAS]) -> 0 | O34: =(samgung26[[#This Row],["J"PRECIO COMPRA ]]*samgung26[[#This Row],[STOCK JUEGOS]]) -> 1209 | P34: =(samgung26[[#This Row],["J" PRECIO VENTA ]]*samgung26[[#This Row],[STOCK JUEGOS]]) -> 2860 | Q34: =(samgung26[[#This Row],["B"PRECIO COMPRA]]*samgung26[[#This Row],[STOCK BARRAS]]) -> 0 | R34: =(samgung26[[#This Row],["B"PRECIO VENTA ]]*samgung26[[#This Row],[STOCK BARRAS]]) -> 0 | S34: 16 | U34: 3.5 | W34: XLM-1660
A35: 29 | B35: 2066 | C35: UN50J SAMSUNG | D35: =(samgung26[[#This Row],[CANTIDAD INICIAL JUEGO ]]+samgung26[[#This Row],[ENTRADAS JUEGOS ]]-samgung26[[#This Row],[SALIDAS JUEGOS]]) -> 2 | E35: =(samgung26[[#This Row],[CANTIDAD INICIAL BARRAS]]+samgung26[[#This Row],[ENTRADAS BARRAS]]-samgung26[[#This Row],[SALIDA BARRAS]]) -> 0 | F35: 300 | G35: 144 | H35: 8 | I35: =(samgung26[[#This Row],["J" PRECIO VENTA ]]/samgung26[[#This Row],[BARRAS]]) -> 37.5 | J35: =(samgung26[[#This Row],["J"PRECIO COMPRA ]]/samgung26[[#This Row],[BARRAS]]) -> 18 | K35: =SUMIF(entradas26[CODIGO],samgung26[[#This Row],[CODIGO ]],entradas26[[CAN JUEGOS ]]) -> 0 | L35: =SUMIF(entradas26[CODIGO],samgung26[[#This Row],[CODIGO ]],entradas26[CAN BARRAS]) -> 0 | M35: =SUMIF(salidas26[[CODIGO ]],samgung26[[#This Row],[CODIGO ]],salidas26[[CANT JUEGOS ]]) -> 0 | N35: =SUMIF(salidas26[[CODIGO ]],samgung26[[#This Row],[CODIGO ]],salidas26[CANT BARRAS]) -> 0 | O35: =(samgung26[[#This Row],["J"PRECIO COMPRA ]]*samgung26[[#This Row],[STOCK JUEGOS]]) -> 288 | P35: =(samgung26[[#This Row],["J" PRECIO VENTA ]]*samgung26[[#This Row],[STOCK JUEGOS]]) -> 600 | Q35: =(samgung26[[#This Row],["B"PRECIO COMPRA]]*samgung26[[#This Row],[STOCK BARRAS]]) -> 0 | R35: =(samgung26[[#This Row],["B"PRECIO VENTA ]]*samgung26[[#This Row],[STOCK BARRAS]]) -> 0 | S35: 2 | U35: 6.55 | W35: XY-0055
A36: 30 | B36: 2067 | C36: UN50J5300-50J5500 12B | D36: =(samgung26[[#This Row],[CANTIDAD INICIAL JUEGO ]]+samgung26[[#This Row],[ENTRADAS JUEGOS ]]-samgung26[[#This Row],[SALIDAS JUEGOS]]) -> 8 | E36: =(samgung26[[#This Row],[CANTIDAD INICIAL BARRAS]]+samgung26[[#This Row],[ENTRADAS BARRAS]]-samgung26[[#This Row],[SALIDA BARRAS]]) -> 0 | F36: 400 | G36: 271 | H36: 12 | I36: =(samgung26[[#This Row],["J" PRECIO VENTA ]]/samgung26[[#This Row],[BARRAS]]) -> 33.333333 | J36: =(samgung26[[#This Row],["J"PRECIO COMPRA ]]/samgung26[[#This Row],[BARRAS]]) -> 22.583333 | K36: =SUMIF(entradas26[CODIGO],samgung26[[#This Row],[CODIGO ]],entradas26[[CAN JUEGOS ]]) -> 0 | L36: =SUMIF(entradas26[CODIGO],samgung26[[#This Row],[CODIGO ]],entradas26[CAN BARRAS]) -> 0 | M36: =SUMIF(salidas26[[CODIGO ]],samgung26[[#This Row],[CODIGO ]],salidas26[[CANT JUEGOS ]]) -> 2 | N36: =SUMIF(salidas26[[CODIGO ]],samgung26[[#This Row],[CODIGO ]],salidas26[CANT BARRAS]) -> 0 | O36: =(samgung26[[#This Row],["J"PRECIO COMPRA ]]*samgung26[[#This Row],[STOCK JUEGOS]]) -> 2168 | P36: =(samgung26[[#This Row],["J" PRECIO VENTA ]]*samgung26[[#This Row],[STOCK JUEGOS]]) -> 3200 | Q36: =(samgung26[[#This Row],["B"PRECIO COMPRA]]*samgung26[[#This Row],[STOCK BARRAS]]) -> 0 | R36: =(samgung26[[#This Row],["B"PRECIO VENTA ]]*samgung26[[#This Row],[STOCK BARRAS]]) -> 0 | S36: 10 | U36: 10.3 | W36: XLM-1220/1221
A37: 31 | B37: 2069 | C37: UN55F6400/20B | D37: =(samgung26[[#This Row],[CANTIDAD INICIAL JUEGO ]]+samgung26[[#This Row],[ENTRADAS JUEGOS ]]-samgung26[[#This Row],[SALIDAS JUEGOS]]) -> 8 | E37: =(samgung26[[#This Row],[CANTIDAD INICIAL BARRAS]]+samgung26[[#This Row],[ENTRADAS BARRAS]]-samgung26[[#This Row],[SALIDA BARRAS]]) -> 10 | F37: 420 | G37: 308 | H37: 20 | I37: =(samgung26[[#This Row],["J" PRECIO VENTA ]]/samgung26[[#This Row],[BARRAS]]) -> 21 | J37: =(samgung26[[#This Row],["J"PRECIO COMPRA ]]/samgung26[[#This Row],[BARRAS]]) -> 15.4 | K37: =SUMIF(entradas26[CODIGO],samgung26[[#This Row],[CODIGO ]],entradas26[[CAN JUEGOS ]]) -> 0 | L37: =SUMIF(entradas26[CODIGO],samgung26[[#This Row],[CODIGO ]],entradas26[CAN BARRAS]) -> 0 | M37: =SUMIF(salidas26[[CODIGO ]],samgung26[[#This Row],[CODIGO ]],salidas26[[CANT JUEGOS ]]) -> 0 | N37: =SUMIF(salidas26[[CODIGO ]],samgung26[[#This Row],[CODIGO ]],salidas26[CANT BARRAS]) -> 0 | O37: =(samgung26[[#This Row],["J"PRECIO COMPRA ]]*samgung26[[#This Row],[STOCK JUEGOS]]) -> 2464 | P37: =(samgung26[[#This Row],["J" PRECIO VENTA ]]*samgung26[[#This Row],[STOCK JUEGOS]]) -> 3360 | Q37: =(samgung26[[#This Row],["B"PRECIO COMPRA]]*samgung26[[#This Row],[STOCK BARRAS]]) -> 154 | R37: =(samgung26[[#This Row],["B"PRECIO VENTA ]]*samgung26[[#This Row],[STOCK BARRAS]]) -> 210 | S37: 8 | T37: 10 | U37: 1.1 | V37: verificar | W37: 55´2013SVS55F
A38: 32 | B38: 2070 | C38: UN55F8000-55F7500/2B/83L | D38: =(samgung26[[#This Row],[CANTIDAD INICIAL JUEGO ]]+samgung26[[#This Row],[ENTRADAS JUEGOS ]]-samgung26[[#This Row],[SALIDAS JUEGOS]]) -> 6 | E38: =(samgung26[[#This Row],[CANTIDAD INICIAL BARRAS]]+samgung26[[#This Row],[ENTRADAS BARRAS]]-samgung26[[#This Row],[SALIDA BARRAS]]) -> 0 | F38: 700 | G38: 329 | H38: 2 | I38: =(samgung26[[#This Row],["J" PRECIO VENTA ]]/samgung26[[#This Row],[BARRAS]]) -> 350 | J38: =(samgung26[[#This Row],["J"PRECIO COMPRA ]]/samgung26[[#This Row],[BARRAS]]) -> 164.5 | K38: =SUMIF(entradas26[CODIGO],samgung26[[#This Row],[CODIGO ]],entradas26[[CAN JUEGOS ]]) -> 0 | L38: =SUMIF(entradas26[CODIGO],samgung26[[#This Row],[CODIGO ]],entradas26[CAN BARRAS]) -> 0 | M38: =SUMIF(salidas26[[CODIGO ]],samgung26[[#This Row],[CODIGO ]],salidas26[[CANT JUEGOS ]]) -> 0 | N38: =SUMIF(salidas26[[CODIGO ]],samgung26[[#This Row],[CODIGO ]],salidas26[CANT BARRAS]) -> 0 | O38: =(samgung26[[#This Row],["J"PRECIO COMPRA ]]*samgung26[[#This Row],[STOCK JUEGOS]]) -> 1974 | P38: =(samgung26[[#This Row],["J" PRECIO VENTA ]]*samgung26[[#This Row],[STOCK JUEGOS]]) -> 4200 | Q38: =(samgung26[[#This Row],["B"PRECIO COMPRA]]*samgung26[[#This Row],[STOCK BARRAS]]) -> 0 | R38: =(samgung26[[#This Row],["B"PRECIO VENTA ]]*samgung26[[#This Row],[STOCK BARRAS]]) -> 0 | S38: 6 | U38: 16.4 | W38: XLM-W0595
A39: 33 | B39: 2072 | C39: UN55H6400/12B | D39: =(samgung26[[#This Row],[CANTIDAD INICIAL JUEGO ]]+samgung26[[#This Row],[ENTRADAS JUEGOS ]]-samgung26[[#This Row],[SALIDAS JUEGOS]]) -> 13 | E39: =(samgung26[[#This Row],[CANTIDAD INICIAL BARRAS]]+samgung26[[#This Row],[ENTRADAS BARRAS]]-samgung26[[#This Row],[SALIDA BARRAS]]) -> 5 | F39: 480 | G39: 238 | H39: 12 | I39: =(samgung26[[#This Row],["J" PRECIO VENTA ]]/samgung26[[#This Row],[BARRAS]]) -> 40 | J39: =(samgung26[[#This Row],["J"PRECIO COMPRA ]]/samgung26[[#This Row],[BARRAS]]) -> 19.833333 | K39: =SUMIF(entradas26[CODIGO],samgung26[[#This Row],[CODIGO ]],entradas26[[CAN JUEGOS ]]) -> 10 | L39: =SUMIF(entradas26[CODIGO],samgung26[[#This Row],[CODIGO ]],entradas26[CAN BARRAS]) -> 0 | M39: =SUMIF(salidas26[[CODIGO ]],samgung26[[#This Row],[CODIGO ]],salidas26[[CANT JUEGOS ]]) -> 1 | N39: =SUMIF(salidas26[[CODIGO ]],samgung26[[#This Row],[CODIGO ]],salidas26[CANT BARRAS]) -> 0 | O39: =(samgung26[[#This Row],["J"PRECIO COMPRA ]]*samgung26[[#This Row],[STOCK JUEGOS]]) -> 3094 | P39: =(samgung26[[#This Row],["J" PRECIO VENTA ]]*samgung26[[#This Row],[STOCK JUEGOS]]) -> 6240 | Q39: =(samgung26[[#This Row],["B"PRECIO COMPRA]]*samgung26[[#This Row],[STOCK BARRAS]]) -> 99.166667 | R39: =(samgung26[[#This Row],["B"PRECIO VENTA ]]*samgung26[[#This Row],[STOCK BARRAS]]) -> 200 | S39: 4 | T39: 5 | U39: 12.5 | W39: XLM-1327-1328
A40: 34 | B40: 2075 | C40: UN55NU7100-UN55RU7100/2B EDGE | D40: =(samgung26[[#This Row],[CANTIDAD INICIAL JUEGO ]]+samgung26[[#This Row],[ENTRADAS JUEGOS ]]-samgung26[[#This Row],[SALIDAS JUEGOS]]) -> 9 | E40: =(samgung26[[#This Row],[CANTIDAD INICIAL BARRAS]]+samgung26[[#This Row],[ENTRADAS BARRAS]]-samgung26[[#This Row],[SALIDA BARRAS]]) -> 0 | F40: 200 | G40: 62 | H40: 2 | I40: =(samgung26[[#This Row],["J" PRECIO VENTA ]]/samgung26[[#This Row],[BARRAS]]) -> 100 | J40: =(samgung26[[#This Row],["J"PRECIO COMPRA ]]/samgung26[[#This Row],[BARRAS]]) -> 31 | K40: =SUMIF(entradas26[CODIGO],samgung26[[#This Row],[CODIGO ]],entradas26[[CAN JUEGOS ]]) -> 0 | L40: =SUMIF(entradas26[CODIGO],samgung26[[#This Row],[CODIGO ]],entradas26[CAN BARRAS]) -> 0 | M40: =SUMIF(salidas26[[CODIGO ]],samgung26[[#This Row],[CODIGO ]],salidas26[[CANT JUEGOS ]]) -> 18 | N40: =SUMIF(salidas26[[CODIGO ]],samgung26[[#This Row],[CODIGO ]],salidas26[CANT BARRAS]) -> 1 | O40: =(samgung26[[#This Row],["J"PRECIO COMPRA ]]*samgung26[[#This Row],[STOCK JUEGOS]]) -> 558 | P40: =(samgung26[[#This Row],["J" PRECIO VENTA ]]*samgung26[[#This Row],[STOCK JUEGOS]]) -> 1800 | Q40: =(samgung26[[#This Row],["B"PRECIO COMPRA]]*samgung26[[#This Row],[STOCK BARRAS]]) -> 0 | R40: =(samgung26[[#This Row],["B"PRECIO VENTA ]]*samgung26[[#This Row],[STOCK BARRAS]]) -> 0 | S40: 27 | T40: 1 | U40: 3.4 | W40: XLM-285 | X40: ES-ELED-690/40/7020/6V
A41: 35 | B41: 2078 | C41: UN55NU7095G/9L/4B | D41: =(samgung26[[#This Row],[CANTIDAD INICIAL JUEGO ]]+samgung26[[#This Row],[ENTRADAS JUEGOS ]]-samgung26[[#This Row],[SALIDAS JUEGOS]]) -> 6 | E41: =(samgung26[[#This Row],[CANTIDAD INICIAL BARRAS]]+samgung26[[#This Row],[ENTRADAS BARRAS]]-samgung26[[#This Row],[SALIDA BARRAS]]) -> 2 | F41: 250 | G41: 51 | H41: 4 | I41: =(samgung26[[#This Row],["J" PRECIO VENTA ]]/samgung26[[#This Row],[BARRAS]]) -> 62.5 | J41: =(samgung26[[#This Row],["J"PRECIO COMPRA ]]/samgung26[[#This Row],[BARRAS]]) -> 12.75 | K41: =SUMIF(entradas26[CODIGO],samgung26[[#This Row],[CODIGO ]],entradas26[[CAN JUEGOS ]]) -> 0 | L41: =SUMIF(entradas26[CODIGO],samgung26[[#This Row],[CODIGO ]],entradas26[CAN BARRAS]) -> 4 | M41: =SUMIF(salidas26[[CODIGO ]],samgung26[[#This Row],[CODIGO ]],salidas26[[CANT JUEGOS ]]) -> 8 | N41: =SUMIF(salidas26[[CODIGO ]],samgung26[[#This Row],[CODIGO ]],salidas26[CANT BARRAS]) -> 3 | O41: =(samgung26[[#This Row],["J"PRECIO COMPRA ]]*samgung26[[#This Row],[STOCK JUEGOS]]) -> 306 | P41: =(samgung26[[#This Row],["J" PRECIO VENTA ]]*samgung26[[#This Row],[STOCK JUEGOS]]) -> 1500 | Q41: =(samgung26[[#This Row],["B"PRECIO COMPRA]]*samgung26[[#This Row],[STOCK BARRAS]]) -> 25.5 | R41: =(samgung26[[#This Row],["B"PRECIO VENTA ]]*samgung26[[#This Row],[STOCK BARRAS]]) -> 125 | S41: 14 | T41: 1 | U41: 3.67 | W41: XLM-1224 | X41: XY-648
A42: 36 | B42: 2079 | C42: UN55MU6100- 55KU 6000 12B/ 3V | D42: =(samgung26[[#This Row],[CANTIDAD INICIAL JUEGO ]]+samgung26[[#This Row],[ENTRADAS JUEGOS ]]-samgung26[[#This Row],[SALIDAS JUEGOS]]) -> 7 | E42: =(samgung26[[#This Row],[CANTIDAD INICIAL BARRAS]]+samgung26[[#This Row],[ENTRADAS BARRAS]]-samgung26[[#This Row],[SALIDA BARRAS]]) -> 0 | F42: 450 | G42: 360 | H42: 12 | I42: =(samgung26[[#This Row],["J" PRECIO VENTA ]]/samgung26[[#This Row],[BARRAS]]) -> 37.5 | J42: =(samgung26[[#This Row],["J"PRECIO COMPRA ]]/samgung26[[#This Row],[BARRAS]]) -> 30 | K42: =SUMIF(entradas26[CODIGO],samgung26[[#This Row],[CODIGO ]],entradas26[[CAN JUEGOS ]]) -> 0 | L42: =SUMIF(entradas26[CODIGO],samgung26[[#This Row],[CODIGO ]],entradas26[CAN BARRAS]) -> 0 | M42: =SUMIF(salidas26[[CODIGO ]],samgung26[[#This Row],[CODIGO ]],salidas26[[CANT JUEGOS ]]) -> 2 | N42: =SUMIF(salidas26[[CODIGO ]],samgung26[[#This Row],[CODIGO ]],salidas26[CANT BARRAS]) -> 0 | O42: =(samgung26[[#This Row],["J"PRECIO COMPRA ]]*samgung26[[#This Row],[STOCK JUEGOS]]) -> 2520 | P42: =(samgung26[[#This Row],["J" PRECIO VENTA ]]*samgung26[[#This Row],[STOCK JUEGOS]]) -> 3150 | Q42: =(samgung26[[#This Row],["B"PRECIO COMPRA]]*samgung26[[#This Row],[STOCK BARRAS]]) -> 0 | R42: =(samgung26[[#This Row],["B"PRECIO VENTA ]]*samgung26[[#This Row],[STOCK BARRAS]]) -> 0 | S42: 9 | U42: 12 | V42: poner nombre y verificar | W42: XLM-1154-1155
A43: 37 | B43: 2081 | C43: UN55MU6500-55KU6500/2B | D43: =(samgung26[[#This Row],[CANTIDAD INICIAL JUEGO ]]+samgung26[[#This Row],[ENTRADAS JUEGOS ]]-samgung26[[#This Row],[SALIDAS JUEGOS]]) -> 21 | E43: =(samgung26[[#This Row],[CANTIDAD INICIAL BARRAS]]+samgung26[[#This Row],[ENTRADAS BARRAS]]-samgung26[[#This Row],[SALIDA BARRAS]]) -> 1 | F43: 420 | G43: 126 | H43: 2 | I43: =(samgung26[[#This Row],["J" PRECIO VENTA ]]/samgung26[[#This Row],[BARRAS]]) -> 210 | J43: =(samgung26[[#This Row],["J"PRECIO COMPRA ]]/samgung26[[#This Row],[BARRAS]]) -> 63 | K43: =SUMIF(entradas26[CODIGO],samgung26[[#This Row],[CODIGO ]],entradas26[[CAN JUEGOS ]]) -> 0 | L43: =SUMIF(entradas26[CODIGO],samgung26[[#This Row],[CODIGO ]],entradas26[CAN BARRAS]) -> 0 | M43: =SUMIF(salidas26[[CODIGO ]],samgung26[[#This Row],[CODIGO ]],salidas26[[CANT JUEGOS ]]) -> 0 | N43: =SUMIF(salidas26[[CODIGO ]],samgung26[[#This Row],[CODIGO ]],salidas26[CANT BARRAS]) -> 0 | O43: =(samgung26[[#This Row],["J"PRECIO COMPRA ]]*samgung26[[#This Row],[STOCK JUEGOS]]) -> 2646 | P43: =(samgung26[[#This Row],["J" PRECIO VENTA ]]*samgung26[[#This Row],[STOCK JUEGOS]]) -> 8820 | Q43: =(samgung26[[#This Row],["B"PRECIO COMPRA]]*samgung26[[#This Row],[STOCK BARRAS]]) -> 63 | R43: =(samgung26[[#This Row],["B"PRECIO VENTA ]]*samgung26[[#This Row],[STOCK BARRAS]]) -> 210 | S43: 21 | T43: 1 | U43: 6.3 | V43: poner nombre y verificar | W43: XLM-1117/1118
A44: 38 | B44: 2082 | C44: QN55Q60A | D44: =(samgung26[[#This Row],[CANTIDAD INICIAL JUEGO ]]+samgung26[[#This Row],[ENTRADAS JUEGOS ]]-samgung26[[#This Row],[SALIDAS JUEGOS]]) -> 9 | E44: =(samgung26[[#This Row],[CANTIDAD INICIAL BARRAS]]+samgung26[[#This Row],[ENTRADAS BARRAS]]-samgung26[[#This Row],[SALIDA BARRAS]]) -> 0 | F44: 400 | G44: 194 | H44: 2 | I44: =(samgung26[[#This Row],["J" PRECIO VENTA ]]/samgung26[[#This Row],[BARRAS]]) -> 200 | J44: =(samgung26[[#This Row],["J"PRECIO COMPRA ]]/samgung26[[#This Row],[BARRAS]]) -> 97 | K44: =SUMIF(entradas26[CODIGO],samgung26[[#This Row],[CODIGO ]],entradas26[[CAN JUEGOS ]]) -> 0 | L44: =SUMIF(entradas26[CODIGO],samgung26[[#This Row],[CODIGO ]],entradas26[CAN BARRAS]) -> 0 | M44: =SUMIF(salidas26[[CODIGO ]],samgung26[[#This Row],[CODIGO ]],salidas26[[CANT JUEGOS ]]) -> 1 | N44: =SUMIF(salidas26[[CODIGO ]],samgung26[[#This Row],[CODIGO ]],salidas26[CANT BARRAS]) -> 0 | O44: =(samgung26[[#This Row],["J"PRECIO COMPRA ]]*samgung26[[#This Row],[STOCK JUEGOS]]) -> 1746 | P44: =(samgung26[[#This Row],["J" PRECIO VENTA ]]*samgung26[[#This Row],[STOCK JUEGOS]]) -> 3600 | Q44: =(samgung26[[#This Row],["B"PRECIO COMPRA]]*samgung26[[#This Row],[STOCK BARRAS]]) -> 0 | R44: =(samgung26[[#This Row],["B"PRECIO VENTA ]]*samgung26[[#This Row],[STOCK BARRAS]]) -> 0 | S44: 10 | U44: 6.28 | W44: XLM-0103-0104
A45: 39 | B45: 2084 | C45: UN55TU SAMSUNG 8B | D45: =(samgung26[[#This Row],[CANTIDAD INICIAL JUEGO ]]+samgung26[[#This Row],[ENTRADAS JUEGOS ]]-samgung26[[#This Row],[SALIDAS JUEGOS]]) -> 1 | E45: =(samgung26[[#This Row],[CANTIDAD INICIAL BARRAS]]+samgung26[[#This Row],[ENTRADAS BARRAS]]-samgung26[[#This Row],[SALIDA BARRAS]]) -> 0 | F45: 300 | G45: 125 | H45: 8 | I45: =(samgung26[[#This Row],["J" PRECIO VENTA ]]/samgung26[[#This Row],[BARRAS]]) -> 37.5 | J45: =(samgung26[[#This Row],["J"PRECIO COMPRA ]]/samgung26[[#This Row],[BARRAS]]) -> 15.625 | K45: =SUMIF(entradas26[CODIGO],samgung26[[#This Row],[CODIGO ]],entradas26[[CAN JUEGOS ]]) -> 0 | L45: =SUMIF(entradas26[CODIGO],samgung26[[#This Row],[CODIGO ]],entradas26[CAN BARRAS]) -> 0 | M45: =SUMIF(salidas26[[CODIGO ]],samgung26[[#This Row],[CODIGO ]],salidas26[[CANT JUEGOS ]]) -> 0 | N45: =SUMIF(salidas26[[CODIGO ]],samgung26[[#This Row],[CODIGO ]],salidas26[CANT BARRAS]) -> 0 | O45: =(samgung26[[#This Row],["J"PRECIO COMPRA ]]*samgung26[[#This Row],[STOCK JUEGOS]]) -> 125 | P45: =(samgung26[[#This Row],["J" PRECIO VENTA ]]*samgung26[[#This Row],[STOCK JUEGOS]]) -> 300 | Q45: =(samgung26[[#This Row],["B"PRECIO COMPRA]]*samgung26[[#This Row],[STOCK BARRAS]]) -> 0 | R45: =(samgung26[[#This Row],["B"PRECIO VENTA ]]*samgung26[[#This Row],[STOCK BARRAS]]) -> 0 | S45: 1
A46: 40 | B46: 2085 | C46: UN55JS9000 2B | D46: =(samgung26[[#This Row],[CANTIDAD INICIAL JUEGO ]]+samgung26[[#This Row],[ENTRADAS JUEGOS ]]-samgung26[[#This Row],[SALIDAS JUEGOS]]) -> 5 | E46: =(samgung26[[#This Row],[CANTIDAD INICIAL BARRAS]]+samgung26[[#This Row],[ENTRADAS BARRAS]]-samgung26[[#This Row],[SALIDA BARRAS]]) -> 0 | F46: 450 | G46: 264 | H46: 2 | I46: =(samgung26[[#This Row],["J" PRECIO VENTA ]]/samgung26[[#This Row],[BARRAS]]) -> 225 | J46: =(samgung26[[#This Row],["J"PRECIO COMPRA ]]/samgung26[[#This Row],[BARRAS]]) -> 132 | K46: =SUMIF(entradas26[CODIGO],samgung26[[#This Row],[CODIGO ]],entradas26[[CAN JUEGOS ]]) -> 0 | L46: =SUMIF(entradas26[CODIGO],samgung26[[#This Row],[CODIGO ]],entradas26[CAN BARRAS]) -> 0 | M46: =SUMIF(salidas26[[CODIGO ]],samgung26[[#This Row],[CODIGO ]],salidas26[[CANT JUEGOS ]]) -> 0 | N46: =SUMIF(salidas26[[CODIGO ]],samgung26[[#This Row],[CODIGO ]],salidas26[CANT BARRAS]) -> 0 | O46: =(samgung26[[#This Row],["J"PRECIO COMPRA ]]*samgung26[[#This Row],[STOCK JUEGOS]]) -> 1320 | P46: =(samgung26[[#This Row],["J" PRECIO VENTA ]]*samgung26[[#This Row],[STOCK JUEGOS]]) -> 2250 | Q46: =(samgung26[[#This Row],["B"PRECIO COMPRA]]*samgung26[[#This Row],[STOCK BARRAS]]) -> 0 | R46: =(samgung26[[#This Row],["B"PRECIO VENTA ]]*samgung26[[#This Row],[STOCK BARRAS]]) -> 0 | S46: 5 | U46: 13.2 | W46: XLM-W0051
A47: 41 | B47: 2087 | C47: UN58NU7100 /2B EDGE | D47: =(samgung26[[#This Row],[CANTIDAD INICIAL JUEGO ]]+samgung26[[#This Row],[ENTRADAS JUEGOS ]]-samgung26[[#This Row],[SALIDAS JUEGOS]]) -> 0 | E47: =(samgung26[[#This Row],[CANTIDAD INICIAL BARRAS]]+samgung26[[#This Row],[ENTRADAS BARRAS]]-samgung26[[#This Row],[SALIDA BARRAS]]) -> 0 | F47: 240 | G47: 112 | H47: 2 | I47: =(samgung26[[#This Row],["J" PRECIO VENTA ]]/samgung26[[#This Row],[BARRAS]]) -> 120 | J47: =(samgung26[[#This Row],["J"PRECIO COMPRA ]]/samgung26[[#This Row],[BARRAS]]) -> 56 | K47: =SUMIF(entradas26[CODIGO],samgung26[[#This Row],[CODIGO ]],entradas26[[CAN JUEGOS ]]) -> 0 | L47: =SUMIF(entradas26[CODIGO],samgung26[[#This Row],[CODIGO ]],entradas26[CAN BARRAS]) -> 0 | M47: =SUMIF(salidas26[[CODIGO ]],samgung26[[#This Row],[CODIGO ]],salidas26[[CANT JUEGOS ]]) -> 13 | N47: =SUMIF(salidas26[[CODIGO ]],samgung26[[#This Row],[CODIGO ]],salidas26[CANT BARRAS]) -> 1 | O47: =(samgung26[[#This Row],["J"PRECIO COMPRA ]]*samgung26[[#This Row],[STOCK JUEGOS]]) -> 0 | P47: =(samgung26[[#This Row],["J" PRECIO VENTA ]]*samgung26[[#This Row],[STOCK JUEGOS]]) -> 0 | Q47: =(samgung26[[#This Row],["B"PRECIO COMPRA]]*samgung26[[#This Row],[STOCK BARRAS]]) -> 0 | R47: =(samgung26[[#This Row],["B"PRECIO VENTA ]]*samgung26[[#This Row],[STOCK BARRAS]]) -> 0 | S47: 13 | T47: 1 | U47: 3.6 | W47: XLM-1382 | X47: XLM-1188
A48: 42 | B48: 2088 | C48: UN 58 AU7000/8B | D48: =(samgung26[[#This Row],[CANTIDAD INICIAL JUEGO ]]+samgung26[[#This Row],[ENTRADAS JUEGOS ]]-samgung26[[#This Row],[SALIDAS JUEGOS]]) -> 2 | E48: =(samgung26[[#This Row],[CANTIDAD INICIAL BARRAS]]+samgung26[[#This Row],[ENTRADAS BARRAS]]-samgung26[[#This Row],[SALIDA BARRAS]]) -> 0 | F48: 420 | G48: 269 | H48: 8 | I48: =(samgung26[[#This Row],["J" PRECIO VENTA ]]/samgung26[[#This Row],[BARRAS]]) -> 52.5 | J48: =(samgung26[[#This Row],["J"PRECIO COMPRA ]]/samgung26[[#This Row],[BARRAS]]) -> 33.625 | K48: =SUMIF(entradas26[CODIGO],samgung26[[#This Row],[CODIGO ]],entradas26[[CAN JUEGOS ]]) -> 0 | L48: =SUMIF(entradas26[CODIGO],samgung26[[#This Row],[CODIGO ]],entradas26[CAN BARRAS]) -> 0 | M48: =SUMIF(salidas26[[CODIGO ]],samgung26[[#This Row],[CODIGO ]],salidas26[[CANT JUEGOS ]]) -> 0 | N48: =SUMIF(salidas26[[CODIGO ]],samgung26[[#This Row],[CODIGO ]],salidas26[CANT BARRAS]) -> 0 | O48: =(samgung26[[#This Row],["J"PRECIO COMPRA ]]*samgung26[[#This Row],[STOCK JUEGOS]]) -> 538 | P48: =(samgung26[[#This Row],["J" PRECIO VENTA ]]*samgung26[[#This Row],[STOCK JUEGOS]]) -> 840 | Q48: =(samgung26[[#This Row],["B"PRECIO COMPRA]]*samgung26[[#This Row],[STOCK BARRAS]]) -> 0 | R48: =(samgung26[[#This Row],["B"PRECIO VENTA ]]*samgung26[[#This Row],[STOCK BARRAS]]) -> 0 | S48: 2
A49: 43 | B49: 2089 | C49: UN58TU7100 8B/6L 3V-58TU7000 | D49: =(samgung26[[#This Row],[CANTIDAD INICIAL JUEGO ]]+samgung26[[#This Row],[ENTRADAS JUEGOS ]]-samgung26[[#This Row],[SALIDAS JUEGOS]]) -> 22 | E49: =(samgung26[[#This Row],[CANTIDAD INICIAL BARRAS]]+samgung26[[#This Row],[ENTRADAS BARRAS]]-samgung26[[#This Row],[SALIDA BARRAS]]) -> 0 | F49: 320 | G49: 87.4 | H49: 8 | I49: =(samgung26[[#This Row],["J" PRECIO VENTA ]]/samgung26[[#This Row],[BARRAS]]) -> 40 | J49: =(samgung26[[#This Row],["J"PRECIO COMPRA ]]/samgung26[[#This Row],[BARRAS]]) -> 10.925 | K49: =SUMIF(entradas26[CODIGO],samgung26[[#This Row],[CODIGO ]],entradas26[[CAN JUEGOS ]]) -> 23 | L49: =SUMIF(entradas26[CODIGO],samgung26[[#This Row],[CODIGO ]],entradas26[CAN BARRAS]) -> 0 | M49: =SUMIF(salidas26[[CODIGO ]],samgung26[[#This Row],[CODIGO ]],salidas26[[CANT JUEGOS ]]) -> 2 | N49: =SUMIF(salidas26[[CODIGO ]],samgung26[[#This Row],[CODIGO ]],salidas26[CANT BARRAS]) -> 0 | O49: =(samgung26[[#This Row],["J"PRECIO COMPRA ]]*samgung26[[#This Row],[STOCK JUEGOS]]) -> 1922.8 | P49: =(samgung26[[#This Row],["J" PRECIO VENTA ]]*samgung26[[#This Row],[STOCK JUEGOS]]) -> 7040 | Q49: =(samgung26[[#This Row],["B"PRECIO COMPRA]]*samgung26[[#This Row],[STOCK BARRAS]]) -> 0 | R49: =(samgung26[[#This Row],["B"PRECIO VENTA ]]*samgung26[[#This Row],[STOCK BARRAS]]) -> 0 | S49: 1 | U49: 4.6 | W49: XLM-1611/1612
A50: 44 | B50: 2090 | C50: UN58FH/12B | D50: =(samgung26[[#This Row],[CANTIDAD INICIAL JUEGO ]]+samgung26[[#This Row],[ENTRADAS JUEGOS ]]-samgung26[[#This Row],[SALIDAS JUEGOS]]) -> 15 | E50: =(samgung26[[#This Row],[CANTIDAD INICIAL BARRAS]]+samgung26[[#This Row],[ENTRADAS BARRAS]]-samgung26[[#This Row],[SALIDA BARRAS]]) -> 10 | F50: 350 | G50: 166 | H50: 12 | I50: =(samgung26[[#This Row],["J" PRECIO VENTA ]]/samgung26[[#This Row],[BARRAS]]) -> 29.166667 | J50: =(samgung26[[#This Row],["J"PRECIO COMPRA ]]/samgung26[[#This Row],[BARRAS]]) -> 13.833333 | K50: =SUMIF(entradas26[CODIGO],samgung26[[#This Row],[CODIGO ]],entradas26[[CAN JUEGOS ]]) -> 0 | L50: =SUMIF(entradas26[CODIGO],samgung26[[#This Row],[CODIGO ]],entradas26[CAN BARRAS]) -> 0 | M50: =SUMIF(salidas26[[CODIGO ]],samgung26[[#This Row],[CODIGO ]],salidas26[[CANT JUEGOS ]]) -> 8 | N50: =SUMIF(salidas26[[CODIGO ]],samgung26[[#This Row],[CODIGO ]],salidas26[CANT BARRAS]) -> 0 | O50: =(samgung26[[#This Row],["J"PRECIO COMPRA ]]*samgung26[[#This Row],[STOCK JUEGOS]]) -> 2490 | P50: =(samgung26[[#This Row],["J" PRECIO VENTA ]]*samgung26[[#This Row],[STOCK JUEGOS]]) -> 5250 | Q50: =(samgung26[[#This Row],["B"PRECIO COMPRA]]*samgung26[[#This Row],[STOCK BARRAS]]) -> 138.33333 | R50: =(samgung26[[#This Row],["B"PRECIO VENTA ]]*samgung26[[#This Row],[STOCK BARRAS]]) -> 291.66667 | S50: 23 | T50: 10 | U50: 7.2 | W50: XLM-1074/1075
A51: 45 | B51: 2092 | C51: QN60Q60A | D51: =(samgung26[[#This Row],[CANTIDAD INICIAL JUEGO ]]+samgung26[[#This Row],[ENTRADAS JUEGOS ]]-samgung26[[#This Row],[SALIDAS JUEGOS]]) -> 19 | E51: =(samgung26[[#This Row],[CANTIDAD INICIAL BARRAS]]+samgung26[[#This Row],[ENTRADAS BARRAS]]-samgung26[[#This Row],[SALIDA BARRAS]]) -> 0 | F51: 400 | G51: 125 | H51: 2 | I51: =(samgung26[[#This Row],["J" PRECIO VENTA ]]/samgung26[[#This Row],[BARRAS]]) -> 200 | J51: =(samgung26[[#This Row],["J"PRECIO COMPRA ]]/samgung26[[#This Row],[BARRAS]]) -> 62.5 | K51: =SUMIF(entradas26[CODIGO],samgung26[[#This Row],[CODIGO ]],entradas26[[CAN JUEGOS ]]) -> 0 | L51: =SUMIF(entradas26[CODIGO],samgung26[[#This Row],[CODIGO ]],entradas26[CAN BARRAS]) -> 0 | M51: =SUMIF(salidas26[[CODIGO ]],samgung26[[#This Row],[CODIGO ]],salidas26[[CANT JUEGOS ]]) -> 0 | N51: =SUMIF(salidas26[[CODIGO ]],samgung26[[#This Row],[CODIGO ]],salidas26[CANT BARRAS]) -> 0 | O51: =(samgung26[[#This Row],["J"PRECIO COMPRA ]]*samgung26[[#This Row],[STOCK JUEGOS]]) -> 2375 | P51: =(samgung26[[#This Row],["J" PRECIO VENTA ]]*samgung26[[#This Row],[STOCK JUEGOS]]) -> 7600 | Q51: =(samgung26[[#This Row],["B"PRECIO COMPRA]]*samgung26[[#This Row],[STOCK BARRAS]]) -> 0 | R51: =(samgung26[[#This Row],["B"PRECIO VENTA ]]*samgung26[[#This Row],[STOCK BARRAS]]) -> 0 | S51: 19 | X51: ES-ELED-741/72/7020/3V B+W
A52: 46 | B52: 2093 | C52: UN60FH6003/12B | D52: =(samgung26[[#This Row],[CANTIDAD INICIAL JUEGO ]]+samgung26[[#This Row],[ENTRADAS JUEGOS ]]-samgung26[[#This Row],[SALIDAS JUEGOS]]) -> 5 | E52: =(samgung26[[#This Row],[CANTIDAD INICIAL BARRAS]]+samgung26[[#This Row],[ENTRADAS BARRAS]]-samgung26[[#This Row],[SALIDA BARRAS]]) -> 2 | F52: 400 | G52: 240 | H52: 12 | I52: =(samgung26[[#This Row],["J" PRECIO VENTA ]]/samgung26[[#This Row],[BARRAS]]) -> 33.333333 | J52: =(samgung26[[#This Row],["J"PRECIO COMPRA ]]/samgung26[[#This Row],[BARRAS]]) -> 20 | K52: =SUMIF(entradas26[CODIGO],samgung26[[#This Row],[CODIGO ]],entradas26[[CAN JUEGOS ]]) -> 0 | L52: =SUMIF(entradas26[CODIGO],samgung26[[#This Row],[CODIGO ]],entradas26[CAN BARRAS]) -> 0 | M52: =SUMIF(salidas26[[CODIGO ]],samgung26[[#This Row],[CODIGO ]],salidas26[[CANT JUEGOS ]]) -> 3 | N52: =SUMIF(salidas26[[CODIGO ]],samgung26[[#This Row],[CODIGO ]],salidas26[CANT BARRAS]) -> 1 | O52: =(samgung26[[#This Row],["J"PRECIO COMPRA ]]*samgung26[[#This Row],[STOCK JUEGOS]]) -> 1200 | P52: =(samgung26[[#This Row],["J" PRECIO VENTA ]]*samgung26[[#This Row],[STOCK JUEGOS]]) -> 2000 | Q52: =(samgung26[[#This Row],["B"PRECIO COMPRA]]*samgung26[[#This Row],[STOCK BARRAS]]) -> 40 | R52: =(samgung26[[#This Row],["B"PRECIO VENTA ]]*samgung26[[#This Row],[STOCK BARRAS]]) -> 66.666667 | S52: 8 | T52: 3 | U52: 8 | W52: XLM-0811/0812
A53: 47 | B53: 2094 | C53: UN60H6400 14 B | D53: =(samgung26[[#This Row],[CANTIDAD INICIAL JUEGO ]]+samgung26[[#This Row],[ENTRADAS JUEGOS ]]-samgung26[[#This Row],[SALIDAS JUEGOS]]) -> 9 | E53: =(samgung26[[#This Row],[CANTIDAD INICIAL BARRAS]]+samgung26[[#This Row],[ENTRADAS BARRAS]]-samgung26[[#This Row],[SALIDA BARRAS]]) -> 0 | F53: 500 | G53: 340 | H53: 14 | I53: =(samgung26[[#This Row],["J" PRECIO VENTA ]]/samgung26[[#This Row],[BARRAS]]) -> 35.714286 | J53: =(samgung26[[#This Row],["J"PRECIO COMPRA ]]/samgung26[[#This Row],[BARRAS]]) -> 24.285714 | K53: =SUMIF(entradas26[CODIGO],samgung26[[#This Row],[CODIGO ]],entradas26[[CAN JUEGOS ]]) -> 0 | L53: =SUMIF(entradas26[CODIGO],samgung26[[#This Row],[CODIGO ]],entradas26[CAN BARRAS]) -> 0 | M53: =SUMIF(salidas26[[CODIGO ]],samgung26[[#This Row],[CODIGO ]],salidas26[[CANT JUEGOS ]]) -> 0 | N53: =SUMIF(salidas26[[CODIGO ]],samgung26[[#This Row],[CODIGO ]],salidas26[CANT BARRAS]) -> 0 | O53: =(samgung26[[#This Row],["J"PRECIO COMPRA ]]*samgung26[[#This Row],[STOCK JUEGOS]]) -> 3060 | P53: =(samgung26[[#This Row],["J" PRECIO VENTA ]]*samgung26[[#This Row],[STOCK JUEGOS]]) -> 4500 | Q53: =(samgung26[[#This Row],["B"PRECIO COMPRA]]*samgung26[[#This Row],[STOCK BARRAS]]) -> 0 | R53: =(samgung26[[#This Row],["B"PRECIO VENTA ]]*samgung26[[#This Row],[STOCK BARRAS]]) -> 0 | S53: 9 | U53: 15.6 | W53: XLM-1656/1655
A54: 48 | B54: 2095 | C54: UN60AU8000G-60BU8000/2B | D54: =(samgung26[[#This Row],[CANTIDAD INICIAL JUEGO ]]+samgung26[[#This Row],[ENTRADAS JUEGOS ]]-samgung26[[#This Row],[SALIDAS JUEGOS]]) -> 0 | E54: =(samgung26[[#This Row],[CANTIDAD INICIAL BARRAS]]+samgung26[[#This Row],[ENTRADAS BARRAS]]-samgung26[[#This Row],[SALIDA BARRAS]]) -> 0 | F54: 250 | G54: 158 | H54: 2 | I54: =(samgung26[[#This Row],["J" PRECIO VENTA ]]/samgung26[[#This Row],[BARRAS]]) -> 125 | J54: =(samgung26[[#This Row],["J"PRECIO COMPRA ]]/samgung26[[#This Row],[BARRAS]]) -> 79 | K54: =SUMIF(entradas26[CODIGO],samgung26[[#This Row],[CODIGO ]],entradas26[[CAN JUEGOS ]]) -> 0 | L54: =SUMIF(entradas26[CODIGO],samgung26[[#This Row],[CODIGO ]],entradas26[CAN BARRAS]) -> 2 | M54: =SUMIF(salidas26[[CODIGO ]],samgung26[[#This Row],[CODIGO ]],salidas26[[CANT JUEGOS ]]) -> 10 | N54: =SUMIF(salidas26[[CODIGO ]],samgung26[[#This Row],[CODIGO ]],salidas26[CANT BARRAS]) -> 2 | O54: =(samgung26[[#This Row],["J"PRECIO COMPRA ]]*samgung26[[#This Row],[STOCK JUEGOS]]) -> 0 | P54: =(samgung26[[#This Row],["J" PRECIO VENTA ]]*samgung26[[#This Row],[STOCK JUEGOS]]) -> 0 | Q54: =(samgung26[[#This Row],["B"PRECIO COMPRA]]*samgung26[[#This Row],[STOCK BARRAS]]) -> 0 | R54: =(samgung26[[#This Row],["B"PRECIO VENTA ]]*samgung26[[#This Row],[STOCK BARRAS]]) -> 0 | S54: 10 | W54: XLM-1398
A55: 49 | B55: 2096 | C55: UN65MU6500- 65KU6500/2B | D55: =(samgung26[[#This Row],[CANTIDAD INICIAL JUEGO ]]+samgung26[[#This Row],[ENTRADAS JUEGOS ]]-samgung26[[#This Row],[SALIDAS JUEGOS]]) -> 10 | E55: =(samgung26[[#This Row],[CANTIDAD INICIAL BARRAS]]+samgung26[[#This Row],[ENTRADAS BARRAS]]-samgung26[[#This Row],[SALIDA BARRAS]]) -> 0 | F55: 550 | G55: 312 | H55: 2 | I55: =(samgung26[[#This Row],["J" PRECIO VENTA ]]/samgung26[[#This Row],[BARRAS]]) -> 275 | J55: =(samgung26[[#This Row],["J"PRECIO COMPRA ]]/samgung26[[#This Row],[BARRAS]]) -> 156 | K55: =SUMIF(entradas26[CODIGO],samgung26[[#This Row],[CODIGO ]],entradas26[[CAN JUEGOS ]]) -> 0 | L55: =SUMIF(entradas26[CODIGO],samgung26[[#This Row],[CODIGO ]],entradas26[CAN BARRAS]) -> 0 | M55: =SUMIF(salidas26[[CODIGO ]],samgung26[[#This Row],[CODIGO ]],salidas26[[CANT JUEGOS ]]) -> 0 | N55: =SUMIF(salidas26[[CODIGO ]],samgung26[[#This Row],[CODIGO ]],salidas26[CANT BARRAS]) -> 0 | O55: =(samgung26[[#This Row],["J"PRECIO COMPRA ]]*samgung26[[#This Row],[STOCK JUEGOS]]) -> 3120 | P55: =(samgung26[[#This Row],["J" PRECIO VENTA ]]*samgung26[[#This Row],[STOCK JUEGOS]]) -> 5500 | Q55: =(samgung26[[#This Row],["B"PRECIO COMPRA]]*samgung26[[#This Row],[STOCK BARRAS]]) -> 0 | R55: =(samgung26[[#This Row],["B"PRECIO VENTA ]]*samgung26[[#This Row],[STOCK BARRAS]]) -> 0 | S55: 10 | U55: 9 | W55: XLM-1712/1713
A56: 50 | B56: 2097 | C56: UN65AU8000-65BU8000/2B | D56: =(samgung26[[#This Row],[CANTIDAD INICIAL JUEGO ]]+samgung26[[#This Row],[ENTRADAS JUEGOS ]]-samgung26[[#This Row],[SALIDAS JUEGOS]]) -> 5 | E56: =(samgung26[[#This Row],[CANTIDAD INICIAL BARRAS]]+samgung26[[#This Row],[ENTRADAS BARRAS]]-samgung26[[#This Row],[SALIDA BARRAS]]) -> 1 | F56: 320 | G56: 94 | H56: 2 | I56: =(samgung26[[#This Row],["J" PRECIO VENTA ]]/samgung26[[#This Row],[BARRAS]]) -> 160 | J56: =(samgung26[[#This Row],["J"PRECIO COMPRA ]]/samgung26[[#This Row],[BARRAS]]) -> 47 | K56: =SUMIF(entradas26[CODIGO],samgung26[[#This Row],[CODIGO ]],entradas26[[CAN JUEGOS ]]) -> 0 | L56: =SUMIF(entradas26[CODIGO],samgung26[[#This Row],[CODIGO ]],entradas26[CAN BARRAS]) -> 0 | M56: =SUMIF(salidas26[[CODIGO ]],samgung26[[#This Row],[CODIGO ]],salidas26[[CANT JUEGOS ]]) -> 6 | N56: =SUMIF(salidas26[[CODIGO ]],samgung26[[#This Row],[CODIGO ]],salidas26[CANT BARRAS]) -> 0 | O56: =(samgung26[[#This Row],["J"PRECIO COMPRA ]]*samgung26[[#This Row],[STOCK JUEGOS]]) -> 470 | P56: =(samgung26[[#This Row],["J" PRECIO VENTA ]]*samgung26[[#This Row],[STOCK JUEGOS]]) -> 1600 | Q56: =(samgung26[[#This Row],["B"PRECIO COMPRA]]*samgung26[[#This Row],[STOCK BARRAS]]) -> 47 | R56: =(samgung26[[#This Row],["B"PRECIO VENTA ]]*samgung26[[#This Row],[STOCK BARRAS]]) -> 160 | S56: 11 | T56: 1 | U56: 6.7 | W56: XLM-1398 | X56: XM6343
B57: 2106 | C57: QN65Q8CNAG | D57: =(samgung26[[#This Row],[CANTIDAD INICIAL JUEGO ]]+samgung26[[#This Row],[ENTRADAS JUEGOS ]]-samgung26[[#This Row],[SALIDAS JUEGOS]]) -> 3 | E57: =(samgung26[[#This Row],[CANTIDAD INICIAL BARRAS]]+samgung26[[#This Row],[ENTRADAS BARRAS]]-samgung26[[#This Row],[SALIDA BARRAS]]) -> 0 | F57: 800 | G57: 494 | H57: 2 | I57: =(samgung26[[#This Row],["J" PRECIO VENTA ]]/samgung26[[#This Row],[BARRAS]]) -> 400 | J57: =(samgung26[[#This Row],["J"PRECIO COMPRA ]]/samgung26[[#This Row],[BARRAS]]) -> 247 | K57: =SUMIF(entradas26[CODIGO],samgung26[[#This Row],[CODIGO ]],entradas26[[CAN JUEGOS ]]) -> 0 | L57: =SUMIF(entradas26[CODIGO],samgung26[[#This Row],[CODIGO ]],entradas26[CAN BARRAS]) -> 0 | M57: =SUMIF(salidas26[[CODIGO ]],samgung26[[#This Row],[CODIGO ]],salidas26[[CANT JUEGOS ]]) -> 0 | N57: =SUMIF(salidas26[[CODIGO ]],samgung26[[#This Row],[CODIGO ]],salidas26[CANT BARRAS]) -> 0 | O57: =(samgung26[[#This Row],["J"PRECIO COMPRA ]]*samgung26[[#This Row],[STOCK JUEGOS]]) -> 1482 | P57: =(samgung26[[#This Row],["J" PRECIO VENTA ]]*samgung26[[#This Row],[STOCK JUEGOS]]) -> 2400 | Q57: =(samgung26[[#This Row],["B"PRECIO COMPRA]]*samgung26[[#This Row],[STOCK BARRAS]]) -> 0 | R57: =(samgung26[[#This Row],["B"PRECIO VENTA ]]*samgung26[[#This Row],[STOCK BARRAS]]) -> 0 | S57: 3 | U57: 16 | W57: XLM-W1411
B58: 2091 | C58: UN65 H6400 | D58: =(samgung26[[#This Row],[CANTIDAD INICIAL JUEGO ]]+samgung26[[#This Row],[ENTRADAS JUEGOS ]]-samgung26[[#This Row],[SALIDAS JUEGOS]]) -> 8 | E58: =(samgung26[[#This Row],[CANTIDAD INICIAL BARRAS]]+samgung26[[#This Row],[ENTRADAS BARRAS]]-samgung26[[#This Row],[SALIDA BARRAS]]) -> 0 | F58: 700 | I58: =(samgung26[[#This Row],["J" PRECIO VENTA ]]/samgung26[[#This Row],[BARRAS]]) -> #DIV/0! | J58: =(samgung26[[#This Row],["J"PRECIO COMPRA ]]/samgung26[[#This Row],[BARRAS]]) -> #DIV/0! | K58: =SUMIF(entradas26[CODIGO],samgung26[[#This Row],[CODIGO ]],entradas26[[CAN JUEGOS ]]) -> 10 | L58: =SUMIF(entradas26[CODIGO],samgung26[[#This Row],[CODIGO ]],entradas26[CAN BARRAS]) -> 0 | M58: =SUMIF(salidas26[[CODIGO ]],samgung26[[#This Row],[CODIGO ]],salidas26[[CANT JUEGOS ]]) -> 2 | N58: =SUMIF(salidas26[[CODIGO ]],samgung26[[#This Row],[CODIGO ]],salidas26[CANT BARRAS]) -> 0 | O58: =(samgung26[[#This Row],["J"PRECIO COMPRA ]]*samgung26[[#This Row],[STOCK JUEGOS]]) -> 0 | P58: =(samgung26[[#This Row],["J" PRECIO VENTA ]]*samgung26[[#This Row],[STOCK JUEGOS]]) -> 5600 | Q58: =(samgung26[[#This Row],["B"PRECIO COMPRA]]*samgung26[[#This Row],[STOCK BARRAS]]) -> #DIV/0! | R58: =(samgung26[[#This Row],["B"PRECIO VENTA ]]*samgung26[[#This Row],[STOCK BARRAS]]) -> #DIV/0! | W58: XLM-1951/1952
B59: 2086 | C59: UN65 AU7000 | D59: =(samgung26[[#This Row],[CANTIDAD INICIAL JUEGO ]]+samgung26[[#This Row],[ENTRADAS JUEGOS ]]-samgung26[[#This Row],[SALIDAS JUEGOS]]) -> 10 | E59: =(samgung26[[#This Row],[CANTIDAD INICIAL BARRAS]]+samgung26[[#This Row],[ENTRADAS BARRAS]]-samgung26[[#This Row],[SALIDA BARRAS]]) -> 0 | F59: 420 | I59: =(samgung26[[#This Row],["J" PRECIO VENTA ]]/samgung26[[#This Row],[BARRAS]]) -> #DIV/0! | J59: =(samgung26[[#This Row],["J"PRECIO COMPRA ]]/samgung26[[#This Row],[BARRAS]]) -> #DIV/0! | K59: =SUMIF(entradas26[CODIGO],samgung26[[#This Row],[CODIGO ]],entradas26[[CAN JUEGOS ]]) -> 10 | L59: =SUMIF(entradas26[CODIGO],samgung26[[#This Row],[CODIGO ]],entradas26[CAN BARRAS]) -> 0 | M59: =SUMIF(salidas26[[CODIGO ]],samgung26[[#This Row],[CODIGO ]],salidas26[[CANT JUEGOS ]]) -> 0 | N59: =SUMIF(salidas26[[CODIGO ]],samgung26[[#This Row],[CODIGO ]],salidas26[CANT BARRAS]) -> 0 | O59: =(samgung26[[#This Row],["J"PRECIO COMPRA ]]*samgung26[[#This Row],[STOCK JUEGOS]]) -> 0 | P59: =(samgung26[[#This Row],["J" PRECIO VENTA ]]*samgung26[[#This Row],[STOCK JUEGOS]]) -> 4200 | Q59: =(samgung26[[#This Row],["B"PRECIO COMPRA]]*samgung26[[#This Row],[STOCK BARRAS]]) -> #DIV/0! | R59: =(samgung26[[#This Row],["B"PRECIO VENTA ]]*samgung26[[#This Row],[STOCK BARRAS]]) -> #DIV/0! | W59: XLM-1373/1374
A60: 51 | B60: 2098 | C60: UN65 MU6100/16B | D60: =(samgung26[[#This Row],[CANTIDAD INICIAL JUEGO ]]+samgung26[[#This Row],[ENTRADAS JUEGOS ]]-samgung26[[#This Row],[SALIDAS JUEGOS]]) -> 10 | E60: =(samgung26[[#This Row],[CANTIDAD INICIAL BARRAS]]+samgung26[[#This Row],[ENTRADAS BARRAS]]-samgung26[[#This Row],[SALIDA BARRAS]]) -> 0 | F60: 700 | G60: 480 | H60: 16 | I60: =(samgung26[[#This Row],["J" PRECIO VENTA ]]/samgung26[[#This Row],[BARRAS]]) -> 43.75 | J60: =(samgung26[[#This Row],["J"PRECIO COMPRA ]]/samgung26[[#This Row],[BARRAS]]) -> 30 | K60: =SUMIF(entradas26[CODIGO],samgung26[[#This Row],[CODIGO ]],entradas26[[CAN JUEGOS ]]) -> 0 | L60: =SUMIF(entradas26[CODIGO],samgung26[[#This Row],[CODIGO ]],entradas26[CAN BARRAS]) -> 0 | M60: =SUMIF(salidas26[[CODIGO ]],samgung26[[#This Row],[CODIGO ]],salidas26[[CANT JUEGOS ]]) -> 0 | N60: =SUMIF(salidas26[[CODIGO ]],samgung26[[#This Row],[CODIGO ]],salidas26[CANT BARRAS]) -> 0 | O60: =(samgung26[[#This Row],["J"PRECIO COMPRA ]]*samgung26[[#This Row],[STOCK JUEGOS]]) -> 4800 | P60: =(samgung26[[#This Row],["J" PRECIO VENTA ]]*samgung26[[#This Row],[STOCK JUEGOS]]) -> 7000 | Q60: =(samgung26[[#This Row],["B"PRECIO COMPRA]]*samgung26[[#This Row],[STOCK BARRAS]]) -> 0 | R60: =(samgung26[[#This Row],["B"PRECIO VENTA ]]*samgung26[[#This Row],[STOCK BARRAS]]) -> 0 | S60: 10 | U60: 16 | W60: XLM-1661-1662
A61: 52 | B61: 2099 | C61: UN65NU7100/2B | D61: =(samgung26[[#This Row],[CANTIDAD INICIAL JUEGO ]]+samgung26[[#This Row],[ENTRADAS JUEGOS ]]-samgung26[[#This Row],[SALIDAS JUEGOS]]) -> 21 | E61: =(samgung26[[#This Row],[CANTIDAD INICIAL BARRAS]]+samgung26[[#This Row],[ENTRADAS BARRAS]]-samgung26[[#This Row],[SALIDA BARRAS]]) -> 0 | F61: 260 | G61: 106 | H61: 2 | I61: =(samgung26[[#This Row],["J" PRECIO VENTA ]]/samgung26[[#This Row],[BARRAS]]) -> 130 | J61: =(samgung26[[#This Row],["J"PRECIO COMPRA ]]/samgung26[[#This Row],[BARRAS]]) -> 53 | K61: =SUMIF(entradas26[CODIGO],samgung26[[#This Row],[CODIGO ]],entradas26[[CAN JUEGOS ]]) -> 0 | L61: =SUMIF(entradas26[CODIGO],samgung26[[#This Row],[CODIGO ]],entradas26[CAN BARRAS]) -> 0 | M61: =SUMIF(salidas26[[CODIGO ]],samgung26[[#This Row],[CODIGO ]],salidas26[[CANT JUEGOS ]]) -> 1 | N61: =SUMIF(salidas26[[CODIGO ]],samgung26[[#This Row],[CODIGO ]],salidas26[CANT BARRAS]) -> 0 | O61: =(samgung26[[#This Row],["J"PRECIO COMPRA ]]*samgung26[[#This Row],[STOCK JUEGOS]]) -> 2226 | P61: =(samgung26[[#This Row],["J" PRECIO VENTA ]]*samgung26[[#This Row],[STOCK JUEGOS]]) -> 5460 | Q61: =(samgung26[[#This Row],["B"PRECIO COMPRA]]*samgung26[[#This Row],[STOCK BARRAS]]) -> 0 | R61: =(samgung26[[#This Row],["B"PRECIO VENTA ]]*samgung26[[#This Row],[STOCK BARRAS]]) -> 0 | S61: 22 | U61: 4.6 | W61: XLM-0755
A62: 53 | B62: 2100 | C62: UN70TU7000/10B/7L | D62: =(samgung26[[#This Row],[CANTIDAD INICIAL JUEGO ]]+samgung26[[#This Row],[ENTRADAS JUEGOS ]]-samgung26[[#This Row],[SALIDAS JUEGOS]]) -> 10 | E62: =(samgung26[[#This Row],[CANTIDAD INICIAL BARRAS]]+samgung26[[#This Row],[ENTRADAS BARRAS]]-samgung26[[#This Row],[SALIDA BARRAS]]) -> 0 | F62: 460 | G62: 171 | H62: 10 | I62: =(samgung26[[#This Row],["J" PRECIO VENTA ]]/samgung26[[#This Row],[BARRAS]]) -> 46 | J62: =(samgung26[[#This Row],["J"PRECIO COMPRA ]]/samgung26[[#This Row],[BARRAS]]) -> 17.1 | K62: =SUMIF(entradas26[CODIGO],samgung26[[#This Row],[CODIGO ]],entradas26[[CAN JUEGOS ]]) -> 0 | L62: =SUMIF(entradas26[CODIGO],samgung26[[#This Row],[CODIGO ]],entradas26[CAN BARRAS]) -> 0 | M62: =SUMIF(salidas26[[CODIGO ]],samgung26[[#This Row],[CODIGO ]],salidas26[[CANT JUEGOS ]]) -> 0 | N62: =SUMIF(salidas26[[CODIGO ]],samgung26[[#This Row],[CODIGO ]],salidas26[CANT BARRAS]) -> 0 | O62: =(samgung26[[#This Row],["J"PRECIO COMPRA ]]*samgung26[[#This Row],[STOCK JUEGOS]]) -> 1710 | P62: =(samgung26[[#This Row],["J" PRECIO VENTA ]]*samgung26[[#This Row],[STOCK JUEGOS]]) -> 4600 | Q62: =(samgung26[[#This Row],["B"PRECIO COMPRA]]*samgung26[[#This Row],[STOCK BARRAS]]) -> 0 | R62: =(samgung26[[#This Row],["B"PRECIO VENTA ]]*samgung26[[#This Row],[STOCK BARRAS]]) -> 0 | S62: 10 | U62: 6.5 | W62: XLM-1671-1672
A63: 54 | B63: 2101 | C63: UN70AU7000G 10B | D63: =(samgung26[[#This Row],[CANTIDAD INICIAL JUEGO ]]+samgung26[[#This Row],[ENTRADAS JUEGOS ]]-samgung26[[#This Row],[SALIDAS JUEGOS]]) -> 1 | E63: =(samgung26[[#This Row],[CANTIDAD INICIAL BARRAS]]+samgung26[[#This Row],[ENTRADAS BARRAS]]-samgung26[[#This Row],[SALIDA BARRAS]]) -> 0 | F63: 400 | H63: 10 | I63: =(samgung26[[#This Row],["J" PRECIO VENTA ]]/samgung26[[#This Row],[BARRAS]]) -> 40 | J63: =(samgung26[[#This Row],["J"PRECIO COMPRA ]]/samgung26[[#This Row],[BARRAS]]) -> 0 | K63: =SUMIF(entradas26[CODIGO],samgung26[[#This Row],[CODIGO ]],entradas26[[CAN JUEGOS ]]) -> 0 | L63: =SUMIF(entradas26[CODIGO],samgung26[[#This Row],[CODIGO ]],entradas26[CAN BARRAS]) -> 0 | M63: =SUMIF(salidas26[[CODIGO ]],samgung26[[#This Row],[CODIGO ]],salidas26[[CANT JUEGOS ]]) -> 0 | N63: =SUMIF(salidas26[[CODIGO ]],samgung26[[#This Row],[CODIGO ]],salidas26[CANT BARRAS]) -> 0 | O63: =(samgung26[[#This Row],["J"PRECIO COMPRA ]]*samgung26[[#This Row],[STOCK JUEGOS]]) -> 0 | P63: =(samgung26[[#This Row],["J" PRECIO VENTA ]]*samgung26[[#This Row],[STOCK JUEGOS]]) -> 400 | Q63: =(samgung26[[#This Row],["B"PRECIO COMPRA]]*samgung26[[#This Row],[STOCK BARRAS]]) -> 0 | R63: =(samgung26[[#This Row],["B"PRECIO VENTA ]]*samgung26[[#This Row],[STOCK BARRAS]]) -> 0 | S63: 1
A64: 55 | B64: 2102 | C64: UN75F400/36B | D64: =(samgung26[[#This Row],[CANTIDAD INICIAL JUEGO ]]+samgung26[[#This Row],[ENTRADAS JUEGOS ]]-samgung26[[#This Row],[SALIDAS JUEGOS]]) -> 3 | E64: =(samgung26[[#This Row],[CANTIDAD INICIAL BARRAS]]+samgung26[[#This Row],[ENTRADAS BARRAS]]-samgung26[[#This Row],[SALIDA BARRAS]]) -> 0 | F64: 1300 | G64: 618 | H64: 36 | I64: =(samgung26[[#This Row],["J" PRECIO VENTA ]]/samgung26[[#This Row],[BARRAS]]) -> 36.111111 | J64: =(samgung26[[#This Row],["J"PRECIO COMPRA ]]/samgung26[[#This Row],[BARRAS]]) -> 17.166667 | K64: =SUMIF(entradas26[CODIGO],samgung26[[#This Row],[CODIGO ]],entradas26[[CAN JUEGOS ]]) -> 0 | L64: =SUMIF(entradas26[CODIGO],samgung26[[#This Row],[CODIGO ]],entradas26[CAN BARRAS]) -> 0 | M64: =SUMIF(salidas26[[CODIGO ]],samgung26[[#This Row],[CODIGO ]],salidas26[[CANT JUEGOS ]]) -> 1 | N64: =SUMIF(salidas26[[CODIGO ]],samgung26[[#This Row],[CODIGO ]],salidas26[CANT BARRAS]) -> 0 | O64: =(samgung26[[#This Row],["J"PRECIO COMPRA ]]*samgung26[[#This Row],[STOCK JUEGOS]]) -> 1854 | P64: =(samgung26[[#This Row],["J" PRECIO VENTA ]]*samgung26[[#This Row],[STOCK JUEGOS]]) -> 3900 | Q64: =(samgung26[[#This Row],["B"PRECIO COMPRA]]*samgung26[[#This Row],[STOCK BARRAS]]) -> 0 | R64: =(samgung26[[#This Row],["B"PRECIO VENTA ]]*samgung26[[#This Row],[STOCK BARRAS]]) -> 0 | S64: 4 | U64: 44.5
A65: 56 | B65: 2103 | C65: UN75TU7000/18B/4L | D65: =(samgung26[[#This Row],[CANTIDAD INICIAL JUEGO ]]+samgung26[[#This Row],[ENTRADAS JUEGOS ]]-samgung26[[#This Row],[SALIDAS JUEGOS]]) -> 10 | E65: =(samgung26[[#This Row],[CANTIDAD INICIAL BARRAS]]+samgung26[[#This Row],[ENTRADAS BARRAS]]-samgung26[[#This Row],[SALIDA BARRAS]]) -> 0 | F65: 600 | G65: 189 | H65: 18 | I65: =(samgung26[[#This Row],["J" PRECIO VENTA ]]/samgung26[[#This Row],[BARRAS]]) -> 33.333333 | J65: =(samgung26[[#This Row],["J"PRECIO COMPRA ]]/samgung26[[#This Row],[BARRAS]]) -> 10.5 | K65: =SUMIF(entradas26[CODIGO],samgung26[[#This Row],[CODIGO ]],entradas26[[CAN JUEGOS ]]) -> 0 | L65: =SUMIF(entradas26[CODIGO],samgung26[[#This Row],[CODIGO ]],entradas26[CAN BARRAS]) -> 0 | M65: =SUMIF(salidas26[[CODIGO ]],samgung26[[#This Row],[CODIGO ]],salidas26[[CANT JUEGOS ]]) -> 0 | N65: =SUMIF(salidas26[[CODIGO ]],samgung26[[#This Row],[CODIGO ]],salidas26[CANT BARRAS]) -> 0 | O65: =(samgung26[[#This Row],["J"PRECIO COMPRA ]]*samgung26[[#This Row],[STOCK JUEGOS]]) -> 1890 | P65: =(samgung26[[#This Row],["J" PRECIO VENTA ]]*samgung26[[#This Row],[STOCK JUEGOS]]) -> 6000 | Q65: =(samgung26[[#This Row],["B"PRECIO COMPRA]]*samgung26[[#This Row],[STOCK BARRAS]]) -> 0 | R65: =(samgung26[[#This Row],["B"PRECIO VENTA ]]*samgung26[[#This Row],[STOCK BARRAS]]) -> 0 | S65: 10 | U65: 7.2 | W65: XLM-1706-1707-1708
B66: 2107 | C66: 75 AU8000-/4B | D66: =(samgung26[[#This Row],[CANTIDAD INICIAL JUEGO ]]+samgung26[[#This Row],[ENTRADAS JUEGOS ]]-samgung26[[#This Row],[SALIDAS JUEGOS]]) -> 8 | E66: =(samgung26[[#This Row],[CANTIDAD INICIAL BARRAS]]+samgung26[[#This Row],[ENTRADAS BARRAS]]-samgung26[[#This Row],[SALIDA BARRAS]]) -> 0 | F66: 400 | G66: 232 | H66: 4 | I66: =(samgung26[[#This Row],["J" PRECIO VENTA ]]/samgung26[[#This Row],[BARRAS]]) -> 100 | J66: =(samgung26[[#This Row],["J"PRECIO COMPRA ]]/samgung26[[#This Row],[BARRAS]]) -> 58 | K66: =SUMIF(entradas26[CODIGO],samgung26[[#This Row],[CODIGO ]],entradas26[[CAN JUEGOS ]]) -> 0 | L66: =SUMIF(entradas26[CODIGO],samgung26[[#This Row],[CODIGO ]],entradas26[CAN BARRAS]) -> 0 | M66: =SUMIF(salidas26[[CODIGO ]],samgung26[[#This Row],[CODIGO ]],salidas26[[CANT JUEGOS ]]) -> 2 | N66: =SUMIF(salidas26[[CODIGO ]],samgung26[[#This Row],[CODIGO ]],salidas26[CANT BARRAS]) -> 0 | O66: =(samgung26[[#This Row],["J"PRECIO COMPRA ]]*samgung26[[#This Row],[STOCK JUEGOS]]) -> 1856 | P66: =(samgung26[[#This Row],["J" PRECIO VENTA ]]*samgung26[[#This Row],[STOCK JUEGOS]]) -> 3200 | Q66: =(samgung26[[#This Row],["B"PRECIO COMPRA]]*samgung26[[#This Row],[STOCK BARRAS]]) -> 0 | R66: =(samgung26[[#This Row],["B"PRECIO VENTA ]]*samgung26[[#This Row],[STOCK BARRAS]]) -> 0 | S66: 10 | W66: ES-ELED-553/42/7020/3V W+W
A67: 57 | B67: 2104 | C67: UN82TU7000/18B/5L | D67: =(samgung26[[#This Row],[CANTIDAD INICIAL JUEGO ]]+samgung26[[#This Row],[ENTRADAS JUEGOS ]]-samgung26[[#This Row],[SALIDAS JUEGOS]]) -> 7 | E67: =(samgung26[[#This Row],[CANTIDAD INICIAL BARRAS]]+samgung26[[#This Row],[ENTRADAS BARRAS]]-samgung26[[#This Row],[SALIDA BARRAS]]) -> 15 | F67: 600 | G67: 236 | H67: 18 | I67: =(samgung26[[#This Row],["J" PRECIO VENTA ]]/samgung26[[#This Row],[BARRAS]]) -> 33.333333 | J67: =(samgung26[[#This Row],["J"PRECIO COMPRA ]]/samgung26[[#This Row],[BARRAS]]) -> 13.111111 | K67: =SUMIF(entradas26[CODIGO],samgung26[[#This Row],[CODIGO ]],entradas26[[CAN JUEGOS ]]) -> 0 | L67: =SUMIF(entradas26[CODIGO],samgung26[[#This Row],[CODIGO ]],entradas26[CAN BARRAS]) -> 18 | M67: =SUMIF(salidas26[[CODIGO ]],samgung26[[#This Row],[CODIGO ]],salidas26[[CANT JUEGOS ]]) -> 2 | N67: =SUMIF(salidas26[[CODIGO ]],samgung26[[#This Row],[CODIGO ]],salidas26[CANT BARRAS]) -> 3 | O67: =(samgung26[[#This Row],["J"PRECIO COMPRA ]]*samgung26[[#This Row],[STOCK JUEGOS]]) -> 1652 | P67: =(samgung26[[#This Row],["J" PRECIO VENTA ]]*samgung26[[#This Row],[STOCK JUEGOS]]) -> 4200 | Q67: =(samgung26[[#This Row],["B"PRECIO COMPRA]]*samgung26[[#This Row],[STOCK BARRAS]]) -> 196.66667 | R67: =(samgung26[[#This Row],["B"PRECIO VENTA ]]*samgung26[[#This Row],[STOCK BARRAS]]) -> 500 | S67: 9 | U67: 9 | W67: XLM-2047-2048-2049
B68: 2108 | C68: 65 TU8500 | D68: =(samgung26[[#This Row],[CANTIDAD INICIAL JUEGO ]]+samgung26[[#This Row],[ENTRADAS JUEGOS ]]-samgung26[[#This Row],[SALIDAS JUEGOS]]) -> 9 | E68: =(samgung26[[#This Row],[CANTIDAD INICIAL BARRAS]]+samgung26[[#This Row],[ENTRADAS BARRAS]]-samgung26[[#This Row],[SALIDA BARRAS]]) -> 0 | F68: 300 | G68: 105 | I68: =(samgung26[[#This Row],["J" PRECIO VENTA ]]/samgung26[[#This Row],[BARRAS]]) -> #DIV/0! | J68: =(samgung26[[#This Row],["J"PRECIO COMPRA ]]/samgung26[[#This Row],[BARRAS]]) -> #DIV/0! | K68: =SUMIF(entradas26[CODIGO],samgung26[[#This Row],[CODIGO ]],entradas26[[CAN JUEGOS ]]) -> 10 | L68: =SUMIF(entradas26[CODIGO],samgung26[[#This Row],[CODIGO ]],entradas26[CAN BARRAS]) -> 0 | M68: =SUMIF(salidas26[[CODIGO ]],samgung26[[#This Row],[CODIGO ]],salidas26[[CANT JUEGOS ]]) -> 1 | N68: =SUMIF(salidas26[[CODIGO ]],samgung26[[#This Row],[CODIGO ]],salidas26[CANT BARRAS]) -> 0 | O68: =(samgung26[[#This Row],["J"PRECIO COMPRA ]]*samgung26[[#This Row],[STOCK JUEGOS]]) -> 945 | P68: =(samgung26[[#This Row],["J" PRECIO VENTA ]]*samgung26[[#This Row],[STOCK JUEGOS]]) -> 2700 | Q68: =(samgung26[[#This Row],["B"PRECIO COMPRA]]*samgung26[[#This Row],[STOCK BARRAS]]) -> #DIV/0! | R68: =(samgung26[[#This Row],["B"PRECIO VENTA ]]*samgung26[[#This Row],[STOCK BARRAS]]) -> #DIV/0! | U68: 505 | W68: XLM-2101
A69: 58 | B69: 2105 | C69: UN85AU8000G 4B EGDE | D69: =(samgung26[[#This Row],[CANTIDAD INICIAL JUEGO ]]+samgung26[[#This Row],[ENTRADAS JUEGOS ]]-samgung26[[#This Row],[SALIDAS JUEGOS]]) -> 7 | E69: =(samgung26[[#This Row],[CANTIDAD INICIAL BARRAS]]+samgung26[[#This Row],[ENTRADAS BARRAS]]-samgung26[[#This Row],[SALIDA BARRAS]]) -> 0 | F69: 600 | G69: 272 | H69: 4 | I69: =(samgung26[[#This Row],["J" PRECIO VENTA ]]/samgung26[[#This Row],[BARRAS]]) -> 150 | J69: =(samgung26[[#This Row],["J"PRECIO COMPRA ]]/samgung26[[#This Row],[BARRAS]]) -> 68 | K69: =SUMIF(entradas26[CODIGO],samgung26[[#This Row],[CODIGO ]],entradas26[[CAN JUEGOS ]]) -> 0 | L69: =SUMIF(entradas26[CODIGO],samgung26[[#This Row],[CODIGO ]],entradas26[CAN BARRAS]) -> 0 | M69: =SUMIF(salidas26[[CODIGO ]],samgung26[[#This Row],[CODIGO ]],salidas26[[CANT JUEGOS ]]) -> 3 | N69: =SUMIF(salidas26[[CODIGO ]],samgung26[[#This Row],[CODIGO ]],salidas26[CANT BARRAS]) -> 0 | O69: =(samgung26[[#This Row],["J"PRECIO COMPRA ]]*samgung26[[#This Row],[STOCK JUEGOS]]) -> 1904 | P69: =(samgung26[[#This Row],["J" PRECIO VENTA ]]*samgung26[[#This Row],[STOCK JUEGOS]]) -> 4200 | Q69: =(samgung26[[#This Row],["B"PRECIO COMPRA]]*samgung26[[#This Row],[STOCK BARRAS]]) -> 0 | R69: =(samgung26[[#This Row],["B"PRECIO VENTA ]]*samgung26[[#This Row],[STOCK BARRAS]]) -> 0 | S69: 10 | U69: 12.8 | W69: XLM-W1152 | X69: ES-ELED-559/52/7020/3V W+W
A70: 59
A71: 60

Sheet HAIER
B2: HAIER
B4: CODIGO | C4: DESCRIPCION | D4: STOCK JUEGOS | E4: STOCK BARRAS | F4: "J" PRECIO VENTA | G4: "J"PRECIO COMPRA | H4: BARRAS | I4: "B"PRECIO VENTA | J4: "B"PRECIO COMPRA | K4: ENTRADAS JUEGOS | L4: ENTRADAS BARRAS | M4: SALIDAS JUEGOS | N4: SALIDA BARRAS | O4: CAPITAL JUEGOS | P4: CAPITAL/GANANCIA/JUEGOS | Q4: CAPITAL BARRA | R4: CAP GAN BARRAS | S4: CANTIDAD INICIAL JUEGO | T4: CANTIDAD INICIAL BARRAS | U4: PRECIO EN $ | V4: CODIGO 2
A5: 1 | B5: 3000 | C5: 32B8000 3B/10LED/3V | D5: =(haier26[[#This Row],[CANTIDAD INICIAL JUEGO ]]+haier26[[#This Row],[ENTRADAS JUEGOS ]]-haier26[[#This Row],[SALIDAS JUEGOS]]) -> 13 | E5: =(haier26[[#This Row],[CANTIDAD INICIAL BARRAS]]+haier26[[#This Row],[ENTRADAS BARRAS]]-haier26[[#This Row],[SALIDA BARRAS]]) -> 1 | F5: 90 | G5: 54 | H5: 3 | I5: =(haier26[[#This Row],["J" PRECIO VENTA ]]/haier26[[#This Row],[BARRAS]]) -> 30 | J5: =(haier26[[#This Row],["J"PRECIO COMPRA ]]/haier26[[#This Row],[BARRAS]]) -> 18 | K5: =SUMIF(entradas26[CODIGO],haier26[[#This Row],[CODIGO ]],entradas26[[CAN JUEGOS ]]) -> 20 | L5: =SUMIF(entradas26[CODIGO],haier26[[#This Row],[CODIGO ]],entradas26[CAN BARRAS]) -> 0 | M5: =SUMIF(salidas26[[CODIGO ]],haier26[[#This Row],[CODIGO ]],salidas26[[CANT JUEGOS ]]) -> 11 | N5: =SUMIF(salidas26[[CODIGO ]],haier26[[#This Row],[CODIGO ]],salidas26[CANT BARRAS]) -> 0 | O5: =(haier26[[#This Row],["J"PRECIO COMPRA ]]*haier26[[#This Row],[STOCK JUEGOS]]) -> 702 | P5: =(haier26[[#This Row],["J" PRECIO VENTA ]]*haier26[[#This Row],[STOCK JUEGOS]]) -> 1170 | Q5: =(haier26[[#This Row],["B"PRECIO COMPRA]]*haier26[[#This Row],[STOCK BARRAS]]) -> 18 | R5: =(haier26[[#This Row],["B"PRECIO VENTA ]]*haier26[[#This Row],[STOCK BARRAS]]) -> 30 | S5: 4 | T5: 1
A6: 2 | B6: 3001 | C6: 32B7000 3B/10LED/3V DOBLE CONECTOR | D6: =(haier26[[#This Row],[CANTIDAD INICIAL JUEGO ]]+haier26[[#This Row],[ENTRADAS JUEGOS ]]-haier26[[#This Row],[SALIDAS JUEGOS]]) -> 10 | E6: =(haier26[[#This Row],[CANTIDAD INICIAL BARRAS]]+haier26[[#This Row],[ENTRADAS BARRAS]]-haier26[[#This Row],[SALIDA BARRAS]]) -> 0 | F6: 100 | G6: 93 | H6: 3 | I6: =(haier26[[#This Row],["J" PRECIO VENTA ]]/haier26[[#This Row],[BARRAS]]) -> 33.333333 | J6: =(haier26[[#This Row],["J"PRECIO COMPRA ]]/haier26[[#This Row],[BARRAS]]) -> 31 | K6: =SUMIF(entradas26[CODIGO],haier26[[#This Row],[CODIGO ]],entradas26[[CAN JUEGOS ]]) -> 0 | L6: =SUMIF(entradas26[CODIGO],haier26[[#This Row],[CODIGO ]],entradas26[CAN BARRAS]) -> 0 | M6: =SUMIF(salidas26[[CODIGO ]],haier26[[#This Row],[CODIGO ]],salidas26[[CANT JUEGOS ]]) -> 8 | N6: =SUMIF(salidas26[[CODIGO ]],haier26[[#This Row],[CODIGO ]],salidas26[CANT BARRAS]) -> 0 | O6: =(haier26[[#This Row],["J"PRECIO COMPRA ]]*haier26[[#This Row],[STOCK JUEGOS]]) -> 930 | P6: =(haier26[[#This Row],["J" PRECIO VENTA ]]*haier26[[#This Row],[STOCK JUEGOS]]) -> 1000 | Q6: =(haier26[[#This Row],["B"PRECIO COMPRA]]*haier26[[#This Row],[STOCK BARRAS]]) -> 0 | R6: =(haier26[[#This Row],["B"PRECIO VENTA ]]*haier26[[#This Row],[STOCK BARRAS]]) -> 0 | S6: 18
A7: 3 | B7: 3003 | C7: 40B8000 4B/12LED/3V | D7: =(haier26[[#This Row],[CANTIDAD INICIAL JUEGO ]]+haier26[[#This Row],[ENTRADAS JUEGOS ]]-haier26[[#This Row],[SALIDAS JUEGOS]]) -> 6 | E7: =(haier26[[#This Row],[CANTIDAD INICIAL BARRAS]]+haier26[[#This Row],[ENTRADAS BARRAS]]-haier26[[#This Row],[SALIDA BARRAS]]) -> 2 | F7: 160 | G7: 105 | H7: 4 | I7: =(haier26[[#This Row],["J" PRECIO VENTA ]]/haier26[[#This Row],[BARRAS]]) -> 40 | J7: =(haier26[[#This Row],["J"PRECIO COMPRA ]]/haier26[[#This Row],[BARRAS]]) -> 26.25 | K7: =SUMIF(entradas26[CODIGO],haier26[[#This Row],[CODIGO ]],entradas26[[CAN JUEGOS ]]) -> 0 | L7: =SUMIF(entradas26[CODIGO],haier26[[#This Row],[CODIGO ]],entradas26[CAN BARRAS]) -> 4 | M7: =SUMIF(salidas26[[CODIGO ]],haier26[[#This Row],[CODIGO ]],salidas26[[CANT JUEGOS ]]) -> 6 | N7: =SUMIF(salidas26[[CODIGO ]],haier26[[#This Row],[CODIGO ]],salidas26[CANT BARRAS]) -> 4 | O7: =(haier26[[#This Row],["J"PRECIO COMPRA ]]*haier26[[#This Row],[STOCK JUEGOS]]) -> 630 | P7: =(haier26[[#This Row],["J" PRECIO VENTA ]]*haier26[[#This Row],[STOCK JUEGOS]]) -> 960 | Q7: =(haier26[[#This Row],["B"PRECIO COMPRA]]*haier26[[#This Row],[STOCK BARRAS]]) -> 52.5 | R7: =(haier26[[#This Row],["B"PRECIO VENTA ]]*haier26[[#This Row],[STOCK BARRAS]]) -> 80 | S7: 12 | T7: 2
A8: 4 | B8: 3006 | C8: 42B8000 4B/15LEDS/3V | D8: =(haier26[[#This Row],[CANTIDAD INICIAL JUEGO ]]+haier26[[#This Row],[ENTRADAS JUEGOS ]]-haier26[[#This Row],[SALIDAS JUEGOS]]) -> 12 | E8: =(haier26[[#This Row],[CANTIDAD INICIAL BARRAS]]+haier26[[#This Row],[ENTRADAS BARRAS]]-haier26[[#This Row],[SALIDA BARRAS]]) -> 0 | F8: 180 | G8: 131 | H8: 4 | I8: =(haier26[[#This Row],["J" PRECIO VENTA ]]/haier26[[#This Row],[BARRAS]]) -> 45 | J8: =(haier26[[#This Row],["J"PRECIO COMPRA ]]/haier26[[#This Row],[BARRAS]]) -> 32.75 | K8: =SUMIF(entradas26[CODIGO],haier26[[#This Row],[CODIGO ]],entradas26[[CAN JUEGOS ]]) -> 0 | L8: =SUMIF(entradas26[CODIGO],haier26[[#This Row],[CODIGO ]],entradas26[CAN BARRAS]) -> 0 | M8: =SUMIF(salidas26[[CODIGO ]],haier26[[#This Row],[CODIGO ]],salidas26[[CANT JUEGOS ]]) -> 3 | N8: =SUMIF(salidas26[[CODIGO ]],haier26[[#This Row],[CODIGO ]],salidas26[CANT BARRAS]) -> 0 | O8: =(haier26[[#This Row],["J"PRECIO COMPRA ]]*haier26[[#This Row],[STOCK JUEGOS]]) -> 1572 | P8: =(haier26[[#This Row],["J" PRECIO VENTA ]]*haier26[[#This Row],[STOCK JUEGOS]]) -> 2160 | Q8: =(haier26[[#This Row],["B"PRECIO COMPRA]]*haier26[[#This Row],[STOCK BARRAS]]) -> 0 | R8: =(haier26[[#This Row],["B"PRECIO VENTA ]]*haier26[[#This Row],[STOCK BARRAS]]) -> 0 | S8: 15
A9: 5 | B9: 3009 | C9: 43U6600 4B/ 8L/3V DIF 180º | D9: =(haier26[[#This Row],[CANTIDAD INICIAL JUEGO ]]+haier26[[#This Row],[ENTRADAS JUEGOS ]]-haier26[[#This Row],[SALIDAS JUEGOS]]) -> 19 | E9: =(haier26[[#This Row],[CANTIDAD INICIAL BARRAS]]+haier26[[#This Row],[ENTRADAS BARRAS]]-haier26[[#This Row],[SALIDA BARRAS]]) -> 3 | F9: 220 | G9: 74 | H9: 4 | I9: =(haier26[[#This Row],["J" PRECIO VENTA ]]/haier26[[#This Row],[BARRAS]]) -> 55 | J9: =(haier26[[#This Row],["J"PRECIO COMPRA ]]/haier26[[#This Row],[BARRAS]]) -> 18.5 | K9: =SUMIF(entradas26[CODIGO],haier26[[#This Row],[CODIGO ]],entradas26[[CAN JUEGOS ]]) -> 0 | L9: =SUMIF(entradas26[CODIGO],haier26[[#This Row],[CODIGO ]],entradas26[CAN BARRAS]) -> 0 | M9: =SUMIF(salidas26[[CODIGO ]],haier26[[#This Row],[CODIGO ]],salidas26[[CANT JUEGOS ]]) -> 0 | N9: =SUMIF(salidas26[[CODIGO ]],haier26[[#This Row],[CODIGO ]],salidas26[CANT BARRAS]) -> 0 | O9: =(haier26[[#This Row],["J"PRECIO COMPRA ]]*haier26[[#This Row],[STOCK JUEGOS]]) -> 1406 | P9: =(haier26[[#This Row],["J" PRECIO VENTA ]]*haier26[[#This Row],[STOCK JUEGOS]]) -> 4180 | Q9: =(haier26[[#This Row],["B"PRECIO COMPRA]]*haier26[[#This Row],[STOCK BARRAS]]) -> 55.5 | R9: =(haier26[[#This Row],["B"PRECIO VENTA ]]*haier26[[#This Row],[STOCK BARRAS]]) -> 165 | S9: 19 | T9: 3
A10: 6 | B10: 3012 | C10: 48M600 10B/6-7LEDS Y 4 -8LEDS/3V | D10: =(haier26[[#This Row],[CANTIDAD INICIAL JUEGO ]]+haier26[[#This Row],[ENTRADAS JUEGOS ]]-haier26[[#This Row],[SALIDAS JUEGOS]]) -> 16 | E10: =(haier26[[#This Row],[CANTIDAD INICIAL BARRAS]]+haier26[[#This Row],[ENTRADAS BARRAS]]-haier26[[#This Row],[SALIDA BARRAS]]) -> 8 | F10: 260 | G10: 154 | H10: 10 | I10: =(haier26[[#This Row],["J" PRECIO VENTA ]]/haier26[[#This Row],[BARRAS]]) -> 26 | J10: =(haier26[[#This Row],["J"PRECIO COMPRA ]]/haier26[[#This Row],[BARRAS]]) -> 15.4 | K10: =SUMIF(entradas26[CODIGO],haier26[[#This Row],[CODIGO ]],entradas26[[CAN JUEGOS ]]) -> 0 | L10: =SUMIF(entradas26[CODIGO],haier26[[#This Row],[CODIGO ]],entradas26[CAN BARRAS]) -> 0 | M10: =SUMIF(salidas26[[CODIGO ]],haier26[[#This Row],[CODIGO ]],salidas26[[CANT JUEGOS ]]) -> 1 | N10: =SUMIF(salidas26[[CODIGO ]],haier26[[#This Row],[CODIGO ]],salidas26[CANT BARRAS]) -> 4 | O10: =(haier26[[#This Row],["J"PRECIO COMPRA ]]*haier26[[#This Row],[STOCK JUEGOS]]) -> 2464 | P10: =(haier26[[#This Row],["J" PRECIO VENTA ]]*haier26[[#This Row],[STOCK JUEGOS]]) -> 4160 | Q10: =(haier26[[#This Row],["B"PRECIO COMPRA]]*haier26[[#This Row],[STOCK BARRAS]]) -> 123.2 | R10: =(haier26[[#This Row],["B"PRECIO VENTA ]]*haier26[[#This Row],[STOCK BARRAS]]) -> 208 | S10: 17 | T10: 12
A11: 7 | B11: 3015 | C11: 48M600 10B/8 - 8 LEDS/3V | D11: =(haier26[[#This Row],[CANTIDAD INICIAL JUEGO ]]+haier26[[#This Row],[ENTRADAS JUEGOS ]]-haier26[[#This Row],[SALIDAS JUEGOS]]) -> 16 | E11: =(haier26[[#This Row],[CANTIDAD INICIAL BARRAS]]+haier26[[#This Row],[ENTRADAS BARRAS]]-haier26[[#This Row],[SALIDA BARRAS]]) -> 8 | F11: 260 | G11: 147 | H11: 10 | I11: =(haier26[[#This Row],["J" PRECIO VENTA ]]/haier26[[#This Row],[BARRAS]]) -> 26 | J11: =(haier26[[#This Row],["J"PRECIO COMPRA ]]/haier26[[#This Row],[BARRAS]]) -> 14.7 | K11: =SUMIF(entradas26[CODIGO],haier26[[#This Row],[CODIGO ]],entradas26[[CAN JUEGOS ]]) -> 0 | L11: =SUMIF(entradas26[CODIGO],haier26[[#This Row],[CODIGO ]],entradas26[CAN BARRAS]) -> 10 | M11: =SUMIF(salidas26[[CODIGO ]],haier26[[#This Row],[CODIGO ]],salidas26[[CANT JUEGOS ]]) -> 3 | N11: =SUMIF(salidas26[[CODIGO ]],haier26[[#This Row],[CODIGO ]],salidas26[CANT BARRAS]) -> 2 | O11: =(haier26[[#This Row],["J"PRECIO COMPRA ]]*haier26[[#This Row],[STOCK JUEGOS]]) -> 2352 | P11: =(haier26[[#This Row],["J" PRECIO VENTA ]]*haier26[[#This Row],[STOCK JUEGOS]]) -> 4160 | Q11: =(haier26[[#This Row],["B"PRECIO COMPRA]]*haier26[[#This Row],[STOCK BARRAS]]) -> 117.6 | R11: =(haier26[[#This Row],["B"PRECIO VENTA ]]*haier26[[#This Row],[STOCK BARRAS]]) -> 208 | S11: 19
A12: 8 | B12: 3018 | C12: 49 HAIER 9B/5L | D12: =(haier26[[#This Row],[CANTIDAD INICIAL JUEGO ]]+haier26[[#This Row],[ENTRADAS JUEGOS ]]-haier26[[#This Row],[SALIDAS JUEGOS]]) -> 25 | E12: =(haier26[[#This Row],[CANTIDAD INICIAL BARRAS]]+haier26[[#This Row],[ENTRADAS BARRAS]]-haier26[[#This Row],[SALIDA BARRAS]]) -> 0 | F12: 250 | G12: 86 | H12: 9 | I12: =(haier26[[#This Row],["J" PRECIO VENTA ]]/haier26[[#This Row],[BARRAS]]) -> 27.777778 | J12: =(haier26[[#This Row],["J"PRECIO COMPRA ]]/haier26[[#This Row],[BARRAS]]) -> 9.5555556 | K12: =SUMIF(entradas26[CODIGO],haier26[[#This Row],[CODIGO ]],entradas26[[CAN JUEGOS ]]) -> 20 | L12: =SUMIF(entradas26[CODIGO],haier26[[#This Row],[CODIGO ]],entradas26[CAN BARRAS]) -> 0 | M12: =SUMIF(salidas26[[CODIGO ]],haier26[[#This Row],[CODIGO ]],salidas26[[CANT JUEGOS ]]) -> 2 | N12: =SUMIF(salidas26[[CODIGO ]],haier26[[#This Row],[CODIGO ]],salidas26[CANT BARRAS]) -> 0 | O12: =(haier26[[#This Row],["J"PRECIO COMPRA ]]*haier26[[#This Row],[STOCK JUEGOS]]) -> 2150 | P12: =(haier26[[#This Row],["J" PRECIO VENTA ]]*haier26[[#This Row],[STOCK JUEGOS]]) -> 6250 | Q12: =(haier26[[#This Row],["B"PRECIO COMPRA]]*haier26[[#This Row],[STOCK BARRAS]]) -> 0 | R12: =(haier26[[#This Row],["B"PRECIO VENTA ]]*haier26[[#This Row],[STOCK BARRAS]]) -> 0 | S12: 7 | U12: 4.5 | V12: XLM - 2088/2089
A13: 9 | B13: 3021 | C13: 49 U6500 3V/6L/12B | D13: =(haier26[[#This Row],[CANTIDAD INICIAL JUEGO ]]+haier26[[#This Row],[ENTRADAS JUEGOS ]]-haier26[[#This Row],[SALIDAS JUEGOS]]) -> 0 | E13: =(haier26[[#This Row],[CANTIDAD INICIAL BARRAS]]+haier26[[#This Row],[ENTRADAS BARRAS]]-haier26[[#This Row],[SALIDA BARRAS]]) -> 0 | F13: 250 | G13: 210 | H13: 12 | I13: =(haier26[[#This Row],["J" PRECIO VENTA ]]/haier26[[#This Row],[BARRAS]]) -> 20.833333 | J13: =(haier26[[#This Row],["J"PRECIO COMPRA ]]/haier26[[#This Row],[BARRAS]]) -> 17.5 | K13: =SUMIF(entradas26[CODIGO],haier26[[#This Row],[CODIGO ]],entradas26[[CAN JUEGOS ]]) -> 0 | L13: =SUMIF(entradas26[CODIGO],haier26[[#This Row],[CODIGO ]],entradas26[CAN BARRAS]) -> 0 | M13: =SUMIF(salidas26[[CODIGO ]],haier26[[#This Row],[CODIGO ]],salidas26[[CANT JUEGOS ]]) -> 0 | N13: =SUMIF(salidas26[[CODIGO ]],haier26[[#This Row],[CODIGO ]],salidas26[CANT BARRAS]) -> 0 | O13: =(haier26[[#This Row],["J"PRECIO COMPRA ]]*haier26[[#This Row],[STOCK JUEGOS]]) -> 0 | P13: =(haier26[[#This Row],["J" PRECIO VENTA ]]*haier26[[#This Row],[STOCK JUEGOS]]) -> 0 | Q13: =(haier26[[#This Row],["B"PRECIO COMPRA]]*haier26[[#This Row],[STOCK BARRAS]]) -> 0 | R13: =(haier26[[#This Row],["B"PRECIO VENTA ]]*haier26[[#This Row],[STOCK BARRAS]]) -> 0 | S13: 0 | T13: 0
A14: 10 | B14: 3024 | C14: 50M600D 7L/10B | D14: =(haier26[[#This Row],[CANTIDAD INICIAL JUEGO ]]+haier26[[#This Row],[ENTRADAS JUEGOS ]]-haier26[[#This Row],[SALIDAS JUEGOS]]) -> 0 | E14: =(haier26[[#This Row],[CANTIDAD INICIAL BARRAS]]+haier26[[#This Row],[ENTRADAS BARRAS]]-haier26[[#This Row],[SALIDA BARRAS]]) -> 0 | F14: 280 | G14: 120 | H14: 10 | I14: =(haier26[[#This Row],["J" PRECIO VENTA ]]/haier26[[#This Row],[BARRAS]]) -> 28 | J14: =(haier26[[#This Row],["J"PRECIO COMPRA ]]/haier26[[#This Row],[BARRAS]]) -> 12 | K14: =SUMIF(entradas26[CODIGO],haier26[[#This Row],[CODIGO ]],entradas26[[CAN JUEGOS ]]) -> 0 | L14: =SUMIF(entradas26[CODIGO],haier26[[#This Row],[CODIGO ]],entradas26[CAN BARRAS]) -> 0 | M14: =SUMIF(salidas26[[CODIGO ]],haier26[[#This Row],[CODIGO ]],salidas26[[CANT JUEGOS ]]) -> 0 | N14: =SUMIF(salidas26[[CODIGO ]],haier26[[#This Row],[CODIGO ]],salidas26[CANT BARRAS]) -> 0 | O14: =(haier26[[#This Row],["J"PRECIO COMPRA ]]*haier26[[#This Row],[STOCK JUEGOS]]) -> 0 | P14: =(haier26[[#This Row],["J" PRECIO VENTA ]]*haier26[[#This Row],[STOCK JUEGOS]]) -> 0 | Q14: =(haier26[[#This Row],["B"PRECIO COMPRA]]*haier26[[#This Row],[STOCK BARRAS]]) -> 0 | R14: =(haier26[[#This Row],["B"PRECIO VENTA ]]*haier26[[#This Row],[STOCK BARRAS]]) -> 0 | S14: 0 | T14: 0
A15: 11 | B15: 3027 | C15: 50U6600 5L/9B | D15: =(haier26[[#This Row],[CANTIDAD INICIAL JUEGO ]]+haier26[[#This Row],[ENTRADAS JUEGOS ]]-haier26[[#This Row],[SALIDAS JUEGOS]]) -> 8 | E15: =(haier26[[#This Row],[CANTIDAD INICIAL BARRAS]]+haier26[[#This Row],[ENTRADAS BARRAS]]-haier26[[#This Row],[SALIDA BARRAS]]) -> 8 | F15: 280 | G15: 84 | H15: 9 | I15: =(haier26[[#This Row],["J" PRECIO VENTA ]]/haier26[[#This Row],[BARRAS]]) -> 31.111111 | J15: =(haier26[[#This Row],["J"PRECIO COMPRA ]]/haier26[[#This Row],[BARRAS]]) -> 9.3333333 | K15: =SUMIF(entradas26[CODIGO],haier26[[#This Row],[CODIGO ]],entradas26[[CAN JUEGOS ]]) -> 0 | L15: =SUMIF(entradas26[CODIGO],haier26[[#This Row],[CODIGO ]],entradas26[CAN BARRAS]) -> 0 | M15: =SUMIF(salidas26[[CODIGO ]],haier26[[#This Row],[CODIGO ]],salidas26[[CANT JUEGOS ]]) -> 1 | N15: =SUMIF(salidas26[[CODIGO ]],haier26[[#This Row],[CODIGO ]],salidas26[CANT BARRAS]) -> 0 | O15: =(haier26[[#This Row],["J"PRECIO COMPRA ]]*haier26[[#This Row],[STOCK JUEGOS]]) -> 672 | P15: =(haier26[[#This Row],["J" PRECIO VENTA ]]*haier26[[#This Row],[STOCK JUEGOS]]) -> 2240 | Q15: =(haier26[[#This Row],["B"PRECIO COMPRA]]*haier26[[#This Row],[STOCK BARRAS]]) -> 74.666667 | R15: =(haier26[[#This Row],["B"PRECIO VENTA ]]*haier26[[#This Row],[STOCK BARRAS]]) -> 248.88889 | S15: 9 | T15: 8
A16: 12 | B16: 3028 | C16: 55U6500 8L/14B | D16: =(haier26[[#This Row],[CANTIDAD INICIAL JUEGO ]]+haier26[[#This Row],[ENTRADAS JUEGOS ]]-haier26[[#This Row],[SALIDAS JUEGOS]]) -> 7 | E16: =(haier26[[#This Row],[CANTIDAD INICIAL BARRAS]]+haier26[[#This Row],[ENTRADAS BARRAS]]-haier26[[#This Row],[SALIDA BARRAS]]) -> 0 | F16: 350 | G16: 206 | H16: 14 | I16: =(haier26[[#This Row],["J" PRECIO VENTA ]]/haier26[[#This Row],[BARRAS]]) -> 25 | J16: =(haier26[[#This Row],["J"PRECIO COMPRA ]]/haier26[[#This Row],[BARRAS]]) -> 14.714286 | K16: =SUMIF(entradas26[CODIGO],haier26[[#This Row],[CODIGO ]],entradas26[[CAN JUEGOS ]]) -> 0 | L16: =SUMIF(entradas26[CODIGO],haier26[[#This Row],[CODIGO ]],entradas26[CAN BARRAS]) -> 0 | M16: =SUMIF(salidas26[[CODIGO ]],haier26[[#This Row],[CODIGO ]],salidas26[[CANT JUEGOS ]]) -> 2 | N16: =SUMIF(salidas26[[CODIGO ]],haier26[[#This Row],[CODIGO ]],salidas26[CANT BARRAS]) -> 0 | O16: =(haier26[[#This Row],["J"PRECIO COMPRA ]]*haier26[[#This Row],[STOCK JUEGOS]]) -> 1442 | P16: =(haier26[[#This Row],["J" PRECIO VENTA ]]*haier26[[#This Row],[STOCK JUEGOS]]) -> 2450 | Q16: =(haier26[[#This Row],["B"PRECIO COMPRA]]*haier26[[#This Row],[STOCK BARRAS]]) -> 0 | R16: =(haier26[[#This Row],["B"PRECIO VENTA ]]*haier26[[#This Row],[STOCK BARRAS]]) -> 0 | S16: 9
A17: 13 | B17: 3030 | C17: 55 B8500 10L/14B | D17: =(haier26[[#This Row],[CANTIDAD INICIAL JUEGO ]]+haier26[[#This Row],[ENTRADAS JUEGOS ]]-haier26[[#This Row],[SALIDAS JUEGOS]]) -> 18 | E17: =(haier26[[#This Row],[CANTIDAD INICIAL BARRAS]]+haier26[[#This Row],[ENTRADAS BARRAS]]-haier26[[#This Row],[SALIDA BARRAS]]) -> 0 | F17: 320 | G17: 259 | H17: 14 | I17: =(haier26[[#This Row],["J" PRECIO VENTA ]]/haier26[[#This Row],[BARRAS]]) -> 22.857143 | J17: =(haier26[[#This Row],["J"PRECIO COMPRA ]]/haier26[[#This Row],[BARRAS]]) -> 18.5 | K17: =SUMIF(entradas26[CODIGO],haier26[[#This Row],[CODIGO ]],entradas26[[CAN JUEGOS ]]) -> 0 | L17: =SUMIF(entradas26[CODIGO],haier26[[#This Row],[CODIGO ]],entradas26[CAN BARRAS]) -> 0 | M17: =SUMIF(salidas26[[CODIGO ]],haier26[[#This Row],[CODIGO ]],salidas26[[CANT JUEGOS ]]) -> 1 | N17: =SUMIF(salidas26[[CODIGO ]],haier26[[#This Row],[CODIGO ]],salidas26[CANT BARRAS]) -> 0 | O17: =(haier26[[#This Row],["J"PRECIO COMPRA ]]*haier26[[#This Row],[STOCK JUEGOS]]) -> 4662 | P17: =(haier26[[#This Row],["J" PRECIO VENTA ]]*haier26[[#This Row],[STOCK JUEGOS]]) -> 5760 | Q17: =(haier26[[#This Row],["B"PRECIO COMPRA]]*haier26[[#This Row],[STOCK BARRAS]]) -> 0 | R17: =(haier26[[#This Row],["B"PRECIO VENTA ]]*haier26[[#This Row],[STOCK BARRAS]]) -> 0 | S17: 19
A18: 14 | B18: 3033 | C18: 55B8000 14B/2B DE 8L Y 12B DE 7L | D18: =(haier26[[#This Row],[CANTIDAD INICIAL JUEGO ]]+haier26[[#This Row],[ENTRADAS JUEGOS ]]-haier26[[#This Row],[SALIDAS JUEGOS]]) -> 3 | E18: =(haier26[[#This Row],[CANTIDAD INICIAL BARRAS]]+haier26[[#This Row],[ENTRADAS BARRAS]]-haier26[[#This Row],[SALIDA BARRAS]]) -> 7 | F18: 320 | G18: 124 | H18: 14 | I18: =(haier26[[#This Row],["J" PRECIO VENTA ]]/haier26[[#This Row],[BARRAS]]) -> 22.857143 | J18: =(haier26[[#This Row],["J"PRECIO COMPRA ]]/haier26[[#This Row],[BARRAS]]) -> 8.8571429 | K18: =SUMIF(entradas26[CODIGO],haier26[[#This Row],[CODIGO ]],entradas26[[CAN JUEGOS ]]) -> 0 | L18: =SUMIF(entradas26[CODIGO],haier26[[#This Row],[CODIGO ]],entradas26[CAN BARRAS]) -> 0 | M18: =SUMIF(salidas26[[CODIGO ]],haier26[[#This Row],[CODIGO ]],salidas26[[CANT JUEGOS ]]) -> 4 | N18: =SUMIF(salidas26[[CODIGO ]],haier26[[#This Row],[CODIGO ]],salidas26[CANT BARRAS]) -> 0 | O18: =(haier26[[#This Row],["J"PRECIO COMPRA ]]*haier26[[#This Row],[STOCK JUEGOS]]) -> 372 | P18: =(haier26[[#This Row],["J" PRECIO VENTA ]]*haier26[[#This Row],[STOCK JUEGOS]]) -> 960 | Q18: =(haier26[[#This Row],["B"PRECIO COMPRA]]*haier26[[#This Row],[STOCK BARRAS]]) -> 62 | R18: =(haier26[[#This Row],["B"PRECIO VENTA ]]*haier26[[#This Row],[STOCK BARRAS]]) -> 160 | S18: 7 | T18: 7
A19: 15 | B19: 3036 | C19: 55M600D 8L/12B | D19: =(haier26[[#This Row],[CANTIDAD INICIAL JUEGO ]]+haier26[[#This Row],[ENTRADAS JUEGOS ]]-haier26[[#This Row],[SALIDAS JUEGOS]]) -> 13 | E19: =(haier26[[#This Row],[CANTIDAD INICIAL BARRAS]]+haier26[[#This Row],[ENTRADAS BARRAS]]-haier26[[#This Row],[SALIDA BARRAS]]) -> 8 | F19: 350 | G19: 250 | H19: 12 | I19: =(haier26[[#This Row],["J" PRECIO VENTA ]]/haier26[[#This Row],[BARRAS]]) -> 29.166667 | J19: =(haier26[[#This Row],["J"PRECIO COMPRA ]]/haier26[[#This Row],[BARRAS]]) -> 20.833333 | K19: =SUMIF(entradas26[CODIGO],haier26[[#This Row],[CODIGO ]],entradas26[[CAN JUEGOS ]]) -> 0 | L19: =SUMIF(entradas26[CODIGO],haier26[[#This Row],[CODIGO ]],entradas26[CAN BARRAS]) -> 0 | M19: =SUMIF(salidas26[[CODIGO ]],haier26[[#This Row],[CODIGO ]],salidas26[[CANT JUEGOS ]]) -> 1 | N19: =SUMIF(salidas26[[CODIGO ]],haier26[[#This Row],[CODIGO ]],salidas26[CANT BARRAS]) -> 0 | O19: =(haier26[[#This Row],["J"PRECIO COMPRA ]]*haier26[[#This Row],[STOCK JUEGOS]]) -> 3250 | P19: =(haier26[[#This Row],["J" PRECIO VENTA ]]*haier26[[#This Row],[STOCK JUEGOS]]) -> 4550 | Q19: =(haier26[[#This Row],["B"PRECIO COMPRA]]*haier26[[#This Row],[STOCK BARRAS]]) -> 166.66667 | R19: =(haier26[[#This Row],["B"PRECIO VENTA ]]*haier26[[#This Row],[STOCK BARRAS]]) -> 233.33333 | S19: 14 | T19: 8
A20: 16 | B20: 3040 | C20: 65 HAIER LE65U6500DUA | D20: =(haier26[[#This Row],[CANTIDAD INICIAL JUEGO ]]+haier26[[#This Row],[ENTRADAS JUEGOS ]]-haier26[[#This Row],[SALIDAS JUEGOS]]) -> 18 | E20: =(haier26[[#This Row],[CANTIDAD INICIAL BARRAS]]+haier26[[#This Row],[ENTRADAS BARRAS]]-haier26[[#This Row],[SALIDA BARRAS]]) -> 0 | F20: 450 | G20: 335 | H20: 16 | I20: =(haier26[[#This Row],["J" PRECIO VENTA ]]/haier26[[#This Row],[BARRAS]]) -> 28.125 | J20: =(haier26[[#This Row],["J"PRECIO COMPRA ]]/haier26[[#This Row],[BARRAS]]) -> 20.9375 | K20: =SUMIF(entradas26[CODIGO],haier26[[#This Row],[CODIGO ]],entradas26[[CAN JUEGOS ]]) -> 0 | L20: =SUMIF(entradas26[CODIGO],haier26[[#This Row],[CODIGO ]],entradas26[CAN BARRAS]) -> 0 | M20: =SUMIF(salidas26[[CODIGO ]],haier26[[#This Row],[CODIGO ]],salidas26[[CANT JUEGOS ]]) -> 2 | N20: =SUMIF(salidas26[[CODIGO ]],haier26[[#This Row],[CODIGO ]],salidas26[CANT BARRAS]) -> 0 | O20: =(haier26[[#This Row],["J"PRECIO COMPRA ]]*haier26[[#This Row],[STOCK JUEGOS]]) -> 6030 | P20: =(haier26[[#This Row],["J" PRECIO VENTA ]]*haier26[[#This Row],[STOCK JUEGOS]]) -> 8100 | Q20: =(haier26[[#This Row],["B"PRECIO COMPRA]]*haier26[[#This Row],[STOCK BARRAS]]) -> 0 | R20: =(haier26[[#This Row],["B"PRECIO VENTA ]]*haier26[[#This Row],[STOCK BARRAS]]) -> 0 | S20: 20

Sheet DAEWOO
B2: DAEWOO
B4: CODIGO | C4: DESCRIPCION | D4: STOCK JUEGOS | E4: STOCK BARRAS | F4: "J" PRECIO VENTA | G4: "J"PRECIO COMPRA | H4: BARRAS | I4: "B"PRECIO VENTA | J4: "B"PRECIO COMPRA | K4: ENTRADAS JUEGOS | L4: ENTRADAS BARRAS | M4: SALIDAS JUEGOS | N4: SALIDA BARRAS | O4: CAPITAL JUEGOS | P4: CAPITAL/GANANCIA/JUEGOS | Q4: CAPITAL BARRA | R4: CAP GAN BARRAS | S4: CANTIDAD INICIAL JUEGO | T4: CANTIDAD INICIAL BARRAS | U4: PRECIO EN $ | V4: CODIGO 2 | W4: CODIGO 3
A5: 1 | B5: 4000 | C5: 32 DAEWO V780-TCL 5L/6V -2B MI L32M5-5ASP | D5: =(daewoo26[[#This Row],[CANTIDAD INICIAL JUEGO ]]+daewoo26[[#This Row],[ENTRADAS JUEGOS ]]-daewoo26[[#This Row],[SALIDAS JUEGOS]]) -> 17 | E5: =(daewoo26[[#This Row],[CANTIDAD INICIAL BARRAS]]+daewoo26[[#This Row],[ENTRADAS BARRAS]]-daewoo26[[#This Row],[SALIDA BARRAS]]) -> 0 | F5: 60 | G5: 21 | H5: 2 | I5: =(daewoo26[[#This Row],["J" PRECIO VENTA ]]/daewoo26[[#This Row],[BARRAS]]) -> 30 | J5: =(daewoo26[[#This Row],["J"PRECIO COMPRA ]]/daewoo26[[#This Row],[BARRAS]]) -> 10.5 | K5: =SUMIF(entradas26[CODIGO],daewoo26[[#This Row],[CODIGO ]],entradas26[[CAN JUEGOS ]]) -> 20 | L5: =SUMIF(entradas26[CODIGO],daewoo26[[#This Row],[CODIGO ]],entradas26[CAN BARRAS]) -> 0 | M5: =SUMIF(salidas26[[CODIGO ]],daewoo26[[#This Row],[CODIGO ]],salidas26[[CANT JUEGOS ]]) -> 21 | N5: =SUMIF(salidas26[[CODIGO ]],daewoo26[[#This Row],[CODIGO ]],salidas26[CANT BARRAS]) -> 0 | O5: =(daewoo26[[#This Row],["J"PRECIO COMPRA ]]*daewoo26[[#This Row],[STOCK JUEGOS]]) -> 357 | P5: =(daewoo26[[#This Row],["J" PRECIO VENTA ]]*daewoo26[[#This Row],[STOCK JUEGOS]]) -> 1020 | Q5: =(daewoo26[[#This Row],["B"PRECIO COMPRA]]*daewoo26[[#This Row],[STOCK BARRAS]]) -> 0 | R5: =(daewoo26[[#This Row],["B"PRECIO VENTA ]]*daewoo26[[#This Row],[STOCK BARRAS]]) -> 0 | S5: 18 | U5: 1.3 | V5: XLM-0214
A6: 2 | B6: 4002 | C6: 32 DAEWO S780 6L/6V -2B | D6: =(daewoo26[[#This Row],[CANTIDAD INICIAL JUEGO ]]+daewoo26[[#This Row],[ENTRADAS JUEGOS ]]-daewoo26[[#This Row],[SALIDAS JUEGOS]]) -> 28 | E6: =(daewoo26[[#This Row],[CANTIDAD INICIAL BARRAS]]+daewoo26[[#This Row],[ENTRADAS BARRAS]]-daewoo26[[#This Row],[SALIDA BARRAS]]) -> 0 | F6: 60 | G6: 35 | H6: 2 | I6: =(daewoo26[[#This Row],["J" PRECIO VENTA ]]/daewoo26[[#This Row],[BARRAS]]) -> 30 | J6: =(daewoo26[[#This Row],["J"PRECIO COMPRA ]]/daewoo26[[#This Row],[BARRAS]]) -> 17.5 | K6: =SUMIF(entradas26[CODIGO],daewoo26[[#This Row],[CODIGO ]],entradas26[[CAN JUEGOS ]]) -> 20 | L6: =SUMIF(entradas26[CODIGO],daewoo26[[#This Row],[CODIGO ]],entradas26[CAN BARRAS]) -> 0 | M6: =SUMIF(salidas26[[CODIGO ]],daewoo26[[#This Row],[CODIGO ]],salidas26[[CANT JUEGOS ]]) -> 2 | N6: =SUMIF(salidas26[[CODIGO ]],daewoo26[[#This Row],[CODIGO ]],salidas26[CANT BARRAS]) -> 0 | O6: =(daewoo26[[#This Row],["J"PRECIO COMPRA ]]*daewoo26[[#This Row],[STOCK JUEGOS]]) -> 980 | P6: =(daewoo26[[#This Row],["J" PRECIO VENTA ]]*daewoo26[[#This Row],[STOCK JUEGOS]]) -> 1680 | Q6: =(daewoo26[[#This Row],["B"PRECIO COMPRA]]*daewoo26[[#This Row],[STOCK BARRAS]]) -> 0 | R6: =(daewoo26[[#This Row],["B"PRECIO VENTA ]]*daewoo26[[#This Row],[STOCK BARRAS]]) -> 0 | S6: 10 | U6: 1.5 | V6: XLM-0099
A7: 3 | B7: 4003 | C7: 32 DAEWOO 8L/3V - 3B | D7: =(daewoo26[[#This Row],[CANTIDAD INICIAL JUEGO ]]+daewoo26[[#This Row],[ENTRADAS JUEGOS ]]-daewoo26[[#This Row],[SALIDAS JUEGOS]]) -> 16 | E7: =(daewoo26[[#This Row],[CANTIDAD INICIAL BARRAS]]+daewoo26[[#This Row],[ENTRADAS BARRAS]]-daewoo26[[#This Row],[SALIDA BARRAS]]) -> 1 | F7: 90 | G7: 35 | H7: 3 | I7: =(daewoo26[[#This Row],["J" PRECIO VENTA ]]/daewoo26[[#This Row],[BARRAS]]) -> 30 | J7: =(daewoo26[[#This Row],["J"PRECIO COMPRA ]]/daewoo26[[#This Row],[BARRAS]]) -> 11.666667 | K7: =SUMIF(entradas26[CODIGO],daewoo26[[#This Row],[CODIGO ]],entradas26[[CAN JUEGOS ]]) -> 0 | L7: =SUMIF(entradas26[CODIGO],daewoo26[[#This Row],[CODIGO ]],entradas26[CAN BARRAS]) -> 0 | M7: =SUMIF(salidas26[[CODIGO ]],daewoo26[[#This Row],[CODIGO ]],salidas26[[CANT JUEGOS ]]) -> 11 | N7: =SUMIF(salidas26[[CODIGO ]],daewoo26[[#This Row],[CODIGO ]],salidas26[CANT BARRAS]) -> 1 | O7: =(daewoo26[[#This Row],["J"PRECIO COMPRA ]]*daewoo26[[#This Row],[STOCK JUEGOS]]) -> 560 | P7: =(daewoo26[[#This Row],["J" PRECIO VENTA ]]*daewoo26[[#This Row],[STOCK JUEGOS]]) -> 1440 | Q7: =(daewoo26[[#This Row],["B"PRECIO COMPRA]]*daewoo26[[#This Row],[STOCK BARRAS]]) -> 11.666667 | R7: =(daewoo26[[#This Row],["B"PRECIO VENTA ]]*daewoo26[[#This Row],[STOCK BARRAS]]) -> 30 | S7: 27 | T7: 2 | U7: 1.9 | V7: XLM-0084
A8: 4 | B8: 4009 | C8: 43-DAEWO L43R630BKS/ 8B | D8: =(daewoo26[[#This Row],[CANTIDAD INICIAL JUEGO ]]+daewoo26[[#This Row],[ENTRADAS JUEGOS ]]-daewoo26[[#This Row],[SALIDAS JUEGOS]]) -> 30 | E8: =(daewoo26[[#This Row],[CANTIDAD INICIAL BARRAS]]+daewoo26[[#This Row],[ENTRADAS BARRAS]]-daewoo26[[#This Row],[SALIDA BARRAS]]) -> 3 | F8: 160 | G8: 67 | H8: 8 | I8: =(daewoo26[[#This Row],["J" PRECIO VENTA ]]/daewoo26[[#This Row],[BARRAS]]) -> 20 | J8: =(daewoo26[[#This Row],["J"PRECIO COMPRA ]]/daewoo26[[#This Row],[BARRAS]]) -> 8.375 | K8: =SUMIF(entradas26[CODIGO],daewoo26[[#This Row],[CODIGO ]],entradas26[[CAN JUEGOS ]]) -> 20 | L8: =SUMIF(entradas26[CODIGO],daewoo26[[#This Row],[CODIGO ]],entradas26[CAN BARRAS]) -> 0 | M8: =SUMIF(salidas26[[CODIGO ]],daewoo26[[#This Row],[CODIGO ]],salidas26[[CANT JUEGOS ]]) -> 7 | N8: =SUMIF(salidas26[[CODIGO ]],daewoo26[[#This Row],[CODIGO ]],salidas26[CANT BARRAS]) -> 0 | O8: =(daewoo26[[#This Row],["J"PRECIO COMPRA ]]*daewoo26[[#This Row],[STOCK JUEGOS]]) -> 2010 | P8: =(daewoo26[[#This Row],["J" PRECIO VENTA ]]*daewoo26[[#This Row],[STOCK JUEGOS]]) -> 4800 | Q8: =(daewoo26[[#This Row],["B"PRECIO COMPRA]]*daewoo26[[#This Row],[STOCK BARRAS]]) -> 25.125 | R8: =(daewoo26[[#This Row],["B"PRECIO VENTA ]]*daewoo26[[#This Row],[STOCK BARRAS]]) -> 60 | S8: 17 | T8: 3 | U8: 3.5 | V8: XLM-0218
A9: 5 | B9: 4010 | C9: 43 DAEWO S780 3B/8LED/3V | D9: =(daewoo26[[#This Row],[CANTIDAD INICIAL JUEGO ]]+daewoo26[[#This Row],[ENTRADAS JUEGOS ]]-daewoo26[[#This Row],[SALIDAS JUEGOS]]) -> 12 | E9: =(daewoo26[[#This Row],[CANTIDAD INICIAL BARRAS]]+daewoo26[[#This Row],[ENTRADAS BARRAS]]-daewoo26[[#This Row],[SALIDA BARRAS]]) -> 1 | F9: 160 | G9: 44 | H9: 3 | I9: =(daewoo26[[#This Row],["J" PRECIO VENTA ]]/daewoo26[[#This Row],[BARRAS]]) -> 53.333333 | J9: =(daewoo26[[#This Row],["J"PRECIO COMPRA ]]/daewoo26[[#This Row],[BARRAS]]) -> 14.666667 | K9: =SUMIF(entradas26[CODIGO],daewoo26[[#This Row],[CODIGO ]],entradas26[[CAN JUEGOS ]]) -> 0 | L9: =SUMIF(entradas26[CODIGO],daewoo26[[#This Row],[CODIGO ]],entradas26[CAN BARRAS]) -> 3 | M9: =SUMIF(salidas26[[CODIGO ]],daewoo26[[#This Row],[CODIGO ]],salidas26[[CANT JUEGOS ]]) -> 6 | N9: =SUMIF(salidas26[[CODIGO ]],daewoo26[[#This Row],[CODIGO ]],salidas26[CANT BARRAS]) -> 3 | O9: =(daewoo26[[#This Row],["J"PRECIO COMPRA ]]*daewoo26[[#This Row],[STOCK JUEGOS]]) -> 528 | P9: =(daewoo26[[#This Row],["J" PRECIO VENTA ]]*daewoo26[[#This Row],[STOCK JUEGOS]]) -> 1920 | Q9: =(daewoo26[[#This Row],["B"PRECIO COMPRA]]*daewoo26[[#This Row],[STOCK BARRAS]]) -> 14.666667 | R9: =(daewoo26[[#This Row],["B"PRECIO VENTA ]]*daewoo26[[#This Row],[STOCK BARRAS]]) -> 53.333333 | S9: 18 | T9: 1 | U9: 1.75 | V9: XLM-0156 | W9: JL.D43081330-140FS-M
